Workbook

Sheet Income Statement
A1: Ticker | B1: FY | C1: Total Revenue | D1: Cost of Revenue | E1: Gross Profit | F1: SG&A | G1: R&D | H1: D&A | I1: Unusual Expense | J1: Other Operating Expenses | K1: Total Operating Expense | L1: Operating Income | M1: Interest Inc.(Exp) | N1: Gain (Loss) on Sale of Assets | O1: Other | P1: Net Income Before Taxes | Q1: Provision for Income Taxes | R1: Net Income | S1: Basic EPS Excluding Extraordinary Items | T1: Basic EPS Including Extraordinary Items | U1: Normalized Basic EPS | V1: Basic Weighted Average Shares | W1: Diluted EPS Excluding ExtraOrd Items | X1: Diluted EPS Including ExtraOrd Items | Y1: Normalized Diluted EPS | Z1: Diluted Weighted Average Shares | AA1: Dividends Per Share | AB1: Number of Employees
A2: AMZN | B2: 46022 | C2: 716924 | D2: 356414 | E2: 360510 | F2: 167375 | G2: 108521 | H2: 817 | I2: 4900 | J2: -1078 | K2: 636949 | L2: 79975 | M2: 9165 | O2: 8171 | P2: 97311 | Q2: 19087 | R2: 77670 | S2: 7.29 | T2: 7.29 | U2: 7.96 | V2: 10656 | W2: 7.17 | X2: 7.17 | Y2: 7.83 | Z2: 10827 | AB2: 1576000
A3: AMZN | B3: 45657 | C3: 637959 | D3: 326288 | E3: 311671 | F3: 153771 | G3: 88544 | H3: 838 | I3: -75 | K3: 569366 | L3: 68593 | M3: 585 | O3: -564 | P3: 68614 | Q3: 9265 | R3: 59248 | S3: 5.66 | T3: 5.66 | U3: 5.65 | V3: 10473 | W3: 5.53 | X3: 5.53 | Y3: 5.52 | Z3: 10721 | AB3: 1556000
A4: AMZN | B4: 45291 | C4: 574785 | D4: 304739 | E4: 270046 | F4: 146805 | G4: 85622 | H4: 706 | I4: 61 | K4: 537933 | L4: 36852 | M4: 816 | O4: -111 | P4: 37557 | Q4: 7120 | R4: 30425 | S4: 2.95 | T4: 2.95 | U4: 2.96 | V4: 10304 | W4: 2.9 | X4: 2.9 | Y4: 2.9 | Z4: 10492 | AB4: 1525000
A5: AMZN | B5: 44926 | C5: 513983 | D5: 288831 | E5: 225152 | F5: 138428 | G5: 73213 | H5: 604 | I5: 1100 | J5: -441 | K5: 501735 | L5: 12248 | M5: -15588 | O5: -2596 | P5: -5936 | Q5: -3217 | R5: -2722 | S5: -0.27 | T5: -0.27 | U5: -0.2 | V5: 10189 | W5: -0.27 | X5: -0.27 | Y5: -0.2 | Z5: 10189 | AB5: 1541000
A6: AMZN | B6: 44561 | C6: 469822 | D6: 272344 | E6: 197478 | F6: 116485 | G6: 56052 | H6: 512 | J6: -450 | K6: 444943 | L6: 24879 | M6: 10110 | O6: 3162 | P6: 38151 | Q6: 4791 | R6: 33364 | S6: 3.3 | T6: 3.3 | U6: 3.3 | V6: 10120 | W6: 3.24 | X6: 3.24 | Y6: 3.24 | Z6: 10300 | AB6: 1608000
A7: AMZN | B7: 44196 | C7: 386064 | D7: 233307 | E7: 152757 | F7: 87193 | G7: 42740 | H7: 509 | J7: -584 | K7: 363165 | L7: 22899 | M7: -224 | O7: 1503 | P7: 24178 | Q7: 2863 | R7: 21331 | S7: 2.13 | T7: 2.13 | U7: 3.15 | V7: 10000 | W7: 2.09 | X7: 2.09 | Y7: 3.09 | Z7: 10200 | AB7: 1298000
A8: AMZN | B8: 43830 | C8: 280522 | D8: 165536 | E8: 114986 | F8: 64313 | G8: 35931 | H8: 565 | J8: -364 | K8: 265981 | L8: 14541 | M8: -557 | O8: -8 | P8: 13976 | Q8: 2374 | R8: 11588 | S8: 1.17 | T8: 1.17 | U8: 1.17 | V8: 9880 | W8: 1.15 | X8: 1.15 | Y8: 1.15 | Z8: 10080 | AB8: 798000
A9: AMZN | B9: 43465 | C9: 232887 | D9: 139156 | E9: 93731 | F9: 52177 | G9: 28837 | H9: 475 | J9: -179 | K9: 220466 | L9: 12421 | M9: -977 | O9: -183 | P9: 11261 | Q9: 1354 | R9: 10073 | S9: 1.02 | T9: 1.03 | U9: 1.02 | V9: 9740 | W9: 0.99 | X9: 1.01 | Y9: 0.99 | Z9: 10000 | AB9: 647500
A10: AMZN | B10: 43100 | C10: 177866 | D10: 111934 | E10: 65932 | F10: 38992 | G10: 22620 | H10: 366 | J10: -152 | K10: 173760 | L10: 4106 | M10: -406 | O10: 106 | P10: 3806 | Q10: 1558 | R10: 3033 | S10: 0.23 | T10: 0.32 | U10: 0.23 | V10: 9600 | W10: 0.23 | X10: 0.31 | Y10: 0.23 | Z10: 9860 | AB10: 566000
A11: AMZN | B11: 42735 | C11: 135987 | D11: 88265 | E11: 47722 | F11: 27284 | G11: 16085 | H11: 287 | J11: -120 | K11: 131801 | L11: 4186 | M11: -371 | O11: 77 | P11: 3892 | Q11: 1425 | R11: 2371 | S11: 0.25 | T11: 0.25 | U11: 0.25 | V11: 9480 | W11: 0.24 | X11: 0.24 | Y11: 0.24 | Z11: 9680 | AA11: 0 | AB11: 341400
A12: AMZN | B12: 42369 | C12: 107006 | D12: 71651 | E12: 35355 | F12: 20411 | G12: 12540 | H12: 228 | J12: -57 | K12: 104773 | L12: 2233 | M12: -680 | O12: 15 | P12: 1568 | Q12: 950 | R12: 596 | S12: 0.06 | T12: 0.06 | U12: 0.06 | V12: 9340 | W12: 0.06 | X12: 0.06 | Y12: 0.06 | Z12: 9540 | AB12: 230800
A13: AMZN | B13: 42004 | C13: 88988 | D13: 62752 | E13: 26236 | F13: 16650 | G13: 9275 | H13: 181 | J13: -48 | K13: 88810 | L13: 178 | M13: -295 | O13: 6 | P13: -111 | Q13: 167 | R13: -241 | S13: -0.03 | T13: -0.03 | U13: -0.03 | V13: 9240 | W13: -0.03 | X13: -0.03 | Y13: -0.03 | Z13: 9240 | AB13: 154100
A14: AMZN | B14: 41639 | C14: 74452 | D14: 54181 | E14: 20271 | F14: 12847 | G14: 6565 | H14: 168 | J14: -54 | K14: 73707 | L14: 745 | M14: -241 | O14: 2 | P14: 506 | Q14: 161 | R14: 274 | S14: 0.03 | T14: 0.03 | U14: 0.03 | V14: 9140 | W14: 0.03 | X14: 0.03 | Y14: 0.03 | Z14: 9300 | AA14: 0 | AB14: 117300
A15: AMZN | B15: 41274 | C15: 61093 | D15: 45971 | E15: 15122 | F15: 9723 | G15: 4564 | J15: 159 | K15: 60417 | L15: 676 | M15: -137 | O15: 5 | P15: 544 | Q15: 428 | R15: -39 | S15: 0 | T15: 0 | U15: 0 | V15: 9060 | W15: 0 | X15: 0 | Y15: 0 | Z15: 9060 | AA15: 0 | AB15: 88400
A16: AMZN | B16: 40908 | C16: 48077 | D16: 37288 | E16: 10789 | F16: 6864 | G16: 2909 | J16: 154 | K16: 47215 | L16: 862 | M16: 64 | O16: 8 | P16: 934 | Q16: 291 | R16: 631 | S16: 0.07 | T16: 0.07 | U16: 0.07 | V16: 9060 | W16: 0.07 | X16: 0.07 | Y16: 0.07 | Z16: 9220 | AA16: 0 | AB16: 56200
A17: AMZN | B17: 40543 | C17: 34204 | D17: 26561 | E17: 7643 | F17: 4397 | G17: 1734 | J17: 106 | K17: 32798 | L17: 1406 | M17: 88 | O17: 3 | P17: 1497 | Q17: 352 | R17: 1152 | S17: 0.13 | T17: 0.13 | U17: 0.13 | V17: 8940 | W17: 0.13 | X17: 0.13 | Y17: 0.13 | Z17: 9120 | AA17: 0 | AB17: 33700
A18: AMZN | B18: 40178 | C18: 24509 | D18: 18978 | E18: 5531 | F18: 3060 | G18: 1240 | J18: 102 | K18: 23380 | L18: 1129 | M18: 33 | O18: -1 | P18: 1161 | Q18: 253 | R18: 902 | S18: 0.1 | T18: 0.1 | U18: 0.1 | V18: 8660 | W18: 0.1 | X18: 0.1 | Y18: 0.1 | Z18: 8840 | AA18: 0 | AB18: 24300
A19: AMZN | B19: 39813 | C19: 19166 | D19: 14896 | E19: 4270 | F19: 2419 | G19: 1033 | J19: -24 | K19: 18324 | L19: 842 | M19: 50 | O19: 9 | P19: 901 | Q19: 247 | R19: 645 | S19: 0.08 | T19: 0.08 | U19: 0.08 | V19: 8460 | W19: 0.07 | X19: 0.07 | Y19: 0.07 | Z19: 8640 | AA19: 0 | AB19: 20700
A20: AMZN | B20: 39447 | C20: 14835 | D20: 11482 | E20: 3353 | F20: 1871 | G20: 818 | J20: 9 | K20: 14180 | L20: 655 | M20: 12 | O20: -7 | P20: 660 | Q20: 184 | R20: 476 | S20: 0.06 | T20: 0.06 | U20: 0.06 | V20: 8260 | W20: 0.06 | X20: 0.06 | Y20: 0.06 | Z20: 8480 | AA20: 0 | AB20: 17000
A21: AMZN | B21: 39082 | C21: 10711 | D21: 8255 | E21: 2456 | F21: 1395 | G21: 662 | J21: 10 | K21: 10322 | L21: 389 | M21: -6 | O21: -6 | P21: 377 | Q21: 187 | R21: 190 | S21: 0.02 | T21: 0.02 | U21: 0.02 | V21: 8320 | W21: 0.02 | X21: 0.02 | Y21: 0.02 | Z21: 8480 | AA21: 0 | AB21: 13900
A22: MSFT | B22: 46022 | C22: 281724 | D22: 87831 | E22: 193893 | F22: 32877 | G22: 32488 | I22: 943 | K22: 154139 | L22: 127585 | M22: 767 | O22: -4725 | P22: 123627 | Q22: 21795 | R22: 101832 | S22: 13.7 | T22: 13.7 | U22: 13.8 | V22: 7433 | W22: 13.64 | X22: 13.64 | Y22: 13.75 | Z22: 7465 | AA22: 3.32 | AB22: 228000
A23: MSFT | B23: 45657 | C23: 245122 | D23: 74114 | E23: 171008 | F23: 32065 | G23: 29510 | I23: 206 | K23: 135895 | L23: 109227 | M23: -121 | O23: -1319 | P23: 107787 | Q23: 19651 | R23: 88136 | S23: 11.86 | T23: 11.86 | U23: 11.88 | V23: 7431 | W23: 11.8 | X23: 11.8 | Y23: 11.82 | Z23: 7469 | AA23: 3 | AB23: 228000
A24: MSFT | B24: 45291 | C24: 211915 | D24: 65863 | E24: 146052 | F24: 29163 | G24: 27195 | I24: 1201 | K24: 123422 | L24: 88493 | M24: 1041 | O24: -223 | P24: 89311 | Q24: 16950 | R24: 72361 | S24: 9.72 | T24: 9.72 | U24: 9.85 | V24: 7446 | W24: 9.68 | X24: 9.68 | Y24: 9.81 | Z24: 7472 | AA24: 2.72 | AB24: 221000
A25: MSFT | B25: 44926 | C25: 198270 | D25: 62650 | E25: 135620 | F25: 27725 | G25: 24512 | I25: 101 | K25: 114988 | L25: 83282 | M25: 466 | O25: -32 | P25: 83716 | Q25: 10978 | R25: 72738 | S25: 9.7 | T25: 9.7 | U25: 9.72 | V25: 7496 | W25: 9.65 | X25: 9.65 | Y25: 9.66 | Z25: 7540 | AA25: 2.42 | AB25: 221000
A26: MSFT | B26: 44561 | C26: 168088 | D26: 52232 | E26: 115856 | F26: 25224 | G26: 20716 | I26: 13 | K26: 98185 | L26: 69903 | M26: 1101 | O26: 98 | P26: 71102 | Q26: 9831 | R26: 61271 | S26: 8.12 | T26: 8.12 | U26: 8.12 | V26: 7547 | W26: 8.05 | X26: 8.05 | Y26: 8.05 | Z26: 7608 | AA26: 2.24 | AB26: 181000
A27: MSFT | B27: 44196 | C27: 143015 | D27: 46078 | E27: 96937 | F27: 24709 | G27: 19269 | I27: 133 | K27: 90189 | L27: 52826 | M27: 250 | O27: -40 | P27: 53036 | Q27: 8755 | R27: 44281 | S27: 5.82 | T27: 5.82 | U27: 5.85 | V27: 7610 | W27: 5.76 | X27: 5.76 | Y27: 5.8 | Z27: 7683 | AA27: 1.53 | AB27: 163000
A28: MSFT | B28: 43830 | C28: 125843 | D28: 42910 | E28: 82933 | F28: 23098 | G28: 16876 | I28: 26 | K28: 82910 | L28: 42933 | M28: 812 | O28: -57 | P28: 43688 | Q28: 4291 | R28: 39240 | S28: 5.13 | T28: 5.11 | U28: 5.14 | V28: 7673 | W28: 5.08 | X28: 5.06 | Y28: 5.08 | Z28: 7753 | AA28: 1.8 | AB28: 144000
A29: MSFT | B29: 43465 | C29: 110360 | D29: 38353 | E29: 72007 | F29: 22223 | G29: 14726 | I29: 47 | K29: 75349 | L29: 35011 | M29: 1522 | O29: -59 | P29: 36474 | Q29: 6203 | R29: 16571 | S29: 3.93 | T29: 2.15 | U29: 3.94 | V29: 7700 | W29: 3.88 | X29: 2.13 | Y29: 3.89 | Z29: 7794 | AA29: 1.65 | AB29: 131000
A30: MSFT | B30: 43100 | C30: 96571 | D30: 34261 | E30: 62310 | F30: 18648 | G30: 12292 | I30: 2400 | K30: 67601 | L30: 28970 | M30: 1182 | O30: -251 | P30: 29901 | Q30: 4412 | R30: 25489 | S30: 3.29 | T30: 3.29 | U30: 3.66 | V30: 7746 | W30: 3.25 | X30: 3.25 | Y30: 3.62 | Z30: 7832 | AA30: 1.53
A31: MSFT | B31: 42735 | C31: 91154 | D31: 32780 | E31: 58374 | F31: 19198 | G31: 11988 | I31: 1432 | K31: 65398 | L31: 25756 | M31: 78 | O31: -195 | P31: 25639 | Q31: 5100 | R31: 20539 | S31: 2.59 | T31: 2.59 | U31: 2.74 | V31: 7925 | W31: 2.56 | X31: 2.56 | Y31: 2.71 | Z31: 8013 | AA31: 1.39
A32: MSFT | B32: 42369 | C32: 93580 | D32: 33038 | E32: 60542 | F32: 20324 | G32: 12046 | I32: 10194 | K32: 75602 | L32: 17978 | M32: 796 | O32: -267 | P32: 18507 | Q32: 6314 | R32: 12193 | S32: 1.49 | T32: 1.49 | U32: 2.31 | V32: 8177 | W32: 1.48 | X32: 1.48 | Y32: 2.29 | Z32: 8254 | AA32: 1.21 | AB32: 118000
A33: MSFT | B33: 42004 | C33: 86833 | D33: 26934 | E33: 59899 | F33: 20632 | G33: 11381 | I33: 233 | K33: 59180 | L33: 27653 | M33: 336 | O33: -169 | P33: 27820 | Q33: 5746 | R33: 22074 | S33: 2.66 | T33: 2.66 | U33: 2.68 | V33: 8299 | W33: 2.63 | X33: 2.63 | Y33: 2.65 | Z33: 8399 | AA33: 1.07 | AB33: 128000
A34: MSFT | B34: 41639 | C34: 77849 | D34: 20249 | E34: 57600 | F34: 20425 | G34: 10411 | I34: 208 | K34: 51293 | L34: 26556 | M34: 302 | O34: 194 | P34: 27052 | Q34: 5189 | R34: 21863 | S34: 2.61 | T34: 2.61 | U34: 2.63 | V34: 8375 | W34: 2.58 | X34: 2.58 | Y34: 2.6 | Z34: 8470 | AA34: 0.89 | AB34: 99000
A35: MSFT | B35: 41274 | C35: 73723 | D35: 17530 | E35: 56193 | F35: 18426 | G35: 9811 | I35: 6193 | K35: 51960 | L35: 21763 | M35: 205 | O35: 299 | P35: 22267 | Q35: 5289 | R35: 16978 | S35: 2.02 | T35: 2.02 | U35: 2.58 | V35: 8396 | W35: 2 | X35: 2 | Y35: 2.55 | Z35: 8506 | AA35: 0.8 | AB35: 94000
A36: MSFT | B36: 40908 | C36: 69943 | D36: 15577 | E36: 54366 | F36: 18162 | G36: 9043 | I36: 0 | K36: 42782 | L36: 27161 | M36: 861 | O36: 49 | P36: 28071 | Q36: 4921 | R36: 23150 | S36: 2.73 | T36: 2.73 | U36: 2.73 | V36: 8490 | W36: 2.69 | X36: 2.69 | Y36: 2.69 | Z36: 8593 | AA36: 0.64 | AB36: 90000
A37: MSFT | B37: 40543 | C37: 62484 | D37: 12395 | E37: 50089 | F37: 17218 | G37: 8714 | I37: 59 | K37: 38386 | L37: 24098 | M37: 832 | O37: 83 | P37: 25013 | Q37: 6253 | R37: 18760 | S37: 2.13 | T37: 2.13 | U37: 2.14 | V37: 8813 | W37: 2.1 | X37: 2.1 | Y37: 2.12 | Z37: 8927 | AA37: 0.52 | AB37: 89000
A38: MSFT | B38: 40178 | C38: 58437 | D38: 12155 | E38: 46282 | F38: 16579 | G38: 9010 | I38: -532 | K38: 37212 | L38: 21225 | M38: -1348 | O38: -56 | P38: 19821 | Q38: 5252 | R38: 14569 | S38: 1.63 | T38: 1.63 | U38: 1.59 | V38: 8945 | W38: 1.62 | X38: 1.62 | Y38: 1.58 | Z38: 8996 | AA38: 0.52 | AB38: 93000
A39: MSFT | B39: 39813 | C39: 60420 | D39: 11598 | E39: 48822 | F39: 16366 | G39: 8164 | I39: 1800 | K39: 37928 | L39: 22492 | M39: 1772 | O39: -450 | P39: 23814 | Q39: 6133 | R39: 17681 | S39: 1.9 | T39: 1.9 | U39: 2.04 | V39: 9328 | W39: 1.87 | X39: 1.87 | Y39: 2.01 | Z39: 9470 | AA39: 0.44 | AB39: 91000
A40: MSFT | B40: 39447 | C40: 51122 | D40: 10693 | E40: 40429 | F40: 14273 | G40: 7121 | I40: 511 | K40: 32598 | L40: 18524 | M40: 1636 | O40: -59 | P40: 20101 | Q40: 6036 | R40: 14065 | S40: 1.44 | T40: 1.44 | U40: 1.48 | V40: 9742 | W40: 1.42 | X40: 1.42 | Y40: 1.46 | Z40: 9886 | AA40: 0.4 | AB40: 79000
A41: MSFT | B41: 39082 | C41: 44282 | D41: 7650 | E41: 36632 | F41: 12256 | G41: 6584 | I41: 1320 | K41: 27810 | L41: 16472 | M41: 2198 | O41: -408 | P41: 18262 | Q41: 5663 | R41: 12599 | S41: 1.21 | T41: 1.21 | U41: 1.29 | V41: 10438 | W41: 1.2 | X41: 1.2 | Y41: 1.28 | Z41: 10531 | AA41: 0.35 | AB41: 71000
A42: GOOG | B42: 46022 | C42: 402836 | D42: 162535 | E42: 240301 | F42: 43975 | G42: 58687 | H42: 2400 | I42: 6200 | K42: 273797 | L42: 129039 | M42: 28120 | O42: 1667 | P42: 158826 | Q42: 26656 | R42: 132170 | S42: 10.91 | T42: 10.91 | U42: 11.33 | V42: 12116 | W42: 10.81 | X42: 10.81 | Y42: 11.23 | Z42: 12230 | AA42: 0.83 | AB42: 190820
A43: GOOG | B43: 45657 | C43: 350018 | D43: 146306 | E43: 203712 | F43: 40696 | G43: 48789 | I43: 1837 | K43: 237628 | L43: 112390 | M43: 6288 | O43: 1137 | P43: 119815 | Q43: 16997 | R43: 100118 | S43: 8.35 | T43: 8.13 | U43: 8.47 | V43: 12319 | W43: 8.26 | X43: 8.04 | Y43: 8.39 | Z43: 12447 | AA43: 0.6 | AB43: 183323
A44: GOOG | B44: 45291 | C44: 307394 | D44: 132372 | E44: 175022 | F44: 43087 | G44: 43709 | I44: 3933 | K44: 223101 | L44: 84293 | M44: 868 | O44: 556 | P44: 85717 | Q44: 9822 | R44: 73795 | S44: 6.01 | T44: 5.84 | U44: 6.28 | V44: 12630 | W44: 5.97 | X44: 5.8 | Y44: 6.24 | Z44: 12722 | AB44: 182502
A45: GOOG | B45: 44926 | C45: 282836 | D45: 126203 | E45: 156633 | F45: 42291 | G45: 39500 | K45: 207994 | L45: 74842 | M45: -4693 | O45: 1179 | P45: 71328 | Q45: 9756 | R45: 59972 | S45: 4.71 | T45: 4.59 | U45: 4.71 | V45: 13063 | W45: 4.68 | X45: 4.56 | Y45: 4.68 | Z45: 13159 | AB45: 190234
A46: GOOG | B46: 44561 | C46: 257637 | D46: 110939 | E46: 146698 | F46: 36422 | G46: 31562 | I46: 0 | K46: 178923 | L46: 78714 | M46: 13517 | O46: -1497 | P46: 90734 | Q46: 14701 | R46: 76033 | S46: 5.69 | T46: 5.69 | U46: 5.69 | V46: 13353 | W46: 5.61 | X46: 5.61 | Y46: 5.61 | Z46: 13553 | AB46: 156500
A47: GOOG | B47: 44196 | C47: 182527 | D47: 84732 | E47: 97795 | F47: 28998 | G47: 27573 | I47: 0 | K47: 141303 | L47: 41224 | M47: 8104 | O47: -1246 | P47: 48082 | Q47: 7813 | R47: 40269 | S47: 2.96 | T47: 2.96 | U47: 2.96 | V47: 13616 | W47: 2.93 | X47: 2.93 | Y47: 2.93 | Z47: 13741 | AB47: 135301
A48: GOOG | B48: 43830 | C48: 161857 | D48: 71896 | E48: 89961 | F48: 28015 | G48: 26018 | I48: 1697 | K48: 127626 | L48: 34231 | M48: 5473 | O48: -79 | P48: 39625 | Q48: 5282 | R48: 34343 | S48: 2.48 | T48: 2.48 | U48: 2.59 | V48: 13852 | W48: 2.46 | X48: 2.46 | Y48: 2.56 | Z48: 13971 | AB48: 118899
A49: GOOG | B49: 43465 | C49: 136819 | D49: 59549 | E49: 77270 | F49: 24459 | G49: 21419 | I49: 5071 | K49: 110498 | L49: 26321 | M49: 8383 | O49: 209 | P49: 34913 | Q49: 4177 | R49: 30736 | S49: 2.21 | T49: 2.21 | U49: 2.53 | V49: 13903 | W49: 2.19 | X49: 2.19 | Y49: 2.5 | Z49: 14066 | AB49: 98771
A50: GOOG | B50: 43100 | C50: 110855 | D50: 45583 | E50: 65272 | F50: 19765 | G50: 16625 | I50: 2736 | K50: 84709 | L50: 26146 | M50: 764 | O50: 283 | P50: 27193 | Q50: 4707 | R50: 12662 | S50: 1.62 | T50: 0.91 | U50: 1.79 | V50: 13858 | W50: 1.6 | X50: 0.9 | Y50: 1.76 | Z50: 14072 | AB50: 80110
A51: GOOG | B51: 42735 | C51: 90272 | D51: 35138 | E51: 55134 | F51: 17470 | G51: 13948 | K51: 66556 | L51: 23716 | M51: 90 | O51: 344 | P51: 24150 | Q51: 4672 | R51: 19478 | S51: 1.42 | T51: 1.42 | U51: 1.42 | V51: 13756 | W51: 1.39 | X51: 1.39 | Y51: 1.39 | Z51: 13974 | AA51: 0 | AB51: 72053
A52: GOOG | B52: 42369 | C52: 74989 | D52: 28164 | E52: 46825 | F52: 15183 | G52: 12282 | K52: 55629 | L52: 19360 | M52: 35 | N52: 0 | O52: 256 | P52: 19651 | Q52: 3303 | R52: 16348 | S52: 1.16 | T52: 1.16 | U52: 1.16 | V52: 13693 | W52: 1.14 | X52: 1.14 | Y52: 1.14 | Z52: 13859 | AA52: 0 | AB52: 61814
A53: GOOG | B53: 42004 | C53: 66001 | D53: 25313 | E53: 40688 | F53: 13982 | G53: 9832 | I53: 378 | K53: 49505 | L53: 16496 | M53: 585 | N53: 0 | O53: 178 | P53: 17259 | Q53: 3639 | R53: 14136 | S53: 1.01 | T53: 1.05 | U53: 1.03 | V53: 13519 | W53: 0.99 | X53: 1.03 | Y53: 1.01 | Z53: 13741 | AA53: 0 | AB53: 53600
A54: GOOG | B54: 41639 | C54: 55519 | D54: 21993 | E54: 33526 | F54: 10986 | G54: 7137 | K54: 40116 | L54: 15403 | M54: 305 | N54: -57 | O54: 248 | P54: 15899 | Q54: 2739 | R54: 12733 | S54: 0.99 | T54: 0.96 | U54: 0.99 | V54: 13314 | W54: 0.89 | X54: 0.86 | Y54: 0.9 | Z54: 14739 | AA54: 0
A55: GOOG | B55: 41274 | C55: 46039 | D55: 17176 | E55: 28863 | F55: 8946 | G55: 6083 | K55: 32205 | L55: 13834 | M55: -145 | N55: 188 | O55: 592 | P55: 14469 | Q55: 2916 | R55: 10737 | S55: 0.88 | T55: 0.82 | U55: 0.87 | V55: 13089 | W55: 0.87 | X55: 0.81 | Y55: 0.86 | Z55: 13292 | AA55: 0
A56: GOOG | B56: 40908 | C56: 37905 | D56: 13188 | E56: 24717 | F56: 7313 | G56: 5162 | I56: 610 | K56: 26273 | L56: 11632 | M56: 629 | N56: 0 | O56: 65 | P56: 12326 | Q56: 2589 | R56: 9737 | S56: 0.75 | T56: 0.75 | U56: 0.79 | V56: 12911 | W56: 0.74 | X56: 0.74 | Y56: 0.78 | Z56: 13089 | AA56: 0 | AB56: 32467
A57: GOOG | B57: 40543 | C57: 29321 | D57: 10417 | E57: 18904 | F57: 4761 | G57: 3762 | I57: 0 | K57: 18940 | L57: 10381 | M57: 404 | N57: 0 | O57: 11 | P57: 10796 | Q57: 2291 | R57: 8505 | S57: 0.67 | T57: 0.67 | U57: 0.67 | V57: 12748 | W57: 0.66 | X57: 0.66 | Y57: 0.66 | Z57: 12930 | AA57: 0 | AB57: 24400
A58: GOOG | B58: 40178 | C58: 23650.563 | D58: 8844.115 | E58: 14806.448 | F58: 3651.235 | G58: 2843.027 | I58: 0 | K58: 15338.4 | L58: 8312.186 | M58: 66.6 | O58: 2.4 | P58: 8381.189 | Q58: 1860.741 | R58: 6520.448 | S58: 0.52 | T58: 0.52 | U58: 0.52 | V58: 12649 | W58: 0.51 | X58: 0.51 | Y58: 0.51 | Z58: 12777 | AA58: 0 | AB58: 19835
A59: GOOG | B59: 39813 | C59: 21795.55 | D59: 8621.506 | E59: 13174.044 | F59: 3748.883 | G59: 2793.192 | I59: 1094.8 | K59: 16258.3 | L59: 5537.212 | M59: 311.9 | O59: 4.5 | P59: 5853.596 | Q59: 1626.738 | R59: 4226.858 | S59: 0.34 | T59: 0.34 | U59: 0.4 | V59: 12558 | W59: 0.33 | X59: 0.33 | Y59: 0.4 | Z59: 12701 | AA59: 0 | AB59: 20222
A60: GOOG | B60: 39447 | C60: 16593.986 | D60: 6649.085 | E60: 9944.901 | F60: 2740.516 | G60: 2119.985 | I60: 0 | K60: 11509.6 | L60: 5084.4 | M60: 558 | O60: 31.6 | P60: 5673.98 | Q60: 1470.26 | R60: 4203.72 | S60: 0.34 | T60: 0.34 | U60: 0.34 | V60: 12432 | W60: 0.33 | X60: 0.33 | Y60: 0.33 | Z60: 12648 | AA60: 0 | AB60: 16805
A61: GOOG | B61: 39082 | C61: 10604.917 | D61: 4225.027 | E61: 6379.89 | F61: 1601.305 | G61: 1228.589 | I61: 0 | K61: 7054.9 | L61: 3549.996 | M61: 411.8 | O61: 49.2 | P61: 4011.04 | Q61: 933.594 | R61: 3077.446 | S61: 0.26 | T61: 0.26 | U61: 0.26 | V61: 12056 | W61: 0.25 | X61: 0.25 | Y61: 0.25 | Z61: 12382 | AA61: 0 | AB61: 10674
A62: META | B62: 46022 | C62: 200966 | D62: 36175 | E62: 164791 | F62: 24143 | G62: 57372 | K62: 117690 | L62: 83276 | M62: 1723 | O62: 933 | P62: 85932 | Q62: 11444 | R62: 60458 | S62: 29.55 | T62: 23.98 | U62: 29.63 | V62: 2521 | W62: 28.94 | X62: 23.49 | Y62: 29.02 | Z62: 2574 | AA62: 2.1 | AB62: 78865
A63: META | B63: 45657 | C63: 164501 | D63: 30130 | E63: 134371 | F63: 20983 | G63: 43619 | I63: 389 | K63: 95121 | L63: 69380 | M63: 1112 | O63: 171 | P63: 70663 | Q63: 7585 | R63: 62360 | S63: 24.89 | T63: 24.61 | U63: 25.03 | V63: 2534 | W63: 24.13 | X63: 23.86 | Y63: 24.26 | Z63: 2614 | AA63: 2 | AB63: 74067
A64: META | B64: 45291 | C64: 134902 | D64: 26006 | E64: 108896 | F64: 22204 | G64: 36489 | I64: 3452 | K64: 88151 | L64: 46751 | M64: 827 | O64: -150 | P64: 47428 | Q64: 7755 | R64: 39098 | S64: 15.41 | T64: 15.19 | U64: 16.53 | V64: 2574 | W64: 15.09 | X64: 14.87 | Y64: 16.19 | Z64: 2629 | AB64: 67317
A65: META | B65: 44926 | C65: 116609 | D65: 23754 | E65: 92855 | F65: 25681 | G65: 33619 | I65: 4611 | K65: 87665 | L65: 28944 | M65: 195 | O65: -320 | P65: 28819 | Q65: 5258 | R65: 23200 | S65: 8.77 | T65: 8.63 | U65: 10.17 | V65: 2687 | W65: 8.72 | X65: 8.59 | Y65: 10.12 | Z65: 2702 | AB65: 86482
A66: META | B66: 44561 | C66: 117929 | D66: 22649 | E66: 95280 | F66: 23872 | G66: 24655 | K66: 71176 | L66: 46753 | M66: 321 | O66: 210 | P66: 47284 | Q66: 7914 | R66: 39370 | S66: 13.99 | T66: 13.99 | U66: 13.99 | V66: 2815 | W66: 13.77 | X66: 13.77 | Y66: 13.77 | Z66: 2859 | AB66: 71970
A67: META | B67: 44196 | C67: 85965 | D67: 16692 | E67: 69273 | F67: 18155 | G67: 18447 | K67: 53294 | L67: 32671 | M67: 543 | O67: -34 | P67: 33180 | Q67: 4034 | R67: 29146 | S67: 10.22 | T67: 10.22 | U67: 10.22 | V67: 2851 | W67: 10.09 | X67: 10.09 | Y67: 10.09 | Z67: 2888 | AA67: 0 | AB67: 58604
A68: META | B68: 43830 | C68: 70697 | D68: 12770 | E68: 57927 | F68: 15341 | G68: 13600 | I68: 5000 | K68: 46711 | L68: 23986 | M68: 799 | O68: 27 | P68: 24812 | Q68: 6327 | R68: 18485 | S68: 6.48 | T68: 6.48 | U68: 7.78 | V68: 2854 | W68: 6.43 | X68: 6.43 | Y68: 7.72 | Z68: 2876 | AA68: 0 | AB68: 44942
A69: META | B69: 43465 | C69: 55838 | D69: 9355 | E69: 46483 | F69: 11297 | G69: 10273 | K69: 30925 | L69: 24913 | M69: 439 | O69: 9 | P69: 25361 | Q69: 3249 | R69: 22112 | S69: 7.65 | T69: 7.65 | U69: 7.65 | V69: 2890 | W69: 7.57 | X69: 7.57 | Y69: 7.57 | Z69: 2921 | AA69: 0 | AB69: 35587
A70: META | B70: 43100 | C70: 40653 | D70: 5454 | E70: 35199 | F70: 7242 | G70: 7754 | K70: 20450 | L70: 20203 | M70: 386 | O70: 5 | P70: 20594 | Q70: 2387 | R70: 15934 | S70: 6.27 | T70: 5.49 | U70: 6.27 | V70: 2901 | W70: 6.16 | X70: 5.39 | Y70: 6.16 | Z70: 2956 | AB70: 25105
A71: META | B71: 42735 | C71: 27638 | D71: 3789 | E71: 23849 | F71: 5503 | G71: 5919 | K71: 15211 | L71: 12427 | M71: 90 | O71: 1 | P71: 12518 | Q71: 2301 | R71: 10217 | S71: 3.56 | T71: 3.56 | U71: 3.56 | V71: 2863 | W71: 3.49 | X71: 3.49 | Y71: 3.49 | Z71: 2925 | AA71: 0 | AB71: 17048
A72: META | B72: 42369 | C72: 17928 | D72: 2867 | E72: 15061 | F72: 4020 | G72: 4816 | K72: 11703 | L72: 6225 | M72: -37 | O72: 6 | P72: 6194 | Q72: 2506 | R72: 3688 | S72: 1.31 | T72: 1.31 | U72: 1.31 | V72: 2803 | W72: 1.29 | X72: 1.29 | Y72: 1.29 | Z72: 2853 | AA72: 0 | AB72: 12691
A73: META | B73: 42004 | C73: 12466 | D73: 2153 | E73: 10313 | F73: 2653 | G73: 2666 | K73: 7472 | L73: 4994 | M73: -83 | O73: -1 | P73: 4910 | Q73: 1970 | R73: 2940 | S73: 1.12 | T73: 1.12 | U73: 1.12 | V73: 2614 | W73: 1.1 | X73: 1.1 | Y73: 1.1 | Z73: 2664 | AA73: 0 | AB73: 9199
A74: META | B74: 41639 | C74: 7872 | D74: 1875 | E74: 5997 | F74: 1778 | G74: 1415 | K74: 5068 | L74: 2804 | M74: -51 | O74: 1 | P74: 2754 | Q74: 1254 | R74: 1500 | S74: 0.62 | T74: 0.62 | U74: 0.62 | V74: 2420 | W74: 0.6 | X74: 0.6 | Y74: 0.6 | Z74: 2517 | AA74: 0 | AB74: 6337
A75: META | B75: 41274 | C75: 5089 | D75: 1364 | E75: 3725 | F75: 1788 | G75: 1399 | K75: 4551 | L75: 538 | M75: -60 | O75: 16 | P75: 494 | Q75: 441 | R75: 53 | S75: 0.02 | T75: 0.02 | U75: 0.02 | V75: 2006 | W75: 0.01 | X75: 0.01 | Y75: 0.01 | Z75: 2166 | AA75: 0 | AB75: 4619
A76: META | B76: 40908 | C76: 3711 | D76: 860 | E76: 2851 | F76: 707 | G76: 388 | K76: 1955 | L76: 1756 | M76: -71 | O76: 10 | P76: 1695 | Q76: 695 | R76: 1000 | S76: 0.31 | T76: 0.31 | U76: 0.31 | V76: 2138 | W76: 0.31 | X76: 0.31 | Y76: 0.31 | Z76: 2138 | AA76: 0 | AB76: 3200
A77: META | B77: 40543 | C77: 1974 | D77: 493 | E77: 1481 | F77: 305 | G77: 144 | K77: 942 | L77: 1032 | M77: -23 | O77: -1 | P77: 1008 | Q77: 402 | R77: 606 | S77: 0.17 | T77: 0.17 | U77: 0.17 | V77: 2138 | W77: 0.17 | X77: 0.17 | Y77: 0.17 | Z77: 2138 | AA77: 0 | AB77: 2127
A78: META | B78: 40178 | C78: 777 | D78: 223 | E78: 554 | F78: 205 | G78: 87 | K78: 515 | L78: 262 | M78: -10 | O78: 2 | P78: 254 | Q78: 25 | R78: 229 | S78: 0.06 | T78: 0.06 | U78: 0.06 | V78: 2138 | W78: 0.06 | X78: 0.06 | Y78: 0.06 | Z78: 2138 | AA78: 0 | AB78: 1218
A79: META | B79: 39813 | C79: 272 | D79: 124 | E79: 148 | F79: 156 | G79: 47 | K79: 327 | L79: -55 | O79: -1 | P79: -56 | Q79: 0 | R79: -56 | S79: -0.03 | T79: -0.03 | U79: -0.03 | V79: 2138 | W79: -0.03 | X79: -0.03 | Y79: -0.03 | Z79: 2138 | AA79: 0
A80: META | B80: 39447 | C80: 153 | D80: 41 | E80: 112 | F80: 155 | G80: 81 | K80: 277 | L80: -124 | O80: -11 | P80: -135 | Q80: 3 | R80: -138 | S80: -0.06 | T80: -0.06 | U80: -0.06 | V80: 2138 | W80: -0.06 | X80: -0.06 | Y80: -0.06 | Z80: 2138 | AA80: 0
A1048555: GOOG
A1048556: GOOG
A1048557: GOOG
A1048558: GOOG
A1048559: GOOG
A1048560: GOOG
A1048561: GOOG
A1048562: GOOG
A1048563: GOOG
A1048564: GOOG
A1048565: GOOG
A1048566: GOOG
... A1048574: GOOG

Sheet Balance Sheet
A1: Ticker | B1: FY | C1: Cash & Equivalents | D1: Cash, Cash Equiv. & Short Term Inv. | E1: Total Receivables | F1: Total Inventory | G1: Prepaid Expenses | H1: Other Current Assets | I1: Total Current Assets | J1: PP&E Gross | K1: Accumulated Depreciation, Total | L1: PP&E Net | M1: Goodwill | N1: Intangibles | O1: Long Term Investments | P1: Note Receivable - Long Term | Q1: Other Long Term Assets | R1: Total Assets | S1: Accounts Payable | T1: Accrued Expenses | U1: Current Port. of LT Debt/Capital Leases | V1: Notes Payable/Short Term Debt | W1: Other Current Liabilities | X1: Total Current Liabilities | Y1: Long Term Debt | Z1: Capital Lease Obligations | AA1: Total Long Term Debt | AB1: Deferred Income Tax | AC1: Other Liabilities, Total | AD1: Minority Interest | AE1: Total Liabilities | AF1: Common Stock | AG1: Additional Paid-In Capital | AH1: Retained Earnings (Accumulated Deficit) | AI1: Treasury Stock - Common | AJ1: Unrealized Gain (Loss) | AK1: Other Equity, Total | AL1: Total Equity | AM1: Total Liabilities & Shareholders' Equity | AN1: Total Common Shares Outstanding
A2: AMZN | B2: 46022 | C2: 86810 | D2: 123029 | E2: 60529 | F2: 38325 | G2: 6900 | H2: 300 | I2: 229083 | J2: 620152 | K2: -177073 | L2: 443079 | M2: 23273 | N2: 9197 | O2: 5000 | Q2: 108410 | R2: 818042 | S2: 121909 | T2: 70415 | U2: 4650 | V2: 455 | W2: 20576 | X2: 218005 | Y2: 65648 | Z2: 18542 | AA2: 84190 | AC2: 104782 | AE2: 406977 | AF2: 112 | AG2: 140024 | AH2: 250536 | AI2: -7837 | AJ2: 30170 | AK2: -1940 | AL2: 411065 | AM2: 818042 | AN2: 10731
A3: AMZN | B3: 45657 | C3: 78779 | D3: 101202 | E3: 48904 | F3: 34214 | G3: 6300 | H3: 247 | I3: 190867 | J3: 470196 | K3: -141390 | L3: 328806 | M3: 23074 | N3: 8602 | O3: 4600 | Q3: 68945 | R3: 624894 | S3: 94363 | T3: 60110 | U3: 6704 | V3: 151 | W3: 18103 | X3: 179431 | Y3: 52623 | Z3: 16327 | AA3: 68950 | AC3: 90543 | AE3: 338924 | AF3: 111 | AG3: 120864 | AH3: 172866 | AI3: -7837 | AK3: -34 | AL3: 285970 | AM3: 624894 | AN3: 10593
A4: AMZN | B4: 45291 | C4: 73387 | D4: 86780 | E4: 46356 | F4: 33318 | G4: 5400 | H4: 497 | I4: 172351 | J4: 396801 | K4: -120111 | L4: 276690 | M4: 22789 | N4: 7687 | O4: 5700 | Q4: 42637 | R4: 527854 | S4: 84981 | T4: 53765 | U4: 10797 | V4: 147 | W4: 15227 | X4: 164917 | Y4: 58314 | Z4: 16677 | AA4: 74991 | AC4: 86071 | AE4: 325979 | AF4: 109 | AG4: 99025 | AH4: 113618 | AI4: -7837 | AK4: -3040 | AL4: 201875 | AM4: 527854 | AN4: 10383
A5: AMZN | B5: 44926 | C5: 53888 | D5: 70026 | E5: 42002 | F5: 34405 | H5: 358 | I5: 146791 | J5: 349853 | K5: -97015 | L5: 252838 | M5: 20288 | N5: 6097 | O5: 5000 | Q5: 31661 | R5: 462675 | S5: 79600 | T5: 46904 | U5: 7662 | V5: 8000 | W5: 13227 | X5: 155393 | Y5: 67150 | Z5: 18086 | AA5: 85236 | AC5: 76003 | AE5: 316632 | AF5: 108 | AG5: 75066 | AH5: 83193 | AI5: -7837 | AK5: -4487 | AL5: 146043 | AM5: 462675 | AN5: 10242
A6: AMZN | B6: 44561 | C6: 36220 | D6: 96049 | E6: 32649 | F6: 32640 | H6: 242 | I6: 161580 | J6: 294882 | K6: -78519 | L6: 216363 | M6: 15371 | N6: 5107 | O6: 20300 | Q6: 1828 | R6: 420549 | S6: 78664 | T6: 40962 | U6: 9770 | V6: 1043 | W6: 11827 | X6: 142266 | Y6: 48744 | Z6: 21870 | AA6: 70614 | AB6: 494 | AC6: 68930 | AE6: 282304 | AF6: 5 | AG6: 55538 | AH6: 85915 | AI6: -1837 | AK6: -1376 | AL6: 138245 | AM6: 420549 | AN6: 10180
A7: AMZN | B7: 44196 | C7: 42122 | D7: 84396 | E7: 24309 | F7: 23795 | G7: 1 | H7: 232 | I7: 132733 | J7: 211101 | K7: -60434 | L7: 150667 | M7: 15017 | N7: 4981 | O7: 3200 | Q7: 14597 | R7: 321195 | S7: 72539 | T7: 31773 | U7: 11640 | V7: 725 | W7: 9708 | X7: 126385 | Y7: 31816 | Z7: 21460 | AA7: 53276 | AC7: 48130 | AE7: 227791 | AF7: 5 | AG7: 42865 | AH7: 52551 | AI7: -1837 | AK7: -180 | AL7: 93404 | AM7: 321195 | AN7: 10060
A8: AMZN | B8: 43830 | C8: 36092 | D8: 55021 | E8: 20540 | F8: 20497 | G8: 1 | H8: 275 | I8: 96334 | J8: 144821 | K8: -46975 | L8: 97846 | M8: 14754 | N8: 4049 | O8: 679 | Q8: 11586 | R8: 225248 | S8: 47183 | T8: 21248 | U8: 11191 | V8: 0 | W8: 8190 | X8: 87812 | Y8: 23414 | Z8: 17095 | AA8: 40509 | AC8: 34867 | AE8: 163188 | AF8: 5 | AG8: 33658 | AH8: 31220 | AI8: -1837 | AK8: -986 | AL8: 62060 | AM8: 225248 | AN8: 9960
A9: AMZN | B9: 43465 | C9: 31750 | D9: 41250 | E9: 16677 | F9: 17174 | I9: 75101 | J9: 95770 | K9: -33973 | L9: 61797 | M9: 14548 | N9: 4110 | O9: 518 | Q9: 6574 | R9: 162648 | S9: 38192 | T9: 14161 | U9: 9502 | V9: 0 | W9: 6536 | X9: 68391 | Y9: 23495 | Z9: 16292 | AA9: 39787 | AB9: 1490 | AC9: 9431 | AE9: 119099 | AF9: 5 | AG9: 26791 | AH9: 19625 | AI9: -1837 | AK9: -1035 | AL9: 43549 | AM9: 162648 | AN9: 9820
A10: AMZN | B10: 43100 | C10: 20522 | D10: 30986 | E10: 13164 | F10: 16047 | I10: 60197 | J10: 68573 | K10: -19707 | L10: 48866 | M10: 13350 | N10: 3371 | O10: 415 | Q10: 5111 | R10: 131310 | S10: 34616 | T10: 11949 | U10: 6221 | V10: 0 | W10: 5097 | X10: 57883 | Y10: 24743 | Z10: 13183 | AA10: 37926 | AB10: 990 | AC10: 6802 | AE10: 103601 | AF10: 5 | AG10: 21389 | AH10: 8636 | AI10: -1837 | AJ10: -16 | AK10: -468 | AL10: 27709 | AM10: 131310 | AN10: 9680
A11: AMZN | B11: 42735 | C11: 19334 | D11: 25981 | E11: 8339 | F11: 11461 | I11: 45781 | J11: 42441 | K11: -13327 | L11: 29114 | M11: 3784 | N11: 854 | O11: 242 | Q11: 3627 | R11: 83402 | S11: 25309 | T11: 8542 | U11: 5197 | V11: 0 | W11: 4768 | X11: 43816 | Y11: 7694 | Z11: 7519 | AA11: 15213 | AB11: 392 | AC11: 4696 | AE11: 64117 | AF11: 5 | AG11: 17186 | AH11: 4916 | AI11: -1837 | AJ11: 16 | AK11: -1001 | AL11: 19285 | AM11: 83402 | AN11: 9540
A12: AMZN | B12: 42369 | C12: 15890 | D12: 19808 | E12: 5654 | F12: 10243 | I12: 35705 | J12: 30053 | K12: -8215 | L12: 21838 | M12: 3759 | Q12: 3445 | R12: 64747 | S12: 20397 | T12: 7273 | U12: 3099 | V12: 0 | W12: 3118 | X12: 33887 | Y12: 8227 | Z12: 5900 | AA12: 14127 | AC12: 3349 | AE12: 51363 | AF12: 5 | AG12: 13394 | AH12: 2545 | AI12: -1837 | AK12: -723 | AL12: 13384 | AM12: 64747 | AN12: 9420
A13: AMZN | B13: 42004 | C13: 14557 | D13: 17416 | E13: 5612 | F13: 8299 | I13: 31327 | J13: 22730 | K13: -5763 | L13: 16967 | M13: 3319 | N13: 764 | O13: 209 | Q13: 1919 | R13: 54505 | S13: 16459 | T13: 6207 | U13: 3600 | V13: 0 | W13: 1823 | X13: 28089 | Y13: 8265 | Z13: 4224 | AA13: 12489 | AB13: 1021 | AC13: 2165 | AE13: 43764 | AF13: 5 | AG13: 11135 | AH13: 1949 | AI13: -1837 | AJ13: 1 | AK13: -512 | AL13: 10741 | AM13: 54505 | AN13: 9300
A14: AMZN | B14: 41639 | C14: 8658 | D14: 12447 | E14: 4767 | F14: 7411 | I14: 24625 | J14: 14809 | K14: -3860 | L14: 10949 | M14: 2655 | N14: 645 | O14: 127 | Q14: 1158 | R14: 40159 | S14: 15133 | T14: 4952 | U14: 1736 | V14: 0 | W14: 1159 | X14: 22980 | Y14: 3191 | Z14: 1990 | AA14: 5181 | AC14: 2252 | AE14: 30413 | AF14: 5 | AG14: 9573 | AH14: 2190 | AI14: -1837 | AJ14: 2 | AK14: -187 | AL14: 9746 | AM14: 40159 | AN14: 9180
A15: AMZN | B15: 41274 | C15: 8084 | D15: 11448 | E15: 3364 | F15: 6031 | H15: 453 | I15: 21296 | J15: 9582 | K15: -2522 | L15: 7060 | M15: 2552 | N15: 725 | O15: 140 | Q15: 782 | R15: 32555 | S15: 13318 | T15: 5129 | U15: 555 | V15: 0 | X15: 19002 | Y15: 3084 | Z15: 746 | AA15: 3830 | AC15: 1531 | AE15: 24363 | AF15: 5 | AG15: 8347 | AH15: 1916 | AI15: -1837 | AJ15: 11 | AK15: -250 | AL15: 8192 | AM15: 32555 | AN15: 9080
A16: AMZN | B16: 40908 | C16: 5269 | D16: 9576 | E16: 2571 | F16: 4992 | H16: 351 | I16: 17490 | J16: 5786 | K16: -1369 | L16: 4417 | M16: 1955 | N16: 647 | Q16: 769 | R16: 25278 | S16: 11145 | T16: 2765 | U16: 524 | V16: 0 | W16: 462 | X16: 14896 | Y16: 255 | Z16: 1160 | AA16: 1415 | AC16: 1210 | AE16: 17521 | AF16: 5 | AG16: 6990 | AH16: 1955 | AI16: -877 | AJ16: 10 | AK16: -326 | AL16: 7757 | AM16: 25278 | AN16: 9100
A17: AMZN | B17: 40543 | C17: 3777 | D17: 8762 | E17: 1587 | F17: 3202 | H17: 196 | I17: 13747 | J17: 3256 | K17: -842 | L17: 2414 | M17: 1349 | N17: 563 | Q17: 724 | R17: 18797 | S17: 8051 | T17: 1860 | U17: 0 | V17: 0 | W17: 461 | X17: 10372 | Y17: 184 | Z17: 457 | AA17: 641 | AC17: 920 | AE17: 11933 | AF17: 5 | AG17: 6325 | AH17: 1324 | AI17: -600 | AK17: -190 | AL17: 6864 | AM17: 18797 | AN17: 9020
A18: AMZN | B18: 40178 | C18: 3444 | D18: 6366 | E18: 988 | F18: 2171 | H18: 272 | I18: 9797 | J18: 1915 | K18: -625 | L18: 1290 | M18: 1234 | N18: 567 | Q18: 925 | R18: 13813 | S18: 5605 | T18: 1248 | U18: 0 | V18: 0 | W18: 511 | X18: 7364 | Y18: 109 | Z18: 143 | AA18: 252 | AC18: 940 | AE18: 8556 | AF18: 5 | AG18: 5736 | AH18: 172 | AI18: -600 | AK18: -56 | AL18: 5257 | AM18: 13813 | AN18: 8880
A19: AMZN | B19: 39813 | C19: 2769 | D19: 3727 | E19: 827 | F19: 1399 | H19: 204 | I19: 6157 | J19: 1409 | K19: -555 | L19: 854 | M19: 438 | N19: 160 | Q19: 705 | R19: 8314 | S19: 3594 | T19: 902 | U19: 59 | V19: 0 | W19: 191 | X19: 4746 | Y19: 409 | AA19: 409 | AC19: 487 | AE19: 5642 | AF19: 4 | AG19: 4121 | AH19: -730 | AI19: -600 | AK19: -123 | AL19: 2672 | AM19: 8314 | AN19: 8560
A20: AMZN | B20: 39447 | C20: 2539 | D20: 3112 | E20: 682 | F20: 1200 | G20: 23 | H20: 147 | I20: 5164 | J20: 1023 | K20: -480 | L20: 543 | M20: 222 | Q20: 556 | R20: 6485 | S20: 2795 | T20: 919 | U20: 0 | V20: 0 | X20: 3714 | Y20: 1282 | AA20: 1282 | AC20: 292 | AE20: 5288 | AF20: 4 | AG20: 3063 | AH20: -1375 | AI20: -500 | AK20: 5 | AL20: 1197 | AM20: 6485 | AN20: 8320
A21: AMZN | B21: 39082 | C21: 1022 | D21: 2019 | E21: 382 | F21: 877 | G21: 17 | H21: 78 | I21: 3373 | J21: 824 | K21: -367 | L21: 457 | M21: 195 | Q21: 338 | R21: 4363 | S21: 1816 | T21: 716 | U21: 0 | V21: 0 | X21: 2532 | Y21: 1247 | AA21: 1247 | AC21: 153 | AE21: 3932 | AF21: 4 | AG21: 2517 | AH21: -1837 | AI21: -252 | AK21: -1 | AL21: 431 | AM21: 4363 | AN21: 8280
A22: MSFT | B22: 46022 | C22: 30242 | D22: 94565 | E22: 78105 | F22: 938 | H22: 17523 | I22: 191131 | J22: 323442 | K22: -93653 | L22: 229789 | M22: 119509 | N22: 22604 | O22: 15405 | P22: 5200 | Q22: 35365 | R22: 619003 | S22: 27724 | T22: 19133 | U22: 6171 | V22: 0 | W22: 88190 | X22: 141218 | Y22: 40152 | Z22: 43000 | AA22: 83152 | AB22: 2835 | AC22: 48319 | AE22: 275524 | AF22: 46462.5 | AG22: 62632.5 | AH22: 237731 | AJ22: -1051 | AK22: -2296 | AL22: 343479 | AM22: 619003 | AN22: 7434
A23: MSFT | B23: 45657 | C23: 18315 | D23: 75543 | E23: 67424 | F23: 1246 | H23: 15521 | I23: 159734 | J23: 230973 | K23: -76421 | L23: 154552 | M23: 119220 | N23: 27597 | O23: 14600 | P23: 4900 | Q23: 31560 | R23: 512163 | S23: 21996 | T23: 16144 | U23: 4598 | V23: 6693 | W23: 75855 | X23: 125286 | Y23: 42688 | Z23: 24796 | AA23: 67484 | AB23: 2618 | AC23: 48298 | AE23: 243686 | AF23: 46462.5 | AG23: 54460.5 | AH23: 173144 | AJ23: -2625 | AK23: -2965 | AL23: 268477 | AM23: 512163 | AN23: 7434
A24: MSFT | B24: 45291 | C24: 34704 | D24: 111262 | E24: 48688 | F24: 2500 | H24: 21807 | I24: 184257 | J24: 178238 | K24: -68251 | L24: 109987 | M24: 67886 | N24: 9366 | O24: 9879 | P24: 4500 | Q24: 26101 | R24: 411976 | S24: 18095 | T24: 13418 | U24: 6444 | V24: 0 | W24: 66192 | X24: 104149 | Y24: 41990 | Z24: 15870 | AA24: 57860 | AB24: 433 | AC24: 43311 | AE24: 205753 | AF24: 46450 | AG24: 47268 | AH24: 118848 | AJ24: -3582 | AK24: -2761 | AL24: 206223 | AM24: 411976 | AN24: 7432
A25: MSFT | B25: 44926 | C25: 13931 | D25: 104757 | E25: 44261 | F25: 3742 | H25: 16924 | I25: 169684 | J25: 147206 | K25: -59660 | L25: 87546 | M25: 67524 | N25: 11298 | O25: 6891 | P25: 3800 | Q25: 18097 | R25: 364840 | S25: 19000 | T25: 12889 | U25: 3809 | V25: 0 | W25: 59384 | X25: 95082 | Y25: 47032 | Z25: 13842 | AA25: 60874 | AB25: 230 | AC25: 42112 | AE25: 198298 | AF25: 46650 | AG25: 40289 | AH25: 84281 | AJ25: -2138 | AK25: -2540 | AL25: 166542 | AM25: 364840 | AN25: 7464
A26: MSFT | B26: 44561 | C26: 14224 | D26: 130334 | E26: 38043 | F26: 2636 | H26: 13393 | I26: 184406 | J26: 122154 | K26: -51351 | L26: 70803 | M26: 49711 | N26: 7800 | O26: 5984 | P26: 3400 | Q26: 11675 | R26: 333779 | S26: 15163 | T26: 12019 | U26: 8863 | V26: 0 | W26: 52612 | X26: 88657 | Y26: 50074 | Z26: 11750 | AA26: 61824 | AB26: 198 | AC26: 41112 | AE26: 191791 | AF26: 46993.8 | AG26: 36117.25 | AH26: 57055 | AJ26: 3222 | AK26: -1400 | AL26: 141988 | AM26: 333779 | AN26: 7519
A27: MSFT | B27: 44196 | C27: 13576 | D27: 136527 | E27: 32011 | F27: 1895 | H27: 11482 | I27: 181915 | J27: 96101 | K27: -43197 | L27: 52904 | M27: 43351 | N27: 7038 | O27: 2965 | P27: 2700 | Q27: 10438 | R27: 301311 | S27: 12530 | T27: 9490 | U27: 4289 | V27: 0 | W27: 46001 | X27: 72310 | Y27: 59578 | Z27: 8956 | AA27: 68534 | AB27: 204 | AC27: 41959 | AE27: 183007 | AF27: 47318.8 | AG27: 33233.25 | AH27: 34566 | AJ27: 5478 | AK27: -2292 | AL27: 118304 | AM27: 301311 | AN27: 7571
A28: MSFT | B28: 43830 | C28: 11356 | D28: 133819 | E28: 29524 | F28: 2063 | H28: 10146 | I28: 175552 | J28: 79186 | K28: -35330 | L28: 43856 | M28: 42026 | N28: 7750 | O28: 2649 | P28: 2200 | Q28: 12523 | R28: 286556 | S28: 9382 | T28: 8345 | U28: 5833 | V28: 0 | W28: 45860 | X28: 69420 | Y28: 66662 | Z28: 6257 | AA28: 72919 | AB28: 233 | AC28: 41654 | AE28: 184226 | AF28: 49679.5 | AG28: 28840.5 | AH28: 24150 | AJ28: 1488 | AK28: -1828 | AL28: 102330 | AM28: 286556 | AN28: 7643
A29: MSFT | B29: 43465 | C29: 11946 | D29: 133650 | E29: 26481 | F29: 2662 | H29: 6869 | I29: 169662 | J29: 65369 | K29: -29223 | L29: 36146 | M29: 35683 | N29: 8053 | O29: 1862 | P29: 1800 | Q29: 5642 | R29: 258848 | S29: 8617 | T29: 7502 | U29: 4174 | V29: 0 | W29: 38195 | X29: 58488 | Y29: 72242 | Z29: 4125 | AA29: 76367 | AB29: 541 | AC29: 40734 | AE29: 176130 | AF29: 47981.2 | AG29: 23241.75 | AH29: 13682 | AJ29: -892 | AK29: -1295 | AL29: 82718 | AM29: 258848 | AN29: 7677
A30: MSFT | B30: 43100 | C30: 7663 | D30: 132881 | E30: 22431 | F30: 2181 | H30: 5203 | I30: 162696 | J30: 54468 | K30: -24179 | L30: 30289 | M30: 35122 | N30: 10106 | O30: 5956 | Q30: 6143 | R30: 250312 | S30: 7390 | T30: 5819 | U30: 1162 | V30: 9072 | W30: 32302 | X30: 55745 | Y30: 76073 | Z30: 2425 | AA30: 78498 | AB30: 5734 | AC30: 22624 | AE30: 162601 | AF30: 48175 | AG30: 21140 | AH30: 17769 | AJ30: 1825 | AK30: -1198 | AL30: 87711 | AM30: 250312 | AN30: 7708
A31: MSFT | B31: 42735 | C31: 6510 | D31: 113167 | E31: 18277 | F31: 2251 | H31: 5965 | I31: 139660 | J31: 38156 | K31: -19800 | L31: 18356 | M31: 17872 | N31: 3733 | O31: 10413 | Q31: 3434 | R31: 193468 | S31: 6898 | T31: 5264 | U31: 25 | V31: 12904 | W31: 34266 | X31: 59357 | Y31: 40557 | Z31: 761 | AA31: 41318 | AB31: 1476 | AC31: 19320 | AE31: 121471 | AF31: 48800 | AG31: 19378 | AH31: 2282 | AJ31: 2941 | AK31: -1404 | AL31: 71997 | AM31: 193468 | AN31: 7808
A32: MSFT | B32: 42369 | C32: 5595 | D32: 96282 | E32: 17908 | F32: 2902 | H32: 5705 | I32: 122797 | J32: 32337 | K32: -17606 | L32: 14731 | M32: 16939 | N32: 4835 | O32: 12028 | Q32: 3142 | R32: 174472 | S32: 6591 | T32: 5096 | U32: 2499 | V32: 4985 | W32: 30476 | X32: 49647 | Y32: 27808 | AA32: 27808 | AB32: 1295 | AC32: 15639 | AE32: 94389 | AF32: 50168.8 | AG32: 18296.25 | AH32: 9096 | AJ32: 3169 | AK32: -647 | AL32: 80083 | AM32: 174472 | AN32: 8027
A33: MSFT | B33: 42004 | C33: 8669 | D33: 85465 | E33: 19544 | F33: 2660 | H33: 6577 | I33: 114246 | J33: 27804 | K33: -14793 | L33: 13011 | M33: 20127 | N33: 6981 | O33: 14590 | Q33: 3429 | R33: 172384 | S33: 7432 | T33: 4797 | U33: 0 | V33: 2000 | W33: 31396 | X33: 45625 | Y33: 20645 | AA33: 20645 | AB33: 2728 | AC33: 13602 | AE33: 82600 | AF33: 51493.8 | AG33: 16872.25 | AH33: 17710 | AJ33: 3531 | AK33: 177 | AL33: 89784 | AM33: 172384 | AN33: 8239
A34: MSFT | B34: 41639 | C34: 3804 | D34: 76775 | E34: 17486 | F34: 1938 | H34: 5267 | I34: 101466 | J34: 22504 | K34: -12513 | L34: 9991 | M34: 14655 | N34: 3083 | O34: 10844 | Q34: 2392 | R34: 142431 | S34: 4828 | T34: 4117 | U34: 2999 | V34: 0 | W34: 25473 | X34: 37417 | Y34: 12601 | AA34: 12601 | AB34: 1709 | AC34: 11760 | AE34: 63487 | AF34: 52050 | AG34: 15256 | AH34: 9895 | AJ34: 1794 | AK34: -51 | AL34: 78944 | AM34: 142431 | AN34: 8328
A35: MSFT | B35: 41274 | C35: 6938 | D35: 63040 | E35: 15780 | F35: 1137 | H35: 5127 | I35: 85084 | J35: 19231 | K35: -10962 | L35: 8269 | M35: 13452 | N35: 3170 | O35: 9776 | Q35: 1520 | R35: 121271 | S35: 4175 | T35: 3875 | U35: 1231 | V35: 0 | W35: 23407 | X35: 32688 | Y35: 10713 | AA35: 10713 | AB35: 1893 | AC35: 9614 | AE35: 54908 | AF35: 65797 | AH35: -856 | AJ35: 1431 | AK35: -9 | AL35: 66363 | AM35: 121271 | AN35: 8381
A36: MSFT | B36: 40908 | C36: 9610 | D36: 52772 | E36: 14987 | F36: 1372 | H36: 5787 | I36: 74918 | J36: 17991 | K36: -9829 | L36: 8162 | M36: 12581 | N36: 744 | O36: 10865 | Q36: 1434 | R36: 108704 | S36: 4197 | T36: 3575 | U36: 0 | V36: 0 | W36: 21002 | X36: 28774 | Y36: 11921 | AA36: 11921 | AB36: 1456 | AC36: 9470 | AE36: 51621 | AF36: 63415 | AH36: -8195 | AJ36: 1821 | AK36: 42 | AL36: 57083 | AM36: 108704 | AN36: 8376
A37: MSFT | B37: 40543 | C37: 5505 | D37: 36788 | E37: 13014 | F37: 740 | H37: 5134 | I37: 55676 | J37: 16259 | K37: -8629 | L37: 7630 | M37: 12394 | N37: 1158 | O37: 7754 | Q37: 1501 | R37: 86113 | S37: 4025 | T37: 3283 | U37: 0 | V37: 1000 | W37: 17839 | X37: 26147 | Y37: 4939 | AA37: 4939 | AB37: 229 | AC37: 8623 | AE37: 39938 | AF37: 62856 | AH37: -17736 | AJ37: 767 | AK37: 288 | AL37: 46175 | AM37: 86113 | AN37: 8668
A38: MSFT | B38: 40178 | C38: 6076 | D38: 31447 | E38: 11192 | F38: 717 | H38: 5924 | I38: 49280 | J38: 15082 | K38: -7547 | L38: 7535 | M38: 12503 | N38: 1759 | O38: 4933 | Q38: 1878 | R38: 77888 | S38: 3324 | T38: 3156 | U38: 0 | V38: 2000 | W38: 18554 | X38: 27034 | Y38: 3746 | AA38: 3746 | AB38: 0 | AC38: 7550 | AE38: 38330 | AF38: 62382 | AH38: -23793 | AJ38: 502 | AK38: 467 | AL38: 39558 | AM38: 77888 | AN38: 8908
A39: MSFT | B39: 39813 | C39: 10339 | D39: 23662 | E39: 13589 | F39: 985 | H39: 5006 | I39: 43242 | J39: 12544 | K39: -6302 | L39: 6242 | M39: 12108 | N39: 1973 | O39: 6588 | Q39: 2640 | R39: 72793 | S39: 4034 | T39: 2934 | U39: 0 | V39: 0 | W39: 22918 | X39: 29886 | Y39: 0 | AA39: 0 | AC39: 6621 | AE39: 36507 | AF39: 62849 | AH39: -27703 | AK39: 1140 | AL39: 36286 | AM39: 72793 | AN39: 9151
A40: MSFT | B40: 39447 | C40: 6111 | D40: 23411 | E40: 11338 | F40: 1127 | H40: 4292 | I40: 40168 | J40: 9366 | K40: -5016 | L40: 4350 | M40: 4760 | N40: 878 | O40: 10117 | Q40: 2898 | R40: 63171 | S40: 3247 | T40: 2325 | U40: 0 | V40: 0 | W40: 18182 | X40: 23754 | AA40: 0 | AC40: 8320 | AE40: 32074 | AF40: 60557 | AH40: -31114 | AK40: 1654 | AL40: 31097 | AM40: 63171 | AN40: 9380
A41: MSFT | B41: 39082 | C41: 6714 | D41: 34161 | E41: 9316 | F41: 1478 | H41: 4055 | I41: 49010 | J41: 7223 | K41: -4179 | L41: 3044 | M41: 3866 | N41: 539 | O41: 9232 | Q41: 3906 | R41: 69597 | S41: 2909 | T41: 1938 | U41: 0 | V41: 0 | W41: 17595 | X41: 22442 | AA41: 0 | AC41: 7051 | AE41: 29493 | AF41: 59005 | AH41: -20130 | AK41: 1229 | AL41: 40104 | AM41: 69597 | AN41: 10062
A42: GOOG | B42: 46022 | C42: 30708 | D42: 126843 | E42: 62886 | H42: 16309 | I42: 206038 | J42: 360303 | K42: -98485 | L42: 261818 | M42: 33380 | O42: 68687 | Q42: 25358 | R42: 595281 | S42: 12200 | T42: 53599 | U42: 2437 | V42: 0 | W42: 34509 | X42: 102745 | Y42: 46547 | Z42: 2059 | AA42: 48606 | AC42: 28665 | AE42: 180016 | AF42: 12.1 | AG42: 93113.912 | AH42: 324055 | AJ42: 678 | AK42: -2594 | AL42: 415265 | AM42: 595281 | AN42: 12088
A43: GOOG | B43: 45657 | C43: 23466 | D43: 95657 | E43: 52340 | H43: 15714 | I43: 163711 | J43: 264014 | K43: -79390 | L43: 184624 | M43: 31885 | O43: 37982 | Q43: 32054 | R43: 450256 | S43: 7987 | T43: 55836 | U43: 1234 | V43: 0 | W43: 24065 | X43: 89122 | Y43: 10883 | Z43: 1442 | AA43: 12325 | AC43: 23725 | AE43: 125172 | AF43: 12.2 | AG43: 84787.789 | AH43: 245084 | AJ43: -299 | AK43: -4501 | AL43: 325084 | AM43: 450256 | AN43: 12211
A44: GOOG | B44: 45291 | C44: 24048 | D44: 110916 | E44: 47964 | H44: 12650 | I44: 171530 | J44: 215894 | K44: -67458 | L44: 148436 | M44: 29198 | O44: 31008 | Q44: 22220 | R44: 402392 | S44: 7493 | T44: 47672 | U44: 1363 | V44: 0 | W44: 25286 | X44: 81814 | Y44: 11870 | Z44: 1383 | AA44: 13253 | AB44: 485 | AC44: 23461 | AE44: 119013 | AF44: 12.5 | AG44: 76521.546 | AH44: 211247 | AJ44: -965 | AK44: -3437 | AL44: 283379 | AM44: 402392 | AN44: 12460
A45: GOOG | B45: 44926 | C45: 21879 | D45: 113762 | E45: 40258 | F45: 2670 | H45: 8105 | I45: 164795 | J45: 186091 | K45: -59042 | L45: 127049 | M45: 28960 | N45: 2084 | O45: 30492 | Q45: 11884 | R45: 365264 | S45: 5128 | T45: 42490 | U45: 298 | V45: 0 | W45: 21384 | X45: 69300 | Y45: 12857 | Z45: 1844 | AA45: 14701 | AB45: 514 | AC45: 24605 | AE45: 109120 | AF45: 12.8 | AG45: 68171.151 | AH45: 195563 | AJ45: -3477 | AK45: -4126 | AL45: 256144 | AM45: 365264 | AN45: 12849
A46: GOOG | B46: 44561 | C46: 20945 | D46: 139649 | E46: 40270 | F46: 1170 | H46: 7054 | I46: 188143 | J46: 159971 | K46: -49414 | L46: 110558 | M46: 22956 | N46: 1417 | O46: 29549 | Q46: 6645 | R46: 359268 | S46: 6037 | T46: 35213 | U46: 113 | V46: 0 | W46: 22891 | X46: 64254 | Y46: 12841 | Z46: 1976 | AA46: 14817 | AB46: 5257 | AC46: 23305 | AE46: 107633 | AF46: 0.7 | AG46: 61773.338 | AH46: 191484 | AJ46: 236 | AK46: -1859 | AL46: 251635 | AM46: 359268 | AN46: 13242
A47: GOOG | B47: 44196 | C47: 26465 | D47: 136694 | E47: 31384 | F47: 728 | H47: 5490 | I47: 174296 | J47: 138673 | K47: -41713 | L47: 96960 | M47: 21175 | N47: 1445 | O47: 20703 | Q47: 5037 | R47: 319616 | S47: 5589 | T47: 28208 | U47: 1100 | V47: 0 | W47: 21937 | X47: 56834 | Y47: 12832 | Z47: 1100 | AA47: 13932 | AB47: 3561 | AC47: 22745 | AE47: 97072 | AF47: 0.7 | AG47: 58509.325 | AH47: 163401 | AJ47: 1612 | AK47: -979 | AL47: 222544 | AM47: 319616 | AN47: 13504
A48: GOOG | B48: 43830 | C48: 18498 | D48: 119675 | E48: 27492 | F48: 999 | H48: 4412 | I48: 152578 | J48: 115148 | K48: -30561 | L48: 84587 | M48: 20624 | N48: 1979 | O48: 13078 | Q48: 3063 | R48: 275909 | S48: 5561 | T48: 19543 | U48: 0 | V48: 0 | W48: 20117 | X48: 45221 | Y48: 3869 | Z48: 685 | AA48: 4554 | AB48: 1701 | AC48: 22991 | AE48: 74467 | AF48: 0.7 | AG48: 50551.312 | AH48: 152122 | AJ48: 812 | AK48: -2044 | AL48: 201442 | AM48: 275909 | AN48: 13767
A49: GOOG | B49: 43465 | C49: 16701 | D49: 109140 | E49: 21193 | F49: 1107 | H49: 4236 | I49: 135676 | J49: 82507 | K49: -22788 | L49: 59719 | M49: 17888 | N49: 2220 | O49: 13859 | Q49: 3430 | R49: 232792 | S49: 4378 | T49: 14000 | U49: 0 | V49: 0 | W49: 16242 | X49: 34620 | Y49: 3950 | Z49: 62 | AA49: 4012 | AB49: 1264 | AC49: 15268 | AE49: 55164 | AF49: 0.7 | AG49: 45048.304 | AH49: 134885 | AJ49: -688 | AK49: -1618 | AL49: 177628 | AM49: 232792 | AN49: 13911
A50: GOOG | B50: 43100 | C50: 3557 | D50: 101871 | E50: 18705 | F50: 749 | H50: 2983 | I50: 124308 | J50: 59647 | K50: -17264 | L50: 42383 | M50: 16747 | N50: 2692 | O50: 7813 | Q50: 3352 | R50: 197295 | S50: 3137 | T50: 14406 | U50: 0 | V50: 0 | W50: 6640 | X50: 24183 | Y50: 3943 | Z50: 26 | AA50: 3969 | AB50: 430 | AC50: 16211 | AE50: 44793 | AF50: 0.7 | AG50: 40246.305 | AH50: 113247 | AJ50: 233 | AK50: -1225 | AL50: 152502 | AM50: 197295 | AN50: 13896
A51: GOOG | B51: 42735 | C51: 5840 | D51: 86333 | E51: 14232 | F51: 268 | G51: 3979 | H51: 596 | I51: 105408 | J51: 47527 | K51: -13293 | L51: 34234 | M51: 16468 | N51: 3307 | O51: 5878 | Q51: 2202 | R51: 167497 | S51: 2041 | T51: 10107 | U51: 0 | V51: 0 | W51: 4608 | X51: 16756 | Y51: 3935 | AA51: 3935 | AB51: 226 | AC51: 7544 | AE51: 28461 | AF51: 0.7 | AG51: 36306.309 | AH51: 105131 | AJ51: -179 | AK51: -2223 | AL51: 139036 | AM51: 167497 | AN51: 13826
A52: GOOG | B52: 42369 | C52: 9169 | D52: 73066 | E52: 13909 | G52: 2511 | H52: 628 | I52: 90114 | J52: 40146 | K52: -11130 | L52: 29016 | M52: 15869 | N52: 3847 | O52: 5183 | Q52: 3432 | R52: 147461 | S52: 1931 | T52: 8293 | U52: 1225 | V52: 2000 | W52: 5861 | X52: 19310 | Y52: 1995 | Z52: 0 | AA52: 1995 | AB52: 189 | AC52: 5636 | AE52: 27130 | AF52: 0.7 | AG52: 32981.313 | AH52: 89223 | AJ52: -86 | AK52: -1788 | AL52: 120331 | AM52: 147461 | AN52: 13747
A53: GOOG | B53: 42004 | C53: 8484 | D53: 64395 | E53: 10849 | G53: 2560 | H53: 852 | I53: 78656 | J53: 32746 | K53: -8863 | L53: 23883 | M53: 15599 | N53: 4607 | O53: 3079 | Q53: 3363 | R53: 129187 | S53: 1715 | T53: 7473 | U53: 9 | V53: 2000 | W53: 5582 | X53: 16779 | Y53: 2992 | Z53: 236 | AA53: 3228 | AB53: 758 | AC53: 4562 | AE53: 25327 | AF53: 0.7 | AG53: 28766.32 | AH53: 75066 | AJ53: 421 | AK53: -394 | AL53: 103860 | AM53: 129187 | AN53: 13603
A54: GOOG | B54: 41639 | C54: 8989 | D54: 58717 | E54: 9390 | F54: 426 | G54: 2595 | H54: 1758 | I54: 72886 | J54: 23837 | K54: -7313 | L54: 16524 | M54: 11492 | N54: 6066 | O54: 1976 | Q54: 1976 | R54: 110920 | S54: 2453 | T54: 6253 | U54: 9 | V54: 3000 | W54: 4193 | X54: 15908 | Y54: 1990 | Z54: 246 | AA54: 2236 | AB54: 1947 | AC54: 3520 | AE54: 23611 | AF54: 0.3 | AG54: 25921.67 | AH54: 61262 | AJ54: 50 | AK54: 75 | AL54: 87309 | AM54: 110920 | AN54: 13420
A55: GOOG | B55: 41274 | C55: 6712 | D55: 48088 | E55: 8585 | F55: 505 | G55: 2132 | H55: 1144 | I55: 60454 | J55: 17697 | K55: -5843 | L55: 11854 | M55: 10537 | N55: 7473 | O55: 1469 | Q55: 2011 | R55: 93798 | S55: 2012 | T55: 5497 | U55: 2549 | V55: 0 | W55: 4279 | X55: 14337 | Y55: 2988 | AA55: 2988 | AB55: 1872 | AC55: 2886 | AE55: 22083 | AF55: 0.3 | AG55: 22834.67 | AH55: 48342 | AJ55: 604 | AK55: -66 | AL55: 71715 | AM55: 93798 | AN55: 13199
A56: GOOG | B56: 40908 | C56: 4712 | D56: 44626 | E56: 6172 | G56: 1745 | H56: 215 | I56: 52758 | J56: 14400 | K56: -4797 | L56: 9603 | M56: 7346 | N56: 1578 | O56: 790 | Q56: 499 | R56: 72574 | S56: 588 | T56: 3188 | U56: 1218 | V56: 0 | W56: 3919 | X56: 8913 | Y56: 2986 | AA56: 2986 | AB56: 287 | AC56: 2243 | AE56: 14429 | AF56: 0.3 | AG56: 20263.675 | AH56: 37605 | AJ56: 327 | AK56: -51 | AL56: 58145 | AM56: 72574 | AN56: 12996
A57: GOOG | B57: 40543 | C57: 4652 | D57: 34975 | E57: 5002 | G57: 1326 | H57: 259 | I57: 41562 | J57: 11771 | K57: -4012 | L57: 7759 | M57: 6256 | N57: 1044 | O57: 523 | Q57: 707 | R57: 57851 | S57: 483 | T57: 2371 | U57: 3465 | V57: 0 | W57: 3677 | X57: 9996 | Y57: 0 | AA57: 0 | AB57: 0 | AC57: 1614 | AE57: 11610 | AF57: 0.3 | AG57: 18234.679 | AH57: 27868 | AJ57: 94 | AK57: 44 | AL57: 46241 | AM57: 57851 | AN57: 12852
A58: GOOG | B58: 40178 | C58: 4302.578 | D58: 24484.775 | E58: 3201.715 | G58: 836.1 | H58: 644.4 | I58: 29166.958 | J58: 8130.1 | K58: -3285.524 | L58: 4844.6 | M58: 4902.565 | N58: 774.938 | O58: 129 | Q58: 678.7 | R58: 40496.778 | S58: 215.867 | T58: 1552.6 | U58: 0 | V58: 0 | W58: 979 | X58: 2747.467 | AA58: 0 | AB58: 0 | AC58: 1745.1 | AE58: 4492.554 | AF58: 0.3 | AG58: 15816.738 | AH58: 20082.078 | AK58: 105.09 | AL58: 36004.224 | AM58: 40496.778 | AN58: 12711
A59: GOOG | B59: 39813 | C59: 3330.658 | D59: 15845.771 | E59: 2642.192 | G59: 1404.1 | H59: 286.1 | I59: 20178.182 | J59: 7576.3 | K59: -2342.498 | L59: 5233.8 | M59: 4839.854 | N59: 996.69 | O59: 85.2 | Q59: 433.8 | R59: 31767.575 | S59: 178.004 | T59: 1291.9 | U59: 0 | V59: 0 | W59: 832.2 | X59: 2302.09 | AA59: 0 | AB59: 12.515 | AC59: 1214.1 | AE59: 3528.713 | AF59: 0.3 | AG59: 14450.338 | AH59: 13561.63 | AK59: 226.579 | AL59: 28238.862 | AM59: 31767.575 | AN59: 12605
A60: GOOG | B60: 39447 | C60: 2869.528 | D60: 14218.613 | E60: 2307.774 | G60: 694.2 | H60: 68.5 | I60: 17289.138 | J60: 5519.9 | K60: -1480.651 | L60: 4039.3 | M60: 2299.368 | N60: 446.596 | O60: 1059.7 | Q60: 201.7 | R60: 25335.806 | S60: 282.106 | T60: 1053.4 | U60: 0 | V60: 0 | W60: 700.1 | X60: 2035.602 | AA60: 0 | AB60: 0 | AC60: 610.5 | AE60: 2646.127 | AF60: 0.3 | AG60: 13241.221 | AH60: 9334.772 | AK60: 113.373 | AL60: 22689.679 | AM60: 25335.806 | AN60: 12531
A61: GOOG | B61: 39082 | C61: 2996.603 | D61: 11243.914 | E61: 1322.34 | G61: 443.9 | H61: 29.7 | I61: 13039.847 | J61: 3289.6 | K61: -894.355 | L61: 2395.2 | M61: 1545.119 | N61: 346.841 | O61: 1031.8 | Q61: 114.5 | R61: 18473.351 | S61: 211.169 | T61: 617.5 | U61: 0 | V61: 0 | W61: 475.9 | X61: 1304.587 | AA61: 0 | AB61: 40.421 | AC61: 88.5 | AE61: 1433.511 | AF61: 0.3 | AG61: 11882.906 | AH61: 5133.314 | AK61: 23.311 | AL61: 17039.84 | AM61: 18473.351 | AN61: 12360
A62: META | B62: 46022 | C62: 31482 | D62: 81592 | E62: 19769 | G62: 6524 | H62: 837 | I62: 108722 | J62: 254130 | K62: -57326 | L62: 196804 | M62: 24534 | N62: 3692 | O62: 27524 | Q62: 4745 | R62: 366021 | S62: 8894 | T62: 20633 | U62: 308 | V62: 0 | W62: 12001 | X62: 41836 | Y62: 58744 | Z62: 876 | AA62: 59620 | AC62: 47322 | AE62: 148778 | AF62: 0 | AG62: 95793 | AH62: 121179 | AK62: 270.985 | AL62: 217243 | AM62: 366021 | AN62: 2530
A63: META | B63: 45657 | C63: 36671 | D63: 77815 | E63: 16994 | G63: 4883 | H63: 353 | I63: 100045 | J63: 179585 | K63: -43317 | L63: 136268 | M63: 20654 | N63: 915 | O63: 6070 | Q63: 12102 | R63: 276054 | S63: 7687 | T63: 16397 | U63: 76 | V63: 0 | W63: 9436 | X63: 33596 | Y63: 28826 | Z63: 633 | AA63: 29459 | AC63: 30362 | AE63: 93417 | AF63: 0 | AG63: 83228 | AH63: 102506 | AK63: -3097.015 | AL63: 182637 | AM63: 276054 | AN63: 2534
A64: META | B64: 45291 | C64: 35597 | D64: 65403 | E64: 16169 | G64: 3694 | H64: 99 | I64: 85365 | J64: 143015 | K64: -33134 | L64: 109881 | M64: 20654 | N64: 788 | O64: 6141 | Q64: 6794 | R64: 229623 | S64: 5712 | T64: 17087 | U64: 90 | V64: 0 | W64: 9071 | X64: 31960 | Y64: 18385 | Z64: 600 | AA64: 18985 | AC64: 25510 | AE64: 76455 | AF64: 0 | AG64: 73253 | AH64: 82070 | AK64: -2155.015 | AL64: 153168 | AM64: 229623 | AN64: 2561
A65: META | B65: 44926 | C65: 8505 | D65: 40738 | E65: 13466 | G65: 5051 | H65: 294 | I65: 59549 | J65: 117166 | K65: -24975 | L65: 92191 | M65: 20306 | N65: 897 | O65: 6201 | Q65: 6583 | R65: 185727 | S65: 6107 | T65: 13674 | U65: 129 | V65: 0 | W65: 7116 | X65: 27026 | Y65: 9923 | Z65: 558 | AA65: 10481 | AC65: 22507 | AE65: 60014 | AF65: 0 | AG65: 64444 | AH65: 64799 | AK65: -3530.038 | AL65: 125713 | AM65: 185727 | AN65: 2614
A66: META | B66: 44561 | C66: 9293 | D66: 47998 | E66: 14039 | G66: 4480 | H66: 149 | I66: 66666 | J66: 90044 | K66: -20080 | L66: 69964 | M66: 19197 | N66: 634 | O66: 6775 | Q66: 2751 | R66: 165987 | S66: 5135 | T66: 8925 | U66: 75 | V66: 0 | W66: 7000 | X66: 21135 | Z66: 506 | AA66: 506 | AC66: 19467 | AE66: 41108 | AF66: 0 | AG66: 55811 | AH66: 69761 | AK66: -693.017 | AL66: 124879 | AM66: 165987 | AN66: 2741
A67: META | B67: 44196 | C67: 11088 | D67: 61954 | E67: 11335 | G67: 2140 | H67: 241 | I67: 75670 | J67: 70399 | K67: -15418 | L67: 54981 | M67: 19050 | N67: 623 | O67: 6234 | Q67: 2758 | R67: 159316 | S67: 2424 | T67: 6668 | U67: 54 | V67: 0 | W67: 5835 | X67: 14981 | Z67: 469 | AA67: 469 | AC67: 15576 | AE67: 31026 | AF67: 0 | AG67: 50018 | AH67: 77345 | AK67: 926.983 | AL67: 128290 | AM67: 159316 | AN67: 2849
A68: META | B68: 43830 | C68: 14344 | D68: 54855 | E68: 9518 | G68: 1844 | H68: 8 | I68: 66225 | J68: 55446 | K68: -10663 | L68: 44783 | M68: 18715 | N68: 894 | O68: 86 | Q68: 2673 | R68: 133376 | S68: 2249 | T68: 9136 | U68: 55 | V68: 0 | W68: 3613 | X68: 15053 | Z68: 418 | AA68: 418 | AB68: 1039 | AC68: 15812 | AE68: 32322 | AF68: 0 | AG68: 45851 | AH68: 55692 | AK68: -489.017 | AL68: 101054 | AM68: 133376 | AN68: 2852
A69: META | B69: 43465 | C69: 7306 | D69: 41114 | E69: 7587 | G69: 1779 | I69: 50480 | J69: 31573 | K69: -6890 | L69: 24683 | M69: 18301 | N69: 1294 | Q69: 2576 | R69: 97334 | S69: 1361 | T69: 2734 | U69: 0 | V69: 0 | W69: 2922 | X69: 7017 | AA69: 0 | AB69: 673 | AC69: 5517 | AE69: 13207 | AF69: 0 | AG69: 42906 | AH69: 41981 | AK69: -760 | AL69: 84127 | AM69: 97334 | AN69: 2854
A70: META | B70: 43100 | C70: 5867 | D70: 41711 | E70: 5832 | G70: 1020 | I70: 48563 | J70: 18337 | K70: -4616 | L70: 13721 | M70: 18221 | N70: 1884 | Q70: 2135 | R70: 84524 | S70: 770 | T70: 1461 | U70: 0 | V70: 0 | W70: 1529 | X70: 3760 | AA70: 0 | AC70: 6417 | AE70: 10177 | AF70: 0 | AG70: 40584 | AH70: 33990 | AJ70: -211 | AK70: -16 | AL70: 74347 | AM70: 84524 | AN70: 2906
A71: META | B71: 42735 | C71: 7539 | D71: 29449 | E71: 3993 | G71: 959 | I71: 34401 | J71: 11803 | K71: -3212 | L71: 8591 | M71: 18122 | N71: 2535 | Q71: 1312 | R71: 64961 | S71: 582 | T71: 1209 | U71: 0 | V71: 0 | W71: 1084 | X71: 2875 | Z71: 0 | AA71: 0 | AC71: 2892 | AE71: 5767 | AF71: 0 | AG71: 38227 | AH71: 21670 | AJ71: -121 | AK71: -582 | AL71: 59194 | AM71: 64961 | AN71: 2892
A72: META | B72: 42369 | C72: 3204 | D72: 18434 | E72: 2559 | G72: 659 | I72: 21652 | J72: 7819 | K72: -2132 | L72: 5687 | M72: 18026 | N72: 3246 | Q72: 796 | R72: 49407 | S72: 413 | T72: 665 | U72: 7 | V72: 201 | W72: 639 | X72: 1925 | Z72: 107 | AA72: 107 | AB72: 163 | AC72: 2994 | AE72: 5189 | AF72: 0 | AG72: 34886 | AH72: 9787 | AJ72: -25 | AK72: -430 | AL72: 44218 | AM72: 49407 | AN72: 2845
A73: META | B73: 42004 | C73: 2153 | D73: 11199 | E73: 1678 | G73: 513 | I73: 13390 | J73: 5784 | K73: -1817 | L73: 3967 | M73: 17981 | N73: 3929 | Q73: 699 | R73: 39966 | S73: 378 | T73: 486 | U73: 114 | V73: 0 | W73: 446 | X73: 1424 | Z73: 119 | AA73: 119 | AB73: 769 | AC73: 1558 | AE73: 3870 | AF73: 0 | AG73: 30225 | AH73: 6099 | AJ73: -1 | AK73: -227 | AL73: 36096 | AM73: 39966 | AN73: 2797
A74: META | B74: 41639 | C74: 2279 | D74: 11449 | E74: 1160 | G74: 461 | I74: 13070 | J74: 4142 | K74: -1260 | L74: 2882 | M74: 839 | N74: 883 | Q74: 221 | R74: 17895 | S74: 268 | T74: 555 | U74: 239 | V74: 0 | W74: 38 | X74: 1100 | Y74: 0 | Z74: 237 | AA74: 237 | AC74: 1088 | AE74: 2425 | AF74: 0 | AG74: 12297 | AH74: 3159 | AK74: 14 | AL74: 15470 | AM74: 17895 | AN74: 2547
A75: META | B75: 41274 | C75: 871 | D75: 9626 | E75: 1170 | G75: 471 | I75: 11267 | J75: 3273 | K75: -882 | L75: 2391 | M75: 587 | N75: 801 | Q75: 57 | R75: 15103 | S75: 234 | T75: 423 | U75: 365 | V75: 0 | W75: 30 | X75: 1052 | Y75: 1500 | Z75: 491 | AA75: 1991 | AC75: 305 | AE75: 3348 | AF75: 0 | AG75: 10094 | AH75: 1659 | AK75: 2 | AL75: 11755 | AM75: 15103 | AN75: 2373
A76: META | B76: 40908 | C76: 1512 | D76: 3908 | E76: 547 | G76: 149 | I76: 4604 | J76: 1925 | K76: -450 | L76: 1475 | M76: 82 | N76: 80 | Q76: 90 | R76: 6331 | S76: 234 | U76: 279 | V76: 0 | W76: 386 | X76: 899 | Y76: 0 | Z76: 398 | AA76: 398 | AC76: 135 | AE76: 1432 | AF76: 0 | AG76: 2684 | AH76: 1606 | AK76: -6 | AL76: 4899 | AM76: 6331 | AN76: 2138
A77: META | B77: 40543 | C77: 1785 | D77: 1785 | E77: 373 | G77: 88 | I77: 2246 | J77: 820 | K77: -246 | L77: 574 | M77: 37 | N77: 59 | Q77: 74 | R77: 2990 | S77: 104 | U77: 106 | V77: 0 | W77: 179 | X77: 389 | Y77: 250 | Z77: 117 | AA77: 367 | AC77: 72 | AE77: 828 | AF77: 0 | AG77: 947 | AH77: 606 | AK77: -6 | AL77: 2162 | AM77: 2990 | AN77: 2138
A78: META | B78: 40178 | C78: 633 | D78: 633 | L78: 148 | R78: 1109 | U78: 0 | V78: 0 | AA78: 0 | AC78: 241 | AE78: 241 | AL78: 868 | AM78: 1109 | AN78: 2138
A79: META | B79: 39813 | C79: 297 | D79: 297 | L79: 131 | R79: 505 | U79: 0 | V79: 0 | AA79: 0 | AC79: 170 | AE79: 170 | AL79: 335 | AM79: 505 | AN79: 2138
A80: META | B80: 39447 | C80: 305 | D80: 305 | L80: 82 | R80: 448 | U80: 0 | V80: 0 | AA80: 0 | AC80: 174 | AE80: 174 | AL80: 273 | AM80: 448 | AN80: 2138

Sheet Cash Flow
A1: Ticker | B1: FY | C1: Net Income | D1: Changes in Working Capital | E1: Cash from Operating Activities | F1: Capital Expenditures | G1: Sale of Fixed Assets | H1: Acquisition of Business | I1: Sale/Maturity of Investment | J1: Other Investing Cash Flow Items, Total | K1: Cash from Investing Activities | L1: Short Term Debt | M1: Issuance (Retirement) of Debt | N1: Issuance (Retirement) of Stock | O1: Total Cash Dividends Paid | P1: Cash from Financing Activities | Q1: Foreign Exchange Effects | R1: Net Change in Cash | S1: Net Cash - Beginning Balance | T1: Net Cash - Ending Balance
A2: AMZN | B2: 46022 | C2: 77670 | D2: -19969 | E2: 139514 | F2: -131819 | G2: 3499 | H2: -3841 | I2: 44386 | J2: -10726 | K2: -142545 | L2: 894 | M2: 9661 | P2: 9661 | Q2: 1164 | R2: 7794 | S2: 82312 | T2: 90106
A3: AMZN | B3: 45657 | C3: 59248 | D3: -15541 | E3: 115877 | F3: -82999 | G3: 5341 | H3: -7082 | I3: 16403 | J3: -11343 | K3: -94342 | L3: 82 | M3: -11812 | N3: 0 | P3: -11812 | Q3: -1301 | R3: 8422 | S3: 73890 | T3: 82312
A4: AMZN | B4: 45291 | C4: 30425 | D4: -11541 | E4: 84946 | F4: -52729 | G4: 4596 | H4: -5839 | I4: 5627 | J4: 2896 | K4: -49833 | L4: -7548 | M4: -15879 | N4: 0 | P4: -15879 | Q4: 403 | R4: 19637 | S4: 54253 | T4: 73890
A5: AMZN | B5: 44926 | C5: -2722 | D5: -20886 | E5: 46752 | F5: -63645 | G5: 5324 | H5: -8316 | I5: 31601 | J5: 26044 | K5: -37601 | L5: 3999 | M5: 15718 | N5: -6000 | P5: 9718 | Q5: -1093 | R5: 17776 | S5: 36477 | T5: 54253
A6: AMZN | B6: 44561 | C6: 33364 | D6: -19611 | E6: 46327 | F6: -61053 | G6: 5657 | H6: -1985 | I6: 59384 | J6: 2899 | K6: -58154 | L6: 203 | M6: 6291 | P6: 6291 | Q6: -364 | R6: -5900 | S6: 42377 | T6: 36477
A7: AMZN | B7: 44196 | C7: 21331 | D7: 13481 | E7: 66064 | F7: -40140 | G7: 5096 | H7: -2325 | I7: 50237 | J7: -19471 | K7: -59611 | L7: 619 | M7: -1104 | P7: -1104 | Q7: 618 | R7: 5967 | S7: 36410 | T7: 42377
A8: AMZN | B8: 43830 | C8: 11588 | D8: -2438 | E8: 38514 | F8: -16861 | G8: 4172 | H8: -2461 | I8: 22681 | J8: -7420 | K8: -24281 | M8: -10066 | P8: -10066 | Q8: 70 | R8: 4237 | S8: 32173 | T8: 36410
A9: AMZN | B9: 43465 | C9: 10073 | D9: -1043 | E9: 30723 | F9: -13427 | G9: 2104 | H9: -2186 | I9: 8240 | J9: 1058 | K9: -12369 | M9: -7686 | P9: -7686 | Q9: -351 | R9: 10317 | S9: 21856 | T9: 32173
A10: AMZN | B10: 43100 | C10: 3033 | D10: -242 | E10: 18365 | F10: -11955 | G10: 1897 | H10: -13972 | I10: 9677 | J10: -15129 | K10: -27084 | M10: 9928 | P10: 9928 | Q10: 713 | R10: 1922 | S10: 19934 | T10: 21856
A11: AMZN | B11: 42735 | C11: 2371 | D11: 3847 | E11: 17203 | F11: -7804 | G11: 1067 | H11: -116 | I11: 4577 | J11: -1712 | K11: -9516 | M11: -3716 | P11: -3716 | Q11: -212 | R11: 3759 | S11: 16175 | T11: 19934
A12: AMZN | B12: 42369 | C12: 596 | D12: 2557 | E12: 11920 | F12: -4589 | H12: -795 | I12: 3025 | J12: -1861 | K12: -6450 | M12: -3882 | P12: -3763 | Q12: -374 | R12: 1333 | S12: 14557 | T12: 15890
A13: AMZN | B13: 42004 | C13: -241 | D13: 974 | E13: 6842 | F13: -4893 | H13: -979 | I13: 3349 | J13: -172 | K13: -5065 | M13: 4426 | N13: 0 | P13: 4432 | Q13: -310 | R13: 5899 | S13: 8658 | T13: 14557
A14: AMZN | B14: 41639 | C14: 274 | D14: 767 | E14: 5475 | F14: -3444 | H14: -312 | I14: 2306 | J14: -832 | K14: -4276 | M14: -617 | N14: 0 | P14: -539 | Q14: -86 | R14: 574 | S14: 8084 | T14: 8658
A15: AMZN | B15: 41274 | C15: -39 | D15: 1523 | E15: 4180 | F15: -3785 | H15: -745 | I15: 4237 | J15: 190 | K15: -3595 | M15: 2790 | N15: -960 | P15: 2259 | Q15: -29 | R15: 2815 | S15: 5269 | T15: 8084
A16: AMZN | B16: 40908 | C16: 631 | D16: 1464 | E16: 3903 | F16: -1811 | H16: -705 | I16: 6843 | J16: -119 | K16: -1930 | M16: -267 | N16: -277 | P16: -482 | Q16: 1 | R16: 1492 | S16: 3777 | T16: 5269
A17: AMZN | B17: 40543 | C17: 1152 | D17: 1581 | E17: 3495 | F17: -979 | H17: -352 | I17: 4250 | J17: -2381 | K17: -3360 | M17: -78 | N17: 0 | P17: 181 | Q17: 17 | R17: 333 | S17: 3444 | T17: 3777
A18: AMZN | B18: 40178 | C18: 902 | D18: 1612 | E18: 3293 | F18: -373 | H18: -40 | I18: 1966 | J18: -1964 | K18: -2337 | M18: -385 | N18: 0 | P18: -280 | Q18: -1 | R18: 675 | S18: 2769 | T18: 3444
A19: AMZN | B19: 39813 | C19: 645 | D19: 714 | E19: 1697 | F19: -333 | H19: -494 | I19: 1305 | J19: -866 | K19: -1199 | M19: -268 | N19: -89 | P19: -198 | Q19: -70 | R19: 230 | S19: 2539 | T19: 2769
A20: AMZN | B20: 39447 | C20: 476 | D20: 832 | E20: 1405 | F20: -224 | H20: -75 | I20: 1271 | J20: 266 | K20: 42 | M20: -50 | N20: -157 | P20: 50 | Q20: 20 | R20: 1517 | S20: 1022 | T20: 2539
A21: AMZN | B21: 39082 | C21: 190 | D21: 284 | E21: 702 | F21: -216 | H21: -32 | I21: 1845 | J21: -117 | K21: -333 | M21: -285 | N21: -217 | P21: -400 | Q21: 40 | R21: 9 | S21: 1013 | T21: 1022
A22: MSFT | B22: 46022 | C22: 101832 | D22: -5350 | E22: 136162 | F22: -64551 | H22: -5978 | I22: 25388 | J22: -8048 | K22: -72599 | L22: -5746 | M22: -8962 | N22: -16364 | O22: -24082 | P22: -51699 | Q22: 63 | R22: 11927 | S22: 18315 | T22: 30242
A23: MSFT | B23: 45657 | C23: 88136 | D23: 1824 | E23: 118548 | F23: -44477 | H23: -69132 | I23: 35669 | J23: -52493 | K23: -96970 | L23: 5250 | M23: 575 | N23: -15252 | O23: -21771 | P23: -37757 | Q23: -210 | R23: -16389 | S23: 34704 | T23: 18315
A24: MSFT | B24: 45291 | C24: 72361 | D24: -2388 | E24: 87582 | F24: -28107 | H24: -1670 | I24: 47864 | J24: 5427 | K24: -22680 | M24: -2750 | N24: -20379 | O24: -19800 | P24: -43935 | Q24: -194 | R24: 20773 | S24: 13931 | T24: 34704
A25: MSFT | B25: 44926 | C25: 72738 | D25: 446 | E25: 89035 | F25: -23886 | H25: -22038 | I25: 44894 | J25: -6425 | K25: -30311 | M25: -9023 | N25: -30855 | O25: -18135 | P25: -58876 | Q25: -141 | R25: -293 | S25: 14224 | T25: 13931
A26: MSFT | B26: 44561 | C26: 61271 | D26: -936 | E26: 76740 | F26: -20622 | H26: -8909 | I26: 65800 | J26: -6955 | K26: -27577 | M26: -3750 | N26: -25692 | O26: -16521 | P26: -48486 | Q26: -29 | R26: 648 | S26: 13576 | T26: 14224
A27: MSFT | B27: 44196 | C27: 44281 | D27: -1483 | E27: 60675 | F27: -15441 | H27: -2521 | I27: 84170 | J27: 3218 | K27: -12223 | L27: 0 | M27: -5518 | N27: -21625 | O27: -15137 | P27: -46031 | Q27: -201 | R27: 2220 | S27: 11356 | T27: 13576
A28: MSFT | B28: 43830 | C28: 39240 | D28: 3866 | E28: 52185 | F28: -13925 | H28: -2388 | I28: 58237 | J28: -1848 | K28: -15773 | L28: 0 | M28: -4000 | N28: -18401 | O28: -13811 | P28: -36887 | Q28: -115 | R28: -590 | S28: 11946 | T28: 11356
A29: MSFT | B29: 43465 | C29: 16571 | D29: 20467 | E29: 43884 | F29: -11632 | H29: -888 | I29: 143937 | J29: 5571 | K29: -6061 | L29: -7324 | M29: -10201 | N29: -9719 | O29: -12699 | P29: -33590 | Q29: 50 | R29: 4283 | S29: 7663 | T29: 11946
A30: MSFT | B30: 43100 | C30: 21204 | D30: 1652 | E30: 39507 | F30: -8129 | H30: -25944 | I30: 164394 | J30: -38652 | K30: -46781 | L30: -4963 | M30: 31459 | N30: -11016 | O30: -11845 | P30: 8408 | Q30: 19 | R30: 1153 | S30: 6510 | T30: 7663
A31: MSFT | B31: 42735 | C31: 16798 | D31: -2076 | E31: 33325 | F31: -8343 | H31: -1393 | I31: 115341 | J31: -15607 | K31: -23950 | L31: 7195 | M31: 18283 | N31: -15301 | O31: -11006 | P31: -8393 | Q31: -67 | R31: 915 | S31: 5595 | T31: 6510
A32: MSFT | B32: 42369 | C32: 12193 | D32: 1513 | E32: 29080 | F32: -5944 | H32: -3723 | I32: 85861 | J32: -17057 | K32: -23001 | L32: 4481 | M32: 13661 | N32: -13809 | O32: -9882 | P32: -9080 | Q32: -73 | R32: -3074 | S32: 8669 | T32: 5595
A33: MSFT | B33: 42004 | C33: 22074 | D33: 624 | E33: 32231 | F33: -5485 | H33: -5937 | I33: 65366 | J33: -13348 | K33: -18833 | L33: 500 | M33: 6962 | N33: -6709 | O33: -8879 | P33: -8394 | Q33: -139 | R33: 4865 | S33: 3804 | T33: 8669
A34: MSFT | B34: 41639 | C34: 21863 | D34: -1375 | E34: 28833 | F34: -4257 | H34: -1584 | I34: 57594 | J34: -19554 | K34: -23811 | L34: 0 | M34: 3537 | N34: -4429 | O34: -7455 | P34: -8148 | Q34: -8 | R34: -3134 | S34: 6938 | T34: 3804
A35: MSFT | B35: 41274 | C35: 16978 | D35: -174 | E35: 31626 | F35: -2305 | H35: -10112 | I35: 45275 | J35: -22481 | K35: -24786 | L35: 0 | M35: 0 | N35: -3116 | O35: -6385 | P35: -9408 | Q35: -104 | R35: -2672 | S35: 9610 | T35: 6938
A36: MSFT | B36: 40908 | C36: 23150 | D36: -3003 | E36: 26994 | F36: -2355 | H36: -71 | I36: 22777 | J36: -12261 | K36: -14616 | L36: -186 | M36: 5960 | N36: -9133 | O36: -5180 | P36: -8376 | Q36: 103 | R36: 4105 | S36: 5505 | T36: 9610
A37: MSFT | B37: 40543 | C37: 18760 | D37: 661 | E37: 24073 | F37: -1977 | H37: -245 | I37: 22578 | J37: -9337 | K37: -11314 | L37: -991 | M37: 190 | N37: -8958 | O37: -4578 | P37: -13291 | Q37: -39 | R37: -571 | S37: 6076 | T37: 5505
A38: MSFT | B38: 40178 | C38: 14569 | D38: -178 | E38: 19037 | F38: -3119 | H38: -868 | I38: 25997 | J38: -12651 | K38: -15770 | L38: 1178 | M38: 5746 | N38: -8774 | O38: -4468 | P38: -7463 | Q38: -67 | R38: -4263 | S38: 10339 | T38: 6076
A39: MSFT | B39: 39813 | C39: 17681 | D39: -2435 | E39: 21612 | F39: -3182 | H39: -8053 | I39: 27729 | J39: -1405 | K39: -4587 | L39: 0 | M39: 0 | N39: -9039 | O39: -4015 | P39: -12934 | Q39: 137 | R39: 4228 | S39: 6111 | T39: 10339
A40: MSFT | B40: 39447 | C40: 14065 | D40: -961 | E40: 17796 | F40: -2264 | H40: -1150 | I40: 46187 | J40: 8353 | K40: 6089 | N40: -20793 | O40: -3805 | P40: -24544 | Q40: 56 | R40: -603 | S40: 6714 | T40: 6111
A41: MSFT | B41: 39082 | C41: 12599 | D41: -2397 | E41: 14404 | F41: -1578 | H41: -649 | I41: 58230 | J41: 9581 | K41: 8003 | N41: -17106 | O41: -3545 | P41: -20562 | Q41: 18 | R41: 1863 | S41: 4851 | T41: 6714
A42: GOOG | B42: 46022 | C42: 132170 | D42: 618 | E42: 164713 | F42: -91447 | H42: -1592 | I42: 84607 | J42: -28844 | K42: -120291 | M42: 32137 | N42: -45709 | O42: -10049 | P42: -37388 | Q42: 208 | R42: 7242 | S42: 23466 | T42: 30708
A43: GOOG | B43: 45657 | C43: 100118 | D43: -8406 | E43: 125299 | F43: -52535 | H43: -2931 | I43: 104310 | J43: 6999 | K43: -45536 | M43: 888 | N43: -62222 | O43: -7363 | P43: -79733 | Q43: -612 | R43: -582 | S43: 24048 | T43: 23466
A44: GOOG | B44: 45291 | C44: 73795 | D44: -3845 | E44: 101746 | F44: -32251 | H44: -495 | I44: 87619 | J44: 5188 | K44: -27063 | M44: -760 | N44: -61504 | P44: -72093 | Q44: -421 | R44: 2169 | S44: 21879 | T44: 24048
A45: GOOG | B45: 44926 | C45: 59972 | D45: -2235 | E45: 91495 | F45: -31485 | H45: -6969 | I45: 97972 | J45: 11187 | K45: -20298 | M45: -1196 | N45: -59296 | P45: -69757 | Q45: -506 | R45: 934 | S45: 20945 | T45: 21879
A46: GOOG | B46: 44561 | C46: 76033 | D46: -1523 | E46: 91652 | F46: -24640 | H46: -2618 | I46: 129228 | J46: -10883 | K46: -35523 | M46: -1236 | N46: -50274 | P46: -61362 | Q46: -287 | R46: -5520 | S46: 26465 | T46: 20945
A47: GOOG | B47: 44196 | C47: 40269 | D47: 1827 | E47: 65124 | F47: -22281 | H47: -738 | I47: 133929 | J47: -10492 | K47: -32773 | M47: 9661 | N47: -31149 | P47: -24408 | Q47: 24 | R47: 7967 | S47: 18498 | T47: 26465
A48: GOOG | B48: 43830 | C48: 34343 | D48: 819 | E48: 54520 | F48: -23548 | G48: 589 | H48: -2515 | I48: 98230 | J48: -5943 | K48: -29491 | M48: -268 | N48: -18396 | P48: -23209 | Q48: -23 | R48: 1797 | S48: 16701 | T48: 18498
A49: GOOG | B49: 43465 | C49: 30736 | D49: 4908 | E49: 47971 | F49: -25139 | G49: 98 | H49: -1491 | I49: 50259 | J49: -3365 | K49: -28504 | M49: -61 | N49: -8125 | P49: -13179 | Q49: -302 | R49: 5986 | S49: 10715 | T49: 16701
A50: GOOG | B50: 43100 | C50: 12662 | D50: 9246 | E50: 37091 | F50: -13184 | G50: 99 | H50: -287 | I50: 74492 | J50: -18217 | K50: -31401 | M50: -86 | N50: -4046 | P50: -8298 | Q50: 405 | R50: -2203 | S50: 12918 | T50: 10715
A51: GOOG | B51: 42735 | C51: 19478 | D51: 3300 | E51: 36036 | F51: -10212 | G51: 240 | H51: -986 | I51: 67389 | J51: -20953 | K51: -31165 | M51: -1335 | N51: -3693 | P51: -8332 | Q51: -170 | R51: -3631 | S51: 16549 | T51: 12918
A52: GOOG | B52: 42369 | C52: 16348 | D52: -409 | E52: 26024 | F52: -9915 | H52: -236 | I52: 62905 | J52: -13796 | K52: -23711 | M52: -23 | N52: -1780 | P52: -3677 | Q52: -434 | R52: -1798 | S52: 18347 | T52: 16549
A53: GOOG | B53: 42004 | C53: 14444 | D53: 364 | E53: 22376 | F53: -10959 | H53: -4888 | I53: 51315 | J53: -10096 | K53: -21055 | M53: -18 | P53: -1439 | Q53: -433 | R53: -551 | S53: 18898 | T53: 18347
A54: GOOG | B54: 41639 | C54: 12920 | D54: -31 | E54: 18659 | F54: -7358 | H54: -1448 | I54: 38314 | J54: -6321 | K54: -13679 | M54: -557 | P54: -857 | Q54: -3 | R54: 4120 | S54: 14778 | T54: 18898
A55: GOOG | B55: 41274 | C55: 10737 | D55: 898 | E55: 16619 | F55: -3273 | H55: -10568 | I55: 35180 | J55: -9783 | K55: -13056 | M55: 1328 | N55: 0 | P55: 1229 | Q55: 3 | R55: 4795 | S55: 9983 | T55: 14778
A56: GOOG | B56: 40908 | C56: 9737 | D56: 630 | E56: 14565 | F56: -3438 | H56: -1900 | I56: 48746 | J56: -15603 | K56: -19041 | M56: 726 | N56: 0 | P56: 807 | Q56: 22 | R56: -3647 | S56: 13630 | T56: 9983
A57: GOOG | B57: 40543 | C57: 8505 | D57: -99 | E57: 11081 | F57: -4018 | H57: -1067 | I57: 37099 | J57: -6662 | K57: -10680 | M57: 3463 | N57: -801 | P57: 3050 | Q57: -19 | R57: 3432 | S57: 10198 | T57: 13630
A58: GOOG | B58: 40178 | C58: 6520.448 | D58: 485.987 | E58: 9316.198 | F58: -809.888 | H58: -108.024 | I58: 22102.867 | J58: -7209.317 | K58: -8019.205 | M58: 0 | N58: 0 | P58: 233.412 | Q58: 10.511 | R58: 1540.916 | S58: 8656.672 | T58: 10197.588
A59: GOOG | B59: 39813 | C59: 4226.858 | D59: 327.232 | E59: 7852.857 | F59: -2358.461 | H59: -3320.299 | I59: 15762.796 | J59: -2960.961 | K59: -5319.422 | M59: 0 | N59: 0 | P59: 87.567 | Q59: -45.923 | R59: 2575.079 | S59: 6081.593 | T59: 8656.672
A60: GOOG | B60: 39447 | C60: 4203.72 | D60: 318.545 | E60: 5775.41 | F60: -2402.84 | H60: -906.651 | I60: 15659.473 | J60: -1278.749 | K60: -3681.589 | M60: 0 | N60: 0 | P60: 403.067 | Q60: 40.034 | R60: 2536.922 | S60: 3544.671 | T60: 6081.593
A61: GOOG | B61: 39082 | C61: 3077.446 | D61: 42.281 | E61: 3580.508 | F61: -1902.798 | H61: -402.446 | I61: 23107.132 | J61: -4996.352 | K61: -6899.15 | M61: 0 | N61: 2063.549 | P61: 2966.398 | Q61: 19.741 | R61: -332.503 | S61: 3877.174 | T61: 3544.671
A62: META | B62: 46022 | C62: 60458 | D62: -885 | E62: 115800 | F62: -69691 | H62: -4231 | I62: 26874 | J62: -32312 | K62: -102003 | M62: 27382 | N62: -26248 | O62: -5324 | P62: -20370 | Q62: 235 | R62: -6338 | S62: 45438 | T62: 39100
A63: META | B63: 45657 | C63: 62360 | D63: 1048 | E63: 91328 | F63: -37256 | H63: -270 | I63: 15789 | J63: -9894 | K63: -47150 | M63: 8463 | N63: -30125 | O63: -5072 | P63: -40781 | Q63: -786 | R63: 2611 | S63: 42827 | T63: 45438
A64: META | B64: 45291 | C64: 39098 | D64: 3836 | E64: 71113 | F64: -27266 | G64: 221 | H64: -629 | I64: 6184 | J64: 2771 | K64: -24495 | M64: 7397 | N64: -19774 | P64: -19500 | Q64: 113 | R64: 27231 | S64: 15596 | T64: 42827
A65: META | B65: 44926 | C65: 23200 | D65: 5683 | E65: 50475 | F65: -31431 | G65: 245 | H65: -1312 | I65: 13158 | J65: 2461 | K65: -28970 | M65: 9071 | N65: -27956 | P65: -22136 | Q65: -638 | R65: -1269 | S65: 16865 | T65: 15596
A66: META | B66: 44561 | C66: 39370 | D66: 700 | E66: 57683 | F66: -18567 | H66: -851 | I66: 42586 | J66: 10997 | K66: -7570 | M66: -677 | N66: -44537 | P66: -50728 | Q66: -474 | R66: -1089 | S66: 17954 | T66: 16865
A67: META | B67: 44196 | C67: 29146 | D67: -2723 | E67: 38747 | F67: -15115 | H67: -388 | I67: 25771 | J67: -14944 | K67: -30059 | M67: -604 | N67: -6272 | P67: -10292 | Q67: 279 | R67: -1325 | S67: 19279 | T67: 17954
A68: META | B68: 43830 | C68: 18485 | D68: 7250 | E68: 36314 | F68: -15102 | H68: -508 | I68: 19717 | J68: -4762 | K68: -19864 | M68: -552 | N68: -4202 | P68: -7299 | Q68: 4 | R68: 9155 | S68: 10124 | T68: 19279
A69: META | B69: 43465 | C69: 22112 | D69: -1527 | E69: 29274 | F69: -13915 | H69: -137 | I69: 17130 | J69: 2312 | K69: -11603 | M69: 0 | N69: -12879 | P69: -15572 | Q69: -179 | R69: 1920 | S69: 8204 | T69: 10124
A70: META | B70: 43100 | C70: 15934 | D70: 1887 | E70: 24216 | F70: -6733 | H70: -122 | I70: 12432 | J70: -13385 | K70: -20118 | M70: 0 | N70: -1976 | P70: -5235 | Q70: 232 | R70: -905 | S70: 9109 | T70: 8204
A71: META | B71: 42735 | C71: 10217 | D71: 758 | E71: 16108 | F71: -4491 | H71: -123 | I71: 15155 | J71: -7301 | K71: -11792 | M71: -312 | N71: 0 | P71: -310 | Q71: -63 | R71: 3943 | S71: 5166 | T71: 9109
A72: META | B72: 42369 | C72: 3688 | D72: 784 | E72: 8599 | F72: -2523 | H72: -313 | I72: 9238 | J72: -6911 | K72: -9434 | M72: -119 | N72: 0 | P72: 1582 | Q72: -155 | R72: 592 | S72: 4315 | T72: 4907
A73: META | B73: 42004 | C73: 2940 | D73: -262 | E73: 5457 | F73: -1831 | H73: -4975 | I73: 10347 | J73: -4082 | K73: -5913 | M73: -243 | N73: 18 | P73: 1571 | Q73: -123 | R73: 992 | S73: 3323 | T73: 4315
A74: META | B74: 41639 | C74: 1500 | D74: 676 | E74: 4222 | F74: -1362 | H74: -368 | I74: 6551 | J74: -1262 | K74: -2624 | M74: -1891 | N74: 1504 | P74: -667 | Q74: 8 | R74: 939 | S74: 2384 | T74: 3323
A75: META | B75: 41274 | C75: 53 | D75: -491 | E75: 1612 | F75: -1235 | H75: -911 | I75: 5433 | J75: -5789 | K75: -7024 | M75: 1130 | N75: 6777 | P75: 6283 | Q75: 1 | R75: 872 | S75: 1512 | T75: 2384
A76: META | B76: 40908 | C76: 1000 | D76: 5 | E76: 1549 | F76: -606 | H76: -24 | I76: 629 | J76: -2417 | K76: -3023 | M76: -431 | N76: 1026 | P76: 1198 | Q76: 3 | R76: -273 | S76: 1785 | T76: 1512
A77: META | B77: 40543 | C77: 606 | D77: -70 | E77: 698 | F77: -293 | H77: -22 | I77: 0 | J77: -31 | K77: -324 | M77: 160 | N77: 506 | P77: 781 | Q77: -3 | R77: 1152 | S77: 633 | T77: 1785
A78: META | B78: 40178 | C78: 229 | D78: -179 | E78: 155 | F78: -33 | I78: 0 | J78: -29 | K78: -62 | M78: -48 | N78: 9 | P78: 243 | Q78: 0 | R78: 336 | S78: 297 | T78: 633
A79: META | B79: 39813 | E79: 8 | F79: -70
A80: META | B80: 39447 | E80: 11 | F80: -55

Sheet Ratios
A1: Ticker | B1: FY | C1: Revenue | D1: Gross profit | E1: EBITDA | F1: EBIT | G1: Pretax Income | H1: Net Income | I1: Cash + Investments | J1: Current Assets | K1: Total Assets | L1: Current Liabilities | M1: Equity | N1: Interest Expense | O1: Operating Leases | P1: Finance Leases | Q1: Total Debt | R1: Adjusted Total Debt | S1: D&A | T1: CAPEX | U1: Revenue Growth | V1: Gross Margin | W1: EBITDA Margin | X1: Operating Margin | Y1: Pretax Margin | Z1: Effective Tax Rate | AA1: Net Profit Margin | AB1: ROE | AC1: ROIC | AD1: ROA | AE1: Quick Ratio | AF1: Current Ratio | AG1: Net Debt | AH1: Debt / Equity | AI1: Debt / Capital | AJ1: Debt / Assets | AK1: Interest Coverage | AL1: Financial Leverage | AM1: CapEx / Revenue | AN1: PPE / Assets | AO1: Op Cash / Revenue | AP1: FCF Margin | AQ1: Book Value Per Share
A2: AMZN | B2: 46022 | C2: ='Income Statement'!C2 -> 716924 | D2: ='Income Statement'!E2 -> 360510 | E2: =F2+S2 -> 145731 | F2: ='Income Statement'!L2 -> 79975 | G2: ='Income Statement'!P2 -> 97311 | H2: ='Income Statement'!R2 -> 77670 | I2: ='Balance Sheet'!D2 -> 123029 | J2: ='Balance Sheet'!I2 -> 229083 | K2: ='Balance Sheet'!R2 -> 818042 | L2: ='Balance Sheet'!X2 -> 218005 | M2: ='Balance Sheet'!AL2 -> 411065 | N2: 2274 | O2: 89252 | P2: 12286 | Q2: 68851 | R2: =SUM(O2:Q2) -> 170389 | S2: 65756 | T2: =-'Cash Flow'!F2 -> 131819 | U2: =(C2-C3)/C3 -> 0.12377755 | V2: =D2/C2 -> 0.50285665 | W2: =E2/C2 -> 0.20327259 | X2: =F2/C2 -> 0.11155297 | Y2: =G2/C2 -> 0.13573405 | Z2: =(G2-H2)/G2 -> 0.20183741 | AA2: =H2/C2 -> 0.10833784 | AB2: =H2/M2 -> 0.18894822 | AC2: =(F2*(1-Z2))/(Q2-I2+M2) -> 0.17886069 | AD2: =H2/K2 -> 0.094946225 | AE2: =(I2+'Balance Sheet'!E2)/L2 -> 0.84198986 | AF2: =J2/L2 -> 1.0508153 | AG2: =Q2-I2 -> -54178 | AH2: =Q2/M2 -> 0.16749419 | AI2: =Q2/SUM(Q2,M2) -> 0.14346469 | AJ2: =Q2/K2 -> 0.084165605 | AK2: =F2/N2 -> 35.169305 | AL2: =K2/M2 -> 1.9900551 | AM2: =T2/C2 -> 0.18386747 | AN2: ='Balance Sheet'!J2/Ratios!K2 -> 0.75809311 | AO2: ='Cash Flow'!E2/C2 -> 0.19460082 | AP2: =('Cash Flow'!E2 +'Cash Flow'!F2)/Ratios!C2 -> 0.010733355 | AQ2: 38.31
A3: AMZN | B3: 45657 | C3: ='Income Statement'!C3 -> 637959 | D3: ='Income Statement'!E3 -> 311671 | E3: =F3+S3 -> 121388 | F3: ='Income Statement'!L3 -> 68593 | G3: ='Income Statement'!P3 -> 68614 | H3: ='Income Statement'!R3 -> 59248 | I3: ='Balance Sheet'!D3 -> 101202 | J3: ='Balance Sheet'!I3 -> 190867 | K3: ='Balance Sheet'!R3 -> 624894 | L3: ='Balance Sheet'!X3 -> 179431 | M3: ='Balance Sheet'!AL3 -> 285970 | N3: 2406 | O3: 79596 | P3: 10602 | Q3: 57791 | R3: =SUM(O3:Q3) -> 147989 | S3: 52795 | T3: =-'Cash Flow'!F3 -> 82999 | U3: =(C3-C4)/C4 -> 0.10990892 | V3: =D3/C3 -> 0.48854393 | W3: =E3/C3 -> 0.19027555 | X3: =F3/C3 -> 0.10751945 | Y3: =G3/C3 -> 0.10755237 | Z3: =(G3-H3)/G3 -> 0.13650275 | AA3: =H3/C3 -> 0.092871172 | AB3: =H3/M3 -> 0.20718257 | AC3: =(F3*(1-Z3))/(Q3-I3+M3) -> 0.24418746 | AD3: =H3/K3 -> 0.09481288 | AE3: =(I3+'Balance Sheet'!E3)/L3 -> 0.8365667 | AF3: =J3/L3 -> 1.0637348 | AG3: =Q3-I3 -> -43411 | AH3: =Q3/M3 -> 0.20208763 | AI3: =Q3/SUM(Q3,M3) -> 0.16811389 | AJ3: =Q3/K3 -> 0.092481285 | AK3: =F3/N3 -> 28.509144 | AL3: =K3/M3 -> 2.1851733 | AM3: =T3/C3 -> 0.13010084 | AN3: ='Balance Sheet'!J3/Ratios!K3 -> 0.75244121 | AO3: ='Cash Flow'!E3/C3 -> 0.18163706 | AP3: =('Cash Flow'!E3+'Cash Flow'!F3)/Ratios!C3 -> 0.051536227 | AQ3: 27
A4: AMZN | B4: 45291 | C4: ='Income Statement'!C4 -> 574785 | D4: ='Income Statement'!E4 -> 270046 | E4: =F4+S4 -> 85515 | F4: ='Income Statement'!L4 -> 36852 | G4: ='Income Statement'!P4 -> 37557 | H4: ='Income Statement'!R4 -> 30425 | I4: ='Balance Sheet'!D4 -> 86780 | J4: ='Balance Sheet'!I4 -> 172351 | K4: ='Balance Sheet'!R4 -> 527854 | L4: ='Balance Sheet'!X4 -> 164917 | M4: ='Balance Sheet'!AL4 -> 201875 | N4: 3182 | O4: 75639 | P4: 12109 | Q4: 75823 | R4: =SUM(O4:Q4) -> 163571 | S4: 48663 | T4: =-'Cash Flow'!F4 -> 52729 | U4: =(C4-C5)/C5 -> 0.11829574 | V4: =D4/C4 -> 0.46982089 | W4: =E4/C4 -> 0.14877737 | X4: =F4/C4 -> 0.064114408 | Y4: =G4/C4 -> 0.065340954 | Z4: =(G4-H4)/G4 -> 0.18989802 | AA4: =H4/C4 -> 0.052932836 | AB4: =H4/M4 -> 0.15071207 | AC4: =(F4*(1-Z4))/(Q4-I4+M4) -> 0.15637016 | AD4: =H4/K4 -> 0.057639044 | AE4: =(I4+'Balance Sheet'!E4)/L4 -> 0.80729094 | AF4: =J4/L4 -> 1.0450772 | AG4: =Q4-I4 -> -10957 | AH4: =Q4/M4 -> 0.37559381 | AI4: =Q4/SUM(Q4,M4) -> 0.27304122 | AJ4: =Q4/K4 -> 0.14364389 | AK4: =F4/N4 -> 11.581395 | AL4: =K4/M4 -> 2.6147567 | AM4: =T4/C4 -> 0.09173691 | AN4: ='Balance Sheet'!J4/Ratios!K4 -> 0.75172491 | AO4: ='Cash Flow'!E4/C4 -> 0.14778743 | AP4: =('Cash Flow'!E4+'Cash Flow'!F4)/Ratios!C4 -> 0.056050523 | AQ4: 19.44
A5: AMZN | B5: 44926 | C5: ='Income Statement'!C5 -> 513983 | D5: ='Income Statement'!E5 -> 225152 | E5: 38852 | F5: ='Income Statement'!L5 -> 12248 | G5: ='Income Statement'!P5 -> -5936 | H5: ='Income Statement'!R5 -> -2722 | I5: ='Balance Sheet'!D5 -> 70026 | J5: ='Balance Sheet'!I5 -> 146791 | K5: ='Balance Sheet'!R5 -> 462675 | L5: ='Balance Sheet'!X5 -> 155393 | M5: ='Balance Sheet'!AL5 -> 146043 | N5: 2367 | O5: 69040 | P5: 15783 | Q5: 76949 | R5: =SUM(O5:Q5) -> 161772 | S5: 41921 | T5: =-'Cash Flow'!F5 -> 63645 | U5: =(C5-C6)/C6 -> 0.093995173 | V5: =D5/C5 -> 0.4380534 | W5: =E5/C5 -> 0.075590049 | X5: =F5/C5 -> 0.023829582 | Y5: =G5/C5 -> -0.01154902 | Z5: =(G5-H5)/G5 -> 0.54144205 | AA5: =H5/C5 -> -0.005295895 | AB5: =H5/M5 -> -0.018638346 | AC5: =(F5*(1-Z5))/(Q5-I5+M5) -> 0.036716772 | AD5: =H5/K5 -> -0.0058831793 | AE5: =(I5+'Balance Sheet'!E5)/L5 -> 0.72093338 | AF5: =J5/L5 -> 0.94464358 | AG5: =Q5-I5 -> 6923 | AH5: =Q5/M5 -> 0.52689276 | AI5: =Q5/SUM(Q5,M5) -> 0.34507516 | AJ5: =Q5/K5 -> 0.16631329 | AK5: =F5/N5 -> 5.1744825 | AL5: =K5/M5 -> 3.1680738 | AM5: =T5/C5 -> 0.12382705 | AN5: ='Balance Sheet'!J5/Ratios!K5 -> 0.75615281 | AO5: ='Cash Flow'!E5/C5 -> 0.090960207 | AP5: =('Cash Flow'!E5+'Cash Flow'!F5)/Ratios!C5 -> -0.032866846 | AQ5: 14.26
A6: AMZN | B6: 44561 | C6: ='Income Statement'!C6 -> 469822 | D6: ='Income Statement'!E6 -> 197478 | E6: 48291 | F6: ='Income Statement'!L6 -> 24879 | G6: ='Income Statement'!P6 -> 38151 | H6: ='Income Statement'!R6 -> 33364 | I6: ='Balance Sheet'!D6 -> 96049 | J6: ='Balance Sheet'!I6 -> 161580 | K6: ='Balance Sheet'!R6 -> 420549 | L6: ='Balance Sheet'!X6 -> 142266 | M6: ='Balance Sheet'!AL6 -> 138245 | N6: 1809 | O6: 58330 | P6: 23753 | Q6: 52769 | R6: =SUM(O6:Q6) -> 134852 | S6: 34433 | T6: =-'Cash Flow'!F6 -> 61053 | U6: =(C6-C7)/C7 -> 0.21695367 | V6: =D6/C6 -> 0.42032514 | W6: =E6/C6 -> 0.10278574 | X6: =F6/C6 -> 0.052954098 | Y6: =G6/C6 -> 0.081203094 | Z6: =(G6-H6)/G6 -> 0.12547509 | AA6: =H6/C6 -> 0.071014129 | AB6: =H6/M6 -> 0.24133965 | AC6: =(F6*(1-Z6))/(Q6-I6+M6) -> 0.22910868 | AD6: =H6/K6 -> 0.079334394 | AE6: =(I6+'Balance Sheet'!E6)/L6 -> 0.90462936 | AF6: =J6/L6 -> 1.1357598 | AG6: =Q6-I6 -> -43280 | AH6: =Q6/M6 -> 0.38170639 | AI6: =Q6/SUM(Q6,M6) -> 0.27625724 | AJ6: =Q6/K6 -> 0.12547646 | AK6: =F6/N6 -> 13.752902 | AL6: =K6/M6 -> 3.0420558 | AM6: =T6/C6 -> 0.12994921 | AN6: ='Balance Sheet'!J6/Ratios!K6 -> 0.70118345 | AO6: ='Cash Flow'!E6/C6 -> 0.098605429 | AP6: =('Cash Flow'!E6+'Cash Flow'!F6)/Ratios!C6 -> -0.031343786 | AQ6: 13.58
A7: AMZN | B7: 44196 | C7: ='Income Statement'!C7 -> 386064 | D7: ='Income Statement'!E7 -> 152757 | E7: 51108 | F7: ='Income Statement'!L7 -> 22899 | G7: ='Income Statement'!P7 -> 24178 | H7: ='Income Statement'!R7 -> 21331 | I7: ='Balance Sheet'!D7 -> 84396 | J7: ='Balance Sheet'!I7 -> 132733 | K7: ='Balance Sheet'!R7 -> 321195 | L7: ='Balance Sheet'!X7 -> 126385 | M7: ='Balance Sheet'!AL7 -> 93404 | N7: 1647 | O7: 39099 | P7: 28434 | Q7: 33696 | R7: =SUM(O7:Q7) -> 101229 | S7: 25180 | T7: =-'Cash Flow'!F7 -> 40140 | U7: =(C7-C8)/C8 -> 0.37623431 | V7: =D7/C7 -> 0.39567792 | W7: =E7/C7 -> 0.1323822 | X7: =F7/C7 -> 0.059314 | Y7: =G7/C7 -> 0.062626922 | Z7: =(G7-H7)/G7 -> 0.11775168 | AA7: =H7/C7 -> 0.055252497 | AB7: =H7/M7 -> 0.22837352 | AC7: =(F7*(1-Z7))/(Q7-I7+M7) -> 0.47308459 | AD7: =H7/K7 -> 0.06641137 | AE7: =(I7+'Balance Sheet'!E7)/L7 -> 0.86010998 | AF7: =J7/L7 -> 1.0502275 | AG7: =Q7-I7 -> -50700 | AH7: =Q7/M7 -> 0.36075543 | AI7: =Q7/SUM(Q7,M7) -> 0.26511408 | AJ7: =Q7/K7 -> 0.10490823 | AK7: =F7/N7 -> 13.903461 | AL7: =K7/M7 -> 3.4387714 | AM7: =T7/C7 -> 0.1039724 | AN7: ='Balance Sheet'!J7/Ratios!K7 -> 0.65723626 | AO7: ='Cash Flow'!E7/C7 -> 0.17112189 | AP7: =('Cash Flow'!E7+'Cash Flow'!F7)/Ratios!C7 -> 0.067149488 | AQ7: 9.28
A8: AMZN | B8: 43830 | C8: ='Income Statement'!C8 -> 280522 | D8: ='Income Statement'!E8 -> 114986 | E8: 30256 | F8: ='Income Statement'!L8 -> 14541 | G8: ='Income Statement'!P8 -> 13976 | H8: ='Income Statement'!R8 -> 11588 | I8: ='Balance Sheet'!D8 -> 55021 | J8: ='Balance Sheet'!I8 -> 96334 | K8: ='Balance Sheet'!R8 -> 225248 | L8: ='Balance Sheet'!X8 -> 87812 | M8: ='Balance Sheet'!AL8 -> 62060 | N8: 1600 | O8: 25835 | P8: 26979 | Q8: 26127 | R8: =SUM(O8:Q8) -> 78941 | S8: 21789 | T8: =-'Cash Flow'!F8 -> 16861 | U8: =(C8-C9)/C9 -> 0.20454126 | V8: =D8/C8 -> 0.40990011 | W8: =E8/C8 -> 0.10785607 | X8: =F8/C8 -> 0.051835507 | Y8: =G8/C8 -> 0.049821404 | Z8: =(G8-H8)/G8 -> 0.17086434 | AA8: =H8/C8 -> 0.041308703 | AB8: =H8/M8 -> 0.18672253 | AC8: =(F8*(1-Z8))/(Q8-I8+M8) -> 0.36351871 | AD8: =H8/K8 -> 0.051445518 | AE8: =(I8+'Balance Sheet'!E8)/L8 -> 0.86048604 | AF8: =J8/L8 -> 1.0970482 | AG8: =Q8-I8 -> -28894 | AH8: =Q8/M8 -> 0.42099581 | AI8: =Q8/SUM(Q8,M8) -> 0.29626816 | AJ8: =Q8/K8 -> 0.11599215 | AK8: =F8/N8 -> 9.088125 | AL8: =K8/M8 -> 3.6295198 | AM8: =T8/C8 -> 0.060105803 | AN8: ='Balance Sheet'!J8/Ratios!K8 -> 0.64294023 | AO8: ='Cash Flow'!E8/C8 -> 0.13729404 | AP8: =('Cash Flow'!E8+'Cash Flow'!F8)/Ratios!C8 -> 0.077188242 | AQ8: 6.23
A9: AMZN | B9: 43465 | C9: ='Income Statement'!C9 -> 232887 | D9: ='Income Statement'!E9 -> 93731 | E9: 25034 | F9: ='Income Statement'!L9 -> 12421 | G9: ='Income Statement'!P9 -> 11261 | H9: ='Income Statement'!R9 -> 10073 | I9: ='Balance Sheet'!D9 -> 41250 | J9: ='Balance Sheet'!I9 -> 75101 | K9: ='Balance Sheet'!R9 -> 162648 | L9: ='Balance Sheet'!X9 -> 68391 | M9: ='Balance Sheet'!AL9 -> 43549 | N9: 1417 | O9: 26666 | P9: =17370+7053 -> 24423 | Q9: 26336 | R9: =SUM(O9:Q9) -> 77425 | S9: 15341 | T9: =-'Cash Flow'!F9 -> 13427 | U9: =(C9-C10)/C10 -> 0.30933962 | V9: =D9/C9 -> 0.40247416 | W9: =E9/C9 -> 0.10749419 | X9: =F9/C9 -> 0.053334879 | Y9: =G9/C9 -> 0.048353923 | Z9: =(G9-H9)/G9 -> 0.10549685 | AA9: =H9/C9 -> 0.043252736 | AB9: =H9/M9 -> 0.23130267 | AC9: =(F9*(1-Z9))/(Q9-I9+M9) -> 0.38800851 | AD9: =H9/K9 -> 0.061931287 | AE9: =(I9+'Balance Sheet'!E9)/L9 -> 0.84699741 | AF9: =J9/L9 -> 1.0981123 | AG9: =Q9-I9 -> -14914 | AH9: =Q9/M9 -> 0.60474408 | AI9: =Q9/SUM(Q9,M9) -> 0.37684768 | AJ9: =Q9/K9 -> 0.16192022 | AK9: =F9/N9 -> 8.7657022 | AL9: =K9/M9 -> 3.7348274 | AM9: =T9/C9 -> 0.057654571 | AN9: ='Balance Sheet'!J9/Ratios!K9 -> 0.58881757 | AO9: ='Cash Flow'!E9/C9 -> 0.13192235 | AP9: =('Cash Flow'!E9+'Cash Flow'!F9)/Ratios!C9 -> 0.074267778 | AQ9: 4.43
A10: AMZN | B10: 43100 | C10: ='Income Statement'!C10 -> 177866 | D10: ='Income Statement'!E10 -> 65932 | E10: 13272 | F10: ='Income Statement'!L10 -> 4106 | G10: ='Income Statement'!P10 -> 3806 | H10: ='Income Statement'!R10 -> 3033 | I10: ='Balance Sheet'!D10 -> 30986 | J10: ='Balance Sheet'!I10 -> 60197 | K10: ='Balance Sheet'!R10 -> 131310 | L10: ='Balance Sheet'!X10 -> 57883 | M10: ='Balance Sheet'!AL10 -> 27709 | N10: 848 | O10: 22848 | P10: =14277+5027 -> 19304 | Q10: 9894 | R10: =SUM(O10:Q10) -> 52046 | S10: 11478 | T10: =-'Cash Flow'!F10 -> 11955 | U10: =(C10-C11)/C11 -> 0.30796326 | V10: =D10/C10 -> 0.37068355 | W10: =E10/C10 -> 0.074617971 | X10: =F10/C10 -> 0.023084794 | Y10: =G10/C10 -> 0.021398131 | Z10: =(G10-H10)/G10 -> 0.20310037 | AA10: =H10/C10 -> 0.017052163 | AB10: =H10/M10 -> 0.10945902 | AC10: =(F10*(1-Z10))/(Q10-I10+M10) -> 0.49449447 | AD10: =H10/K10 -> 0.023098012 | AE10: =(I10+'Balance Sheet'!E10)/L10 -> 0.76274554 | AF10: =J10/L10 -> 1.0399772 | AG10: =Q10-I10 -> -21092 | AH10: =Q10/M10 -> 0.3570681 | AI10: =Q10/SUM(Q10,M10) -> 0.2631173 | AJ10: =Q10/K10 -> 0.075348412 | AK10: =F10/N10 -> 4.8419811 | AL10: =K10/M10 -> 4.7388935 | AM10: =T10/C10 -> 0.06721352 | AN10: ='Balance Sheet'!J10/Ratios!K10 -> 0.52222222 | AO10: ='Cash Flow'!E10/C10 -> 0.10325189 | AP10: =('Cash Flow'!E10+'Cash Flow'!F10)/Ratios!C10 -> 0.036038366 | AQ10: 2.86
A11: AMZN | B11: 42735 | C11: ='Income Statement'!C11 -> 135987 | D11: ='Income Statement'!E11 -> 47722 | E11: 10873 | F11: ='Income Statement'!L11 -> 4186 | G11: ='Income Statement'!P11 -> 3892 | H11: ='Income Statement'!R11 -> 2371 | I11: ='Balance Sheet'!D11 -> 25981 | J11: ='Balance Sheet'!I11 -> 45781 | K11: ='Balance Sheet'!R11 -> 83402 | L11: ='Balance Sheet'!X11 -> 43816 | M11: ='Balance Sheet'!AL11 -> 19285 | N11: 484 | O11: 9510 | P11: 11660 | Q11: 8800 | R11: =SUM(O11:Q11) -> 29970 | S11: 8116 | T11: =-'Cash Flow'!F11 -> 7804 | U11: =(C11-C12)/C12 -> 0.27083528 | V11: =D11/C11 -> 0.3509306 | W11: =E11/C11 -> 0.079956172 | X11: =F11/C11 -> 0.030782354 | Y11: =G11/C11 -> 0.028620383 | Z11: =(G11-H11)/G11 -> 0.39080164 | AA11: =H11/C11 -> 0.01743549 | AB11: =H11/M11 -> 0.12294529 | AC11: =(F11*(1-Z11))/(Q11-I11+M11) -> 1.2120268 | AD11: =H11/K11 -> 0.028428575 | AE11: =(I11+'Balance Sheet'!E11)/L11 -> 0.78327552 | AF11: =J11/L11 -> 1.0448466 | AG11: =Q11-I11 -> -17181 | AH11: =Q11/M11 -> 0.4563132 | AI11: =Q11/SUM(Q11,M11) -> 0.31333452 | AJ11: =Q11/K11 -> 0.10551306 | AK11: =F11/N11 -> 8.6487603 | AL11: =K11/M11 -> 4.3247083 | AM11: =T11/C11 -> 0.057387839 | AN11: ='Balance Sheet'!J11/Ratios!K11 -> 0.50887269 | AO11: ='Cash Flow'!E11/C11 -> 0.12650474 | AP11: =('Cash Flow'!E11+'Cash Flow'!F11)/Ratios!C11 -> 0.069116901 | AQ11: 2.02
A12: AMZN | B12: 42369 | C12: ='Income Statement'!C12 -> 107006 | D12: ='Income Statement'!E12 -> 35355 | E12: 7361 | F12: ='Income Statement'!L12 -> 2233 | G12: ='Income Statement'!P12 -> 1568 | H12: ='Income Statement'!R12 -> 596 | I12: ='Balance Sheet'!D12 -> 19808 | J12: ='Balance Sheet'!I12 -> 35705 | K12: ='Balance Sheet'!R12 -> 64747 | L12: ='Balance Sheet'!X12 -> 33887 | M12: ='Balance Sheet'!AL12 -> 13384 | N12: 459 | O12: 6517 | P12: =7239+1835 -> 9074 | Q12: 8562 | R12: =SUM(O12:Q12) -> 24153 | S12: 6281 | T12: =-'Cash Flow'!F12 -> 4589 | U12: =(C12-C13)/C13 -> 0.20247674 | V12: =D12/C12 -> 0.33040203 | W12: =E12/C12 -> 0.068790535 | X12: =F12/C12 -> 0.020867989 | Y12: =G12/C12 -> 0.014653384 | Z12: =(G12-H12)/G12 -> 0.61989796 | AA12: =H12/C12 -> 0.0055697811 | AB12: =H12/M12 -> 0.044530783 | AC12: =(F12*(1-Z12))/(Q12-I12+M12) -> 0.39699151 | AD12: =H12/K12 -> 0.0092050597 | AE12: =(I12+'Balance Sheet'!E12)/L12 -> 0.75137959 | AF12: =J12/L12 -> 1.0536489 | AG12: =Q12-I12 -> -11246 | AH12: =Q12/M12 -> 0.63971907 | AI12: =Q12/SUM(Q12,M12) -> 0.39013943 | AJ12: =Q12/K12 -> 0.13223779 | AK12: =F12/N12 -> 4.8649237 | AL12: =K12/M12 -> 4.837642 | AM12: =T12/C12 -> 0.042885446 | AN12: ='Balance Sheet'!J12/Ratios!K12 -> 0.4641605 | AO12: ='Cash Flow'!E12/C12 -> 0.11139562 | AP12: =('Cash Flow'!E12+'Cash Flow'!F12)/Ratios!C12 -> 0.068510177 | AQ12: 1.42
A13: AMZN | B13: 42004 | C13: ='Income Statement'!C13 -> 88988 | D13: ='Income Statement'!E13 -> 26236 | E13: 3959 | F13: ='Income Statement'!L13 -> 178 | G13: ='Income Statement'!P13 -> -111 | H13: ='Income Statement'!R13 -> -241 | I13: ='Balance Sheet'!D13 -> 17416 | J13: ='Balance Sheet'!I13 -> 31327 | K13: ='Balance Sheet'!R13 -> 54505 | L13: ='Balance Sheet'!X13 -> 28089 | M13: ='Balance Sheet'!AL13 -> 10741 | N13: 210 | O13: 5913 | P13: =5039+1265 -> 6304 | Q13: 9881 | R13: =SUM(O13:Q13) -> 22098 | S13: 4746 | T13: =-'Cash Flow'!F13 -> 4893 | U13: =(C13-C14)/C14 -> 0.19523989 | V13: =D13/C13 -> 0.29482627 | W13: =E13/C13 -> 0.044489145 | X13: =F13/C13 -> 0.0020002697 | Y13: =G13/C13 -> -0.0012473592 | Z13: =(G13-H13)/G13 -> -1.1711712 | AA13: =H13/C13 -> -0.0027082303 | AB13: =H13/M13 -> -0.022437389 | AC13: =(F13*(1-Z13))/(Q13-I13+M13) -> 0.12054537 | AD13: =H13/K13 -> -0.0044216127 | AE13: =(I13+'Balance Sheet'!E13)/L13 -> 0.81982271 | AF13: =J13/L13 -> 1.1152764 | AG13: =Q13-I13 -> -7535 | AH13: =Q13/M13 -> 0.91993297 | AI13: =Q13/SUM(Q13,M13) -> 0.47914848 | AJ13: =Q13/K13 -> 0.18128612 | AK13: =F13/N13 -> 0.84761905 | AL13: =K13/M13 -> 5.074481 | AM13: =T13/C13 -> 0.054984942 | AN13: ='Balance Sheet'!J13/Ratios!K13 -> 0.41702596 | AO13: ='Cash Flow'!E13/C13 -> 0.076886771 | AP13: =('Cash Flow'!E13+'Cash Flow'!F13)/Ratios!C13 -> 0.021901829 | AQ13: 1.15
A14: AMZN | B14: 41639 | C14: ='Income Statement'!C14 -> 74452 | D14: ='Income Statement'!E14 -> 20271 | E14: 3413 | F14: ='Income Statement'!L14 -> 745 | G14: ='Income Statement'!P14 -> 506 | H14: ='Income Statement'!R14 -> 274 | I14: ='Balance Sheet'!D14 -> 12447 | J14: ='Balance Sheet'!I14 -> 24625 | K14: ='Balance Sheet'!R14 -> 40159 | L14: ='Balance Sheet'!X14 -> 22980 | M14: ='Balance Sheet'!AL14 -> 9746 | N14: 141 | O14: 5135 | P14: =2390+583 -> 2973 | Q14: 3967 | R14: 3967 | S14: 3253 | T14: =-'Cash Flow'!F14 -> 3444 | U14: =(C14-C15)/C15 -> 0.21866662 | V14: =D14/C14 -> 0.27226938 | W14: =E14/C14 -> 0.045841616 | X14: =F14/C14 -> 0.010006447 | Y14: =G14/C14 -> 0.0067963251 | Z14: =(G14-H14)/G14 -> 0.45849802 | AA14: =H14/C14 -> 0.0036802235 | AB14: =H14/M14 -> 0.028114098 | AC14: =(F14*(1-Z14))/(Q14-I14+M14) -> 0.31865638 | AD14: =H14/K14 -> 0.0068228791 | AE14: =(I14+'Balance Sheet'!E14)/L14 -> 0.74908616 | AF14: =J14/L14 -> 1.071584 | AG14: =Q14-I14 -> -8480 | AH14: =Q14/M14 -> 0.40703879 | AI14: =Q14/SUM(Q14,M14) -> 0.28928754 | AJ14: =Q14/K14 -> 0.09878234 | AK14: =F14/N14 -> 5.2836879 | AL14: =K14/M14 -> 4.1205623 | AM14: =T14/C14 -> 0.046257992 | AN14: ='Balance Sheet'!J14/Ratios!K14 -> 0.36875918 | AO14: ='Cash Flow'!E14/C14 -> 0.073537313 | AP14: =('Cash Flow'!E14+'Cash Flow'!F14)/Ratios!C14 -> 0.027279321 | AQ14: 1.06
A15: AMZN | B15: 41274 | C15: ='Income Statement'!C15 -> 61093 | D15: ='Income Statement'!E15 -> 15122 | E15: 2539 | F15: ='Income Statement'!L15 -> 676 | G15: ='Income Statement'!P15 -> 544 | H15: ='Income Statement'!R15 -> -39 | I15: ='Balance Sheet'!D15 -> 11448 | J15: ='Balance Sheet'!I15 -> 21296 | K15: ='Balance Sheet'!R15 -> 32555 | L15: ='Balance Sheet'!X15 -> 19002 | M15: ='Balance Sheet'!AL15 -> 8192 | N15: 92 | O15: 5454 | P15: 1292 | Q15: 3691 | R15: =SUM(O15:Q15) -> 10437 | S15: 2159 | T15: =-'Cash Flow'!F15 -> 3785 | U15: =(C15-C16)/C16 -> 0.27073237 | V15: =D15/C15 -> 0.24752427 | W15: =E15/C15 -> 0.041559589 | X15: =F15/C15 -> 0.011065097 | Y15: =G15/C15 -> 0.0089044571 | Z15: =(G15-H15)/G15 -> 1.0716912 | AA15: =H15/C15 -> -0.00063837101 | AB15: =H15/M15 -> -0.0047607422 | AC15: =(F15*(1-Z15))/(Q15-I15+M15) -> -0.11140974 | AD15: =H15/K15 -> -0.0011979727 | AE15: =(I15+'Balance Sheet'!E15)/L15 -> 0.7794969 | AF15: =J15/L15 -> 1.1207241 | AG15: =Q15-I15 -> -7757 | AH15: =Q15/M15 -> 0.45056152 | AI15: =Q15/SUM(Q15,M15) -> 0.3106118 | AJ15: =Q15/K15 -> 0.11337736 | AK15: =F15/N15 -> 7.3478261 | AL15: =K15/M15 -> 3.973999 | AM15: =T15/C15 -> 0.061954725 | AN15: ='Balance Sheet'!J15/Ratios!K15 -> 0.29433267 | AO15: ='Cash Flow'!E15/C15 -> 0.068420277 | AP15: =('Cash Flow'!E15+'Cash Flow'!F15)/Ratios!C15 -> 0.0064655525 | AQ15: 0.9
A16: AMZN | B16: 40908 | C16: ='Income Statement'!C16 -> 48077 | D16: ='Income Statement'!E16 -> 10789 | E16: 2011 | F16: ='Income Statement'!L16 -> 862 | G16: ='Income Statement'!P16 -> 934 | H16: ='Income Statement'!R16 -> 631 | I16: ='Balance Sheet'!D16 -> 9576 | J16: ='Balance Sheet'!I16 -> 17490 | K16: ='Balance Sheet'!R16 -> 25278 | L16: ='Balance Sheet'!X16 -> 14896 | M16: ='Balance Sheet'!AL16 -> 7757 | N16: 65 | O16: 3093 | P16: =975+580 -> 1555 | Q16: 384 | R16: =SUM(O16:Q16) -> 5032 | S16: 1083 | T16: =-'Cash Flow'!F16 -> 1811 | U16: =(C16-C17)/C17 -> 0.40559584 | V16: =D16/C16 -> 0.22441084 | W16: =E16/C16 -> 0.041828733 | X16: =F16/C16 -> 0.017929571 | Y16: =G16/C16 -> 0.019427169 | Z16: =(G16-H16)/G16 -> 0.32441113 | AA16: =H16/C16 -> 0.013124779 | AB16: =H16/M16 -> 0.081345881 | AC16: =(F16*(1-Z16))/(Q16-I16+M16) -> -0.40582411 | AD16: =H16/K16 -> 0.024962418 | AE16: =(I16+'Balance Sheet'!E16)/L16 -> 0.81545381 | AF16: =J16/L16 -> 1.1741407 | AG16: =Q16-I16 -> -9192 | AH16: =Q16/M16 -> 0.049503674 | AI16: =Q16/SUM(Q16,M16) -> 0.047168652 | AJ16: =Q16/K16 -> 0.015191075 | AK16: =F16/N16 -> 13.261538 | AL16: =K16/M16 -> 3.258734 | AM16: =T16/C16 -> 0.03766874 | AN16: ='Balance Sheet'!J16/Ratios!K16 -> 0.22889469 | AO16: ='Cash Flow'!E16/C16 -> 0.08118227 | AP16: =('Cash Flow'!E16+'Cash Flow'!F16)/Ratios!C16 -> 0.04351353 | AQ16: 0.85
A17: AMZN | B17: 40543 | C17: ='Income Statement'!C17 -> 34204 | D17: ='Income Statement'!E17 -> 7643 | E17: 2063 | F17: ='Income Statement'!L17 -> 1406 | G17: ='Income Statement'!P17 -> 1497 | H17: ='Income Statement'!R17 -> 1152 | I17: ='Balance Sheet'!D17 -> 8762 | J17: ='Balance Sheet'!I17 -> 13747 | K17: ='Balance Sheet'!R17 -> 18797 | L17: ='Balance Sheet'!X17 -> 10372 | M17: ='Balance Sheet'!AL17 -> 6864 | N17: 39 | O17: 1553 | P17: =494+187 -> 681 | Q17: 184 | R17: =SUM(O17:Q17) -> 2418 | S17: 568 | T17: =-'Cash Flow'!F17 -> 979 | U17: =(C17-C18)/C18 -> 0.39556897 | V17: =D17/C17 -> 0.2234534 | W17: =E17/C17 -> 0.060314583 | X17: =F17/C17 -> 0.041106303 | Y17: =G17/C17 -> 0.043766811 | Z17: =(G17-H17)/G17 -> 0.23046092 | AA17: =H17/C17 -> 0.033680271 | AB17: =H17/M17 -> 0.16783217 | AC17: =(F17*(1-Z17))/(Q17-I17+M17) -> -0.63125551 | AD17: =H17/K17 -> 0.061286375 | AE17: =(I17+'Balance Sheet'!E17)/L17 -> 0.99778249 | AF17: =J17/L17 -> 1.3253953 | AG17: =Q17-I17 -> -8578 | AH17: =Q17/M17 -> 0.026806527 | AI17: =Q17/SUM(Q17,M17) -> 0.026106697 | AJ17: =Q17/K17 -> 0.0097887961 | AK17: =F17/N17 -> 36.051282 | AL17: =K17/M17 -> 2.7384907 | AM17: =T17/C17 -> 0.028622383 | AN17: ='Balance Sheet'!J17/Ratios!K17 -> 0.17321913 | AO17: ='Cash Flow'!E17/C17 -> 0.10218103 | AP17: =('Cash Flow'!E17+'Cash Flow'!F17)/Ratios!C17 -> 0.073558648 | AQ17: 0.76
A18: AMZN | B18: 40178 | C18: 24509 | D18: ='Income Statement'!E18 -> 5531 | E18: 1561 | F18: ='Income Statement'!L18 -> 1129 | G18: ='Income Statement'!P18 -> 1161 | H18: ='Income Statement'!R18 -> 902 | I18: ='Balance Sheet'!D18 -> 6366 | J18: ='Balance Sheet'!I18 -> 9797 | K18: ='Balance Sheet'!R18 -> 13813 | L18: ='Balance Sheet'!X18 -> 7364 | M18: ='Balance Sheet'!AL18 -> 5257 | N18: 34 | O18: 992 | P18: 262 | Q18: 131 | R18: =SUM(O18:Q18) -> 1385 | S18: 378 | T18: =-'Cash Flow'!F18 -> 373 | U18: =(C18-C19)/C19 -> 0.27877491 | V18: =D18/C18 -> 0.2256722 | W18: =E18/C18 -> 0.063690889 | X18: =F18/C18 -> 0.046064711 | Y18: =G18/C18 -> 0.047370354 | Z18: =(G18-H18)/G18 -> 0.22308355 | AA18: =H18/C18 -> 0.036802807 | AB18: =H18/M18 -> 0.17158075 | AC18: =(F18*(1-Z18))/(Q18-I18+M18) -> -0.89686981 | AD18: =H18/K18 -> 0.065300804 | AE18: =(I18+'Balance Sheet'!E18)/L18 -> 0.99864204 | AF18: =J18/L18 -> 1.3303911 | AG18: =Q18-I18 -> -6235 | AH18: =Q18/M18 -> 0.024919155 | AI18: =Q18/SUM(Q18,M18) -> 0.024313289 | AJ18: =Q18/K18 -> 0.0094838196 | AK18: =F18/N18 -> 33.205882 | AL18: =K18/M18 -> 2.6275442 | AM18: =T18/C18 -> 0.015218899 | AN18: ='Balance Sheet'!J18/Ratios!K18 -> 0.13863752 | AO18: ='Cash Flow'!E18/C18 -> 0.13435881 | AP18: =('Cash Flow'!E18+'Cash Flow'!F18)/Ratios!C18 -> 0.11913991 | AQ18: 0.59
A19: AMZN | B19: 39813 | C19: ='Income Statement'!C19 -> 19166 | D19: ='Income Statement'!E19 -> 4270 | E19: 1182 | F19: ='Income Statement'!L19 -> 842 | G19: ='Income Statement'!P19 -> 901 | H19: ='Income Statement'!R19 -> 645 | I19: ='Balance Sheet'!D19 -> 3727 | J19: ='Balance Sheet'!I19 -> 6157 | K19: ='Balance Sheet'!R19 -> 8314 | L19: ='Balance Sheet'!X19 -> 4746 | M19: ='Balance Sheet'!AL19 -> 2672 | N19: 71 | O19: 816 | P19: 196 | Q19: 468 | R19: =SUM(O19:Q19) -> 1480 | S19: 287 | T19: =-'Cash Flow'!F19 -> 333 | U19: =(C19-C20)/C20 -> 0.29194473 | V19: =D19/C19 -> 0.22279036 | W19: =E19/C19 -> 0.06167171 | X19: =F19/C19 -> 0.043931963 | Y19: =G19/C19 -> 0.047010331 | Z19: =(G19-H19)/G19 -> 0.28412875 | AA19: =H19/C19 -> 0.033653344 | AB19: =H19/M19 -> 0.24139222 | AC19: =(F19*(1-Z19))/(Q19-I19+M19) -> -1.0268545 | AD19: =H19/K19 -> 0.077579986 | AE19: =(I19+'Balance Sheet'!E19)/L19 -> 0.95954488 | AF19: =J19/L19 -> 1.297303 | AG19: =Q19-I19 -> -3259 | AH19: =Q19/M19 -> 0.1751497 | AI19: =Q19/SUM(Q19,M19) -> 0.14904459 | AJ19: =Q19/K19 -> 0.056290594 | AK19: =F19/N19 -> 11.859155 | AL19: =K19/M19 -> 3.1115269 | AM19: =T19/C19 -> 0.017374517 | AN19: ='Balance Sheet'!J19/Ratios!K19 -> 0.16947318 | AO19: ='Cash Flow'!E19/C19 -> 0.08854221 | AP19: =('Cash Flow'!E19+'Cash Flow'!F19)/Ratios!C19 -> 0.071167693 | AQ19: 0.31
A20: AMZN | B20: 39447 | C20: ='Income Statement'!C20 -> 14835 | D20: ='Income Statement'!E20 -> 3353 | E20: 926 | F20: ='Income Statement'!L20 -> 655 | G20: ='Income Statement'!P20 -> 660 | H20: ='Income Statement'!R20 -> 476 | I20: ='Balance Sheet'!D20 -> 3112 | J20: ='Balance Sheet'!I20 -> 5164 | K20: ='Balance Sheet'!R20 -> 6485 | L20: ='Balance Sheet'!X20 -> 3714 | M20: ='Balance Sheet'!AL20 -> 1197 | N20: 77 | O20: 650 | P20: 88 | Q20: 1299 | R20: =SUM(O20:Q20) -> 2037 | S20: 246 | T20: =-'Cash Flow'!F20 -> 224 | U20: =(C20-C21)/C21 -> 0.38502474 | V20: =D20/C20 -> 0.22601955 | W20: =E20/C20 -> 0.062419953 | X20: =F20/C20 -> 0.044152342 | Y20: =G20/C20 -> 0.044489383 | Z20: =(G20-H20)/G20 -> 0.27878788 | AA20: =H20/C20 -> 0.032086282 | AB20: =H20/M20 -> 0.39766082 | AC20: =(F20*(1-Z20))/(Q20-I20+M20) -> -0.76687328 | AD20: =H20/K20 -> 0.073400154 | AE20: =(I20+'Balance Sheet'!E20)/L20 -> 1.0215401 | AF20: =J20/L20 -> 1.3904146 | AG20: =Q20-I20 -> -1813 | AH20: =Q20/M20 -> 1.085213 | AI20: =Q20/SUM(Q20,M20) -> 0.52043269 | AJ20: =Q20/K20 -> 0.2003084 | AK20: =F20/N20 -> 8.5064935 | AL20: =K20/M20 -> 5.4177109 | AM20: =T20/C20 -> 0.015099427 | AN20: ='Balance Sheet'!J20/Ratios!K20 -> 0.15774865 | AO20: ='Cash Flow'!E20/C20 -> 0.09470846 | AP20: =('Cash Flow'!E20+'Cash Flow'!F20)/Ratios!C20 -> 0.079609033 | AQ20: 0.14
A21: AMZN | B21: 39082 | C21: ='Income Statement'!C21 -> 10711 | D21: ='Income Statement'!E21 -> 2456 | E21: 599 | F21: ='Income Statement'!L21 -> 389 | G21: ='Income Statement'!P21 -> 377 | H21: ='Income Statement'!R21 -> 190 | I21: ='Balance Sheet'!D21 -> 2019 | J21: ='Balance Sheet'!I21 -> 3373 | K21: ='Balance Sheet'!R21 -> 4363 | L21: ='Balance Sheet'!X21 -> 2532 | M21: ='Balance Sheet'!AL21 -> 431 | N21: 78 | O21: 639 | P21: 55 | Q21: 1263 | R21: =SUM(O21:Q21) -> 1957 | S21: 205 | T21: =-'Cash Flow'!F21 -> 216 | V21: =D21/C21 -> 0.22929698 | W21: =E21/C21 -> 0.055923817 | X21: =F21/C21 -> 0.036317804 | Y21: =G21/C21 -> 0.035197461 | Z21: =(G21-H21)/G21 -> 0.49602122 | AA21: =H21/C21 -> 0.017738773 | AB21: =H21/M21 -> 0.44083527 | AC21: =(F21*(1-Z21))/(Q21-I21+M21) -> -0.60322383 | AD21: =H21/K21 -> 0.043548017 | AE21: =(I21+'Balance Sheet'!E21)/L21 -> 0.94826224 | AF21: =J21/L21 -> 1.3321485 | AG21: =Q21-I21 -> -756 | AH21: =Q21/M21 -> 2.9303944 | AI21: =Q21/SUM(Q21,M21) -> 0.74557261 | AJ21: =Q21/K21 -> 0.28947972 | AK21: =F21/N21 -> 4.9871795 | AL21: =K21/M21 -> 10.12297 | AM21: =T21/C21 -> 0.020166184 | AN21: ='Balance Sheet'!J21/Ratios!K21 -> 0.18886088 | AO21: ='Cash Flow'!E21/C21 -> 0.065540099 | AP21: =('Cash Flow'!E21+'Cash Flow'!F21)/Ratios!C21 -> 0.045373915 | AQ21: 0.05
A22: MSFT | B22: 46022 | C22: ='Income Statement'!C22 -> 281724 | D22: ='Income Statement'!E22 -> 193893 | E22: 156528 | F22: 128528 | G22: ='Income Statement'!P22 -> 123627 | H22: ='Income Statement'!R22 -> 101832 | I22: ='Balance Sheet'!D22 -> 94565 | J22: ='Balance Sheet'!I22 -> 191131 | K22: ='Balance Sheet'!R22 -> 619003 | L22: ='Balance Sheet'!X22 -> 141218 | M22: ='Balance Sheet'!AL22 -> 343479 | N22: 2385 | O22: 22861 | P22: 46172 | Q22: 43151 | R22: =SUM(O22:Q22) -> 112184 | S22: 34153 | T22: =-'Cash Flow'!F22 -> 64551 | U22: =(C22-C23)/C23 -> 0.14932156 | V22: =D22/C22 -> 0.68823742 | W22: =E22/C22 -> 0.55560762 | X22: =F22/C22 -> 0.45621956 | Y22: =G22/C22 -> 0.4388231 | Z22: =(G22-H22)/G22 -> 0.17629644 | AA22: =H22/C22 -> 0.36146015 | AB22: =H22/M22 -> 0.29647227 | AC22: =(F22*(1-Z22))/(Q22-I22+M22) -> 0.36248428 | AD22: =H22/K22 -> 0.1645097 | AE22: =(I22+'Balance Sheet'!E22)/L22 -> 1.2227195 | AF22: =J22/L22 -> 1.3534464 | AG22: =Q22-I22 -> -51414 | AH22: =Q22/M22 -> 0.12562922 | AI22: =Q22/SUM(Q22,M22) -> 0.111608 | AJ22: =Q22/K22 -> 0.069710486 | AK22: =F22/N22 -> 53.890147 | AL22: =K22/M22 -> 1.8021568 | AM22: =T22/C22 -> 0.22912851 | AN22: ='Balance Sheet'!J22/Ratios!K22 -> 0.52252089 | AO22: ='Cash Flow'!E22/C22 -> 0.48331701 | AP22: =('Cash Flow'!E22+'Cash Flow'!F22)/Ratios!C22 -> 0.2541885 | AQ22: 46.2
A23: MSFT | B23: 45657 | C23: ='Income Statement'!C23 -> 245122 | D23: ='Income Statement'!E23 -> 171008 | E23: 129433 | F23: 109433 | G23: ='Income Statement'!P23 -> 107787 | H23: ='Income Statement'!R23 -> 88136 | I23: ='Balance Sheet'!D23 -> 75543 | J23: ='Balance Sheet'!I23 -> 159734 | K23: ='Balance Sheet'!R23 -> 512163 | L23: ='Balance Sheet'!X23 -> 125286 | M23: ='Balance Sheet'!AL23 -> 268477 | N23: 2935 | O23: 19077 | P23: 27145 | Q23: 44937 | R23: =SUM(O23:Q23) -> 91159 | S23: 22287 | T23: =-'Cash Flow'!F23 -> 44477 | U23: =(C23-C24)/C24 -> 0.15669962 | V23: =D23/C23 -> 0.69764444 | W23: =E23/C23 -> 0.52803502 | X23: =F23/C23 -> 0.446443 | Y23: =G23/C23 -> 0.43972797 | Z23: =(G23-H23)/G23 -> 0.18231327 | AA23: =H23/C23 -> 0.35955973 | AB23: =H23/M23 -> 0.32828138 | AC23: =(F23*(1-Z23))/(Q23-I23+M23) -> 0.37617832 | AD23: =H23/K23 -> 0.17208584 | AE23: =(I23+'Balance Sheet'!E23)/L23 -> 1.1411251 | AF23: =J23/L23 -> 1.2749549 | AG23: =Q23-I23 -> -30606 | AH23: =Q23/M23 -> 0.16737747 | AI23: =Q23/SUM(Q23,M23) -> 0.14337904 | AJ23: =Q23/K23 -> 0.087739645 | AK23: =F23/N23 -> 37.28552 | AL23: =K23/M23 -> 1.9076606 | AM23: =T23/C23 -> 0.18144842 | AN23: ='Balance Sheet'!J23/Ratios!K23 -> 0.45097557 | AO23: ='Cash Flow'!E23/C23 -> 0.48362856 | AP23: =('Cash Flow'!E23+'Cash Flow'!F23)/Ratios!C23 -> 0.30218014 | AQ23: 36.11
A24: MSFT | B24: 45291 | C24: ='Income Statement'!C24 -> 211915 | D24: ='Income Statement'!E24 -> 146052 | E24: 103555 | F24: 88523 | G24: ='Income Statement'!P24 -> 89311 | H24: ='Income Statement'!R24 -> 72361 | I24: ='Balance Sheet'!D24 -> 111262 | J24: ='Balance Sheet'!I24 -> 184257 | K24: ='Balance Sheet'!R24 -> 411976 | L24: ='Balance Sheet'!X24 -> 104149 | M24: ='Balance Sheet'!AL24 -> 206223 | N24: 1968 | O24: 15137 | P24: 17067 | Q24: 47237 | R24: =SUM(O24:Q24) -> 79441 | S24: 13861 | T24: =-'Cash Flow'!F24 -> 28107 | U24: =(C24-C25)/C25 -> 0.068820296 | V24: =D24/C24 -> 0.68920086 | W24: =E24/C24 -> 0.48866291 | X24: =F24/C24 -> 0.41772881 | Y24: =G24/C24 -> 0.42144728 | Z24: =(G24-H24)/G24 -> 0.18978625 | AA24: =H24/C24 -> 0.34146238 | AB24: =H24/M24 -> 0.35088715 | AC24: =(F24*(1-Z24))/(Q24-I24+M24) -> 0.50438509 | AD24: =H24/K24 -> 0.17564373 | AE24: =(I24+'Balance Sheet'!E24)/L24 -> 1.5357805 | AF24: =J24/L24 -> 1.7691673 | AG24: =Q24-I24 -> -64025 | AH24: =Q24/M24 -> 0.22905786 | AI24: =Q24/SUM(Q24,M24) -> 0.18636866 | AJ24: =Q24/K24 -> 0.11465959 | AK24: =F24/N24 -> 44.981199 | AL24: =K24/M24 -> 1.9977209 | AM24: =T24/C24 -> 0.13263337 | AN24: ='Balance Sheet'!J24/Ratios!K24 -> 0.43264171 | AO24: ='Cash Flow'!E24/C24 -> 0.41328835 | AP24: =('Cash Flow'!E24+'Cash Flow'!F24)/Ratios!C24 -> 0.28065498 | AQ24: 27.75
A25: MSFT | B25: 44926 | C25: ='Income Statement'!C25 -> 198270 | D25: ='Income Statement'!E25 -> 135620 | E25: 97983 | F25: 83383 | G25: ='Income Statement'!P25 -> 83716 | H25: ='Income Statement'!R25 -> 72738 | I25: ='Balance Sheet'!D25 -> 104757 | J25: ='Balance Sheet'!I25 -> 169684 | K25: ='Balance Sheet'!R25 -> 364840 | L25: ='Balance Sheet'!X25 -> 95082 | M25: ='Balance Sheet'!AL25 -> 166542 | N25: 2063 | O25: 13717 | P25: 14902 | Q25: 49781 | R25: =SUM(O25:Q25) -> 78400 | S25: 14460 | T25: =-'Cash Flow'!F25 -> 23886 | U25: =(C25-C26)/C26 -> 0.17956071 | V25: =D25/C25 -> 0.68401674 | W25: =E25/C25 -> 0.49418974 | X25: =F25/C25 -> 0.42055278 | Y25: =G25/C25 -> 0.42223231 | Z25: =(G25-H25)/G25 -> 0.13113383 | AA25: =H25/C25 -> 0.36686337 | AB25: =H25/M25 -> 0.43675469 | AC25: =(F25*(1-Z25))/(Q25-I25+M25) -> 0.64937945 | AD25: =H25/K25 -> 0.19936959 | AE25: =(I25+'Balance Sheet'!E25)/L25 -> 1.5672577 | AF25: =J25/L25 -> 1.784607 | AG25: =Q25-I25 -> -54976 | AH25: =Q25/M25 -> 0.29890958 | AI25: =Q25/SUM(Q25,M25) -> 0.23012347 | AJ25: =Q25/K25 -> 0.13644611 | AK25: =F25/N25 -> 40.418323 | AL25: =K25/M25 -> 2.1906786 | AM25: =T25/C25 -> 0.12047208 | AN25: ='Balance Sheet'!J25/Ratios!K25 -> 0.40348098 | AO25: ='Cash Flow'!E25/C25 -> 0.44905936 | AP25: =('Cash Flow'!E25+'Cash Flow'!F25)/Ratios!C25 -> 0.32858728 | AQ25: 22.31
A26: MSFT | B26: 44561 | C26: ='Income Statement'!C26 -> 168088 | D26: ='Income Statement'!E26 -> 115856 | E26: 81602 | F26: 69916 | G26: ='Income Statement'!P26 -> 71102 | H26: ='Income Statement'!R26 -> 61271 | I26: ='Balance Sheet'!D26 -> 130334 | J26: ='Balance Sheet'!I26 -> 184406 | K26: ='Balance Sheet'!R26 -> 333779 | L26: ='Balance Sheet'!X26 -> 88657 | M26: ='Balance Sheet'!AL26 -> 141988 | N26: 2346 | O26: 11591 | P26: 12541 | Q26: 58146 | R26: =SUM(O26:Q26) -> 82278 | S26: 11686 | T26: =-'Cash Flow'!F26 -> 20622 | U26: =(C26-C27)/C27 -> 0.17531727 | V26: =D26/C26 -> 0.68925801 | W26: =E26/C26 -> 0.4854719 | X26: =F26/C26 -> 0.41594879 | Y26: =G26/C26 -> 0.42300462 | Z26: =(G26-H26)/G26 -> 0.13826615 | AA26: =H26/C26 -> 0.3645174 | AB26: =H26/M26 -> 0.43152238 | AC26: =(F26*(1-Z26))/(Q26-I26+M26) -> 0.86316595 | AD26: =H26/K26 -> 0.18356757 | AE26: =(I26+'Balance Sheet'!E26)/L26 -> 1.8991958 | AF26: =J26/L26 -> 2.0799937 | AG26: =Q26-I26 -> -72188 | AH26: =Q26/M26 -> 0.40951348 | AI26: =Q26/SUM(Q26,M26) -> 0.29053534 | AJ26: =Q26/K26 -> 0.17420509 | AK26: =F26/N26 -> 29.802217 | AL26: =K26/M26 -> 2.350755 | AM26: =T26/C26 -> 0.12268574 | AN26: ='Balance Sheet'!J26/Ratios!K26 -> 0.36597269 | AO26: ='Cash Flow'!E26/C26 -> 0.45654657 | AP26: =('Cash Flow'!E26+'Cash Flow'!F26)/Ratios!C26 -> 0.33386083 | AQ26: 18.88
A27: MSFT | B27: 44196 | C27: ='Income Statement'!C27 -> 143015 | D27: ='Income Statement'!E27 -> 96937 | E27: 65941 | F27: 52959 | G27: ='Income Statement'!P27 -> 53036 | H27: ='Income Statement'!R27 -> 44281 | I27: ='Balance Sheet'!D27 -> 136527 | J27: ='Balance Sheet'!I27 -> 181915 | K27: ='Balance Sheet'!R27 -> 301311 | L27: ='Balance Sheet'!X27 -> 72310 | M27: ='Balance Sheet'!AL27 -> 118304 | N27: 2591 | O27: 9287 | P27: 9496 | Q27: 63327 | R27: =SUM(O27:Q27) -> 82110 | S27: 12796 | T27: =-'Cash Flow'!F27 -> 15441 | U27: =(C27-C28)/C28 -> 0.13645574 | V27: =D27/C27 -> 0.67781002 | W27: =E27/C27 -> 0.46107751 | X27: =F27/C27 -> 0.37030381 | Y27: =G27/C27 -> 0.37084222 | Z27: =(G27-H27)/G27 -> 0.16507655 | AA27: =H27/C27 -> 0.30962486 | AB27: =H27/M27 -> 0.37429842 | AC27: =(F27*(1-Z27))/(Q27-I27+M27) -> 0.98032793 | AD27: =H27/K27 -> 0.14696111 | AE27: =(I27+'Balance Sheet'!E27)/L27 -> 2.3307703 | AF27: =J27/L27 -> 2.5157655 | AG27: =Q27-I27 -> -73200 | AH27: =Q27/M27 -> 0.53529044 | AI27: =Q27/SUM(Q27,M27) -> 0.34865744 | AJ27: =Q27/K27 -> 0.21017155 | AK27: =F27/N27 -> 20.439599 | AL27: =K27/M27 -> 2.5469215 | AM27: =T27/C27 -> 0.1079677 | AN27: ='Balance Sheet'!J27/Ratios!K27 -> 0.31894289 | AO27: ='Cash Flow'!E27/C27 -> 0.4242562 | AP27: =('Cash Flow'!E27+'Cash Flow'!F27)/Ratios!C27 -> 0.3162885 | AQ27: 15.63
A28: MSFT | B28: 43830 | C28: ='Income Statement'!C28 -> 125843 | D28: ='Income Statement'!E28 -> 82933 | E28: 54929 | F28: 42959 | G28: ='Income Statement'!P28 -> 43688 | H28: ='Income Statement'!R28 -> 39240 | I28: ='Balance Sheet'!D28 -> 133819 | J28: ='Balance Sheet'!I28 -> 175552 | K28: ='Balance Sheet'!R28 -> 286556 | L28: ='Balance Sheet'!X28 -> 69420 | M28: ='Balance Sheet'!AL28 -> 102330 | N28: 2686 | O28: 7703 | P28: 6574 | Q28: 72781 | R28: =SUM(O28:Q28) -> 87058 | S28: 11682 | T28: =-'Cash Flow'!F28 -> 13925 | U28: =(C28-C29)/C29 -> 0.1402954 | V28: =D28/C28 -> 0.65901957 | W28: =E28/C28 -> 0.43648832 | X28: =F28/C28 -> 0.3413698 | Y28: =G28/C28 -> 0.34716273 | Z28: =(G28-H28)/G28 -> 0.10181285 | AA28: =H28/C28 -> 0.31181711 | AB28: =H28/M28 -> 0.38346526 | AC28: =(F28*(1-Z28))/(Q28-I28+M28) -> 0.93444787 | AD28: =H28/K28 -> 0.13693658 | AE28: =(I28+'Balance Sheet'!E28)/L28 -> 2.3529674 | AF28: =J28/L28 -> 2.528839 | AG28: =Q28-I28 -> -61038 | AH28: =Q28/M28 -> 0.71123815 | AI28: =Q28/SUM(Q28,M28) -> 0.4156278 | AJ28: =Q28/K28 -> 0.25398526 | AK28: =F28/N28 -> 15.993671 | AL28: =K28/M28 -> 2.8003127 | AM28: =T28/C28 -> 0.11065375 | AN28: ='Balance Sheet'!J28/Ratios!K28 -> 0.27633691 | AO28: ='Cash Flow'!E28/C28 -> 0.41468338 | AP28: =('Cash Flow'!E28+'Cash Flow'!F28)/Ratios!C28 -> 0.30402962 | AQ28: 13.39
A29: MSFT | B29: 43465 | C29: ='Income Statement'!C29 -> 110360 | D29: ='Income Statement'!E29 -> 72007 | E29: 45319 | F29: 35058 | G29: ='Income Statement'!P29 -> 36474 | H29: ='Income Statement'!R29 -> 16571 | I29: ='Balance Sheet'!D29 -> 133650 | J29: ='Balance Sheet'!I29 -> 169662 | K29: ='Balance Sheet'!R29 -> 258848 | L29: ='Balance Sheet'!X29 -> 58488 | M29: ='Balance Sheet'!AL29 -> 82718 | N29: 2733 | O29: 6967 | P29: 4301 | Q29: 76898 | R29: =SUM(O29:Q29) -> 88166 | S29: 10261 | T29: =-'Cash Flow'!F29 -> 11632 | U29: =(C29-C30)/C30 -> 0.14278614 | V29: =D29/C29 -> 0.65247372 | W29: =E29/C29 -> 0.41064697 | X29: =F29/C29 -> 0.31766945 | Y29: =G29/C29 -> 0.33050018 | Z29: =(G29-H29)/G29 -> 0.54567637 | AA29: =H29/C29 -> 0.15015404 | AB29: =H29/M29 -> 0.20033125 | AC29: =(F29*(1-Z29))/(Q29-I29+M29) -> 0.61340514 | AD29: =H29/K29 -> 0.064018266 | AE29: =(I29+'Balance Sheet'!E29)/L29 -> 2.7378437 | AF29: =J29/L29 -> 2.9008002 | AG29: =Q29-I29 -> -56752 | AH29: =Q29/M29 -> 0.92964047 | AI29: =Q29/SUM(Q29,M29) -> 0.48176874 | AJ29: =Q29/K29 -> 0.29707782 | AK29: =F29/N29 -> 12.827662 | AL29: =K29/M29 -> 3.1292826 | AM29: =T29/C29 -> 0.10540051 | AN29: ='Balance Sheet'!J29/Ratios!K29 -> 0.25253817 | AO29: ='Cash Flow'!E29/C29 -> 0.39764407 | AP29: =('Cash Flow'!E29+'Cash Flow'!F29)/Ratios!C29 -> 0.29224357 | AQ29: 10.77
A30: MSFT | B30: 43100 | C30: 96571 | D30: ='Income Statement'!E30 -> 62310 | E30: 34667 | F30: 29025 | G30: ='Income Statement'!P30 -> 29901 | H30: ='Income Statement'!R30 -> 25489 | I30: 132981 | J30: ='Balance Sheet'!I30 -> 162696 | K30: ='Balance Sheet'!R30 -> 250312 | L30: ='Balance Sheet'!X30 -> 55745 | M30: ='Balance Sheet'!AL30 -> 87711 | N30: 2222 | O30: 6975 | P30: 2538 | Q30: 77837 | R30: =SUM(O30:Q30) -> 87350 | S30: 8778 | T30: =-'Cash Flow'!F30 -> 8129 | U30: =(C30-C31)/C31 -> 0.059426904 | V30: =D30/C30 -> 0.64522476 | W30: =E30/C30 -> 0.3589794 | X30: =F30/C30 -> 0.30055607 | Y30: =G30/C30 -> 0.30962711 | Z30: =(G30-H30)/G30 -> 0.14755359 | AA30: =H30/C30 -> 0.26394052 | AB30: =H30/M30 -> 0.29060209 | AC30: =(F30*(1-Z30))/(Q30-I30+M30) -> 0.75973399 | AD30: =H30/K30 -> 0.10182892 | AE30: =(I30+'Balance Sheet'!E30)/L30 -> 2.7879092 | AF30: =J30/L30 -> 2.9185757 | AG30: =Q30-I30 -> -55144 | AH30: =Q30/M30 -> 0.88742575 | AI30: =Q30/SUM(Q30,M30) -> 0.47017783 | AJ30: =Q30/K30 -> 0.31095992 | AK30: =F30/N30 -> 13.062556 | AL30: =K30/M30 -> 2.8538268 | AM30: =T30/C30 -> 0.084176409 | AN30: ='Balance Sheet'!J30/Ratios!K30 -> 0.21760043 | AO30: ='Cash Flow'!E30/C30 -> 0.40909797 | AP30: =('Cash Flow'!E30+'Cash Flow'!F30)/Ratios!C30 -> 0.32492156 | AQ30: 9.39
A31: MSFT | B31: 42735 | C31: 91154 | D31: ='Income Statement'!E31 -> 58374 | E31: 27914 | F31: 26078 | G31: ='Income Statement'!P31 -> 25639 | H31: ='Income Statement'!R31 -> 20539 | I31: 113240 | J31: ='Balance Sheet'!I31 -> 139660 | K31: ='Balance Sheet'!R31 -> 193468 | L31: ='Balance Sheet'!X31 -> 59357 | M31: ='Balance Sheet'!AL31 -> 71997 | N31: 1243 | O31: 6464 | P31: 0 | Q31: 40949 | R31: =SUM(O31:Q31) -> 47413 | S31: 6622 | T31: =-'Cash Flow'!F31 -> 8343 | U31: =(C31-C32)/C32 -> -0.025924343 | V31: =D31/C31 -> 0.64038879 | W31: =E31/C31 -> 0.30622902 | X31: =F31/C31 -> 0.28608728 | Y31: =G31/C31 -> 0.28127126 | Z31: =(G31-H31)/G31 -> 0.19891571 | AA31: =H31/C31 -> 0.22532198 | AB31: =H31/M31 -> 0.28527578 | AC31: =(F31*(1-Z31))/(Q31-I31+M31) -> -71.056721 | AD31: =H31/K31 -> 0.10616226 | AE31: =(I31+'Balance Sheet'!E31)/L31 -> 2.2156949 | AF31: =J31/L31 -> 2.3528817 | AG31: =Q31-I31 -> -72291 | AH31: =Q31/M31 -> 0.56875981 | AI31: =Q31/SUM(Q31,M31) -> 0.36255379 | AJ31: =Q31/K31 -> 0.21165774 | AK31: =F31/N31 -> 20.979887 | AL31: =K31/M31 -> 2.6871675 | AM31: =T31/C31 -> 0.091526428 | AN31: ='Balance Sheet'!J31/Ratios!K31 -> 0.19722125 | AO31: ='Cash Flow'!E31/C31 -> 0.3655901 | AP31: =('Cash Flow'!E31+'Cash Flow'!F31)/Ratios!C31 -> 0.27406367 | AQ31: 9.22
A32: MSFT | B32: 42369 | C32: ='Income Statement'!C32 -> 93580 | D32: ='Income Statement'!E32 -> 60542 | E32: 34129 | F32: 18161 | G32: ='Income Statement'!P32 -> 18507 | H32: ='Income Statement'!R32 -> 12193 | I32: 96526 | J32: ='Balance Sheet'!I32 -> 122797 | K32: 174472 | L32: ='Balance Sheet'!X32 -> 49647 | M32: ='Balance Sheet'!AL32 -> 80083 | N32: 781 | O32: 5153 | P32: 0 | Q32: 30463 | R32: =SUM(O32:Q32) -> 35616 | S32: 5957 | T32: =-'Cash Flow'!F32 -> 5944 | U32: =(C32-C33)/C33 -> 0.077700874 | V32: =D32/C32 -> 0.64695448 | W32: =E32/C32 -> 0.364704 | X32: =F32/C32 -> 0.19406925 | Y32: =G32/C32 -> 0.19776662 | Z32: =(G32-H32)/G32 -> 0.34116821 | AA32: =H32/C32 -> 0.13029493 | AB32: =H32/M32 -> 0.15225454 | AC32: =(F32*(1-Z32))/(Q32-I32+M32) -> 0.85342683 | AD32: =H32/K32 -> 0.069885139 | AE32: =(I32+'Balance Sheet'!E32)/L32 -> 2.304953 | AF32: =J32/L32 -> 2.4734022 | AG32: =Q32-I32 -> -66063 | AH32: =Q32/M32 -> 0.38039284 | AI32: =Q32/SUM(Q32,M32) -> 0.27556854 | AJ32: =Q32/K32 -> 0.17460108 | AK32: =F32/N32 -> 23.253521 | AL32: =K32/M32 -> 2.1786397 | AM32: =T32/C32 -> 0.063517846 | AN32: ='Balance Sheet'!J32/Ratios!K32 -> 0.18534206 | AO32: ='Cash Flow'!E32/C32 -> 0.31075016 | AP32: =('Cash Flow'!E32+'Cash Flow'!F32)/Ratios!C32 -> 0.24723231 | AQ32: 9.98
A33: MSFT | B33: 42004 | C33: ='Income Statement'!C33 -> 86833 | D33: 59755 | E33: 33098 | F33: 27759 | G33: ='Income Statement'!P33 -> 27820 | H33: ='Income Statement'!R33 -> 22074 | I33: 85709 | J33: ='Balance Sheet'!I33 -> 114246 | K33: ='Balance Sheet'!R33 -> 172384 | L33: ='Balance Sheet'!X33 -> 45625 | M33: ='Balance Sheet'!AL33 -> 89784 | N33: 597 | O33: 4414 | P33: 0 | Q33: 20745 | R33: =SUM(O33:Q33) -> 25159 | S33: 5212 | T33: =-'Cash Flow'!F33 -> 5485 | U33: =(C33-C34)/C34 -> 0.1154029 | V33: =D33/C33 -> 0.68816003 | W33: =E33/C33 -> 0.38116845 | X33: =F33/C33 -> 0.31968261 | Y33: =G33/C33 -> 0.32038511 | Z33: =(G33-H33)/G33 -> 0.20654206 | AA33: =H33/C33 -> 0.25421211 | AB33: =H33/M33 -> 0.24585672 | AC33: =(F33*(1-Z33))/(Q33-I33+M33) -> 0.88741334 | AD33: =H33/K33 -> 0.12805133 | AE33: =(I33+'Balance Sheet'!E33)/L33 -> 2.3069151 | AF33: =J33/L33 -> 2.5040219 | AG33: =Q33-I33 -> -64964 | AH33: =Q33/M33 -> 0.23105453 | AI33: =Q33/SUM(Q33,M33) -> 0.1876883 | AJ33: =Q33/K33 -> 0.1203418 | AK33: =F33/N33 -> 46.497487 | AL33: =K33/M33 -> 1.9199857 | AM33: =T33/C33 -> 0.063167229 | AN33: ='Balance Sheet'!J33/Ratios!K33 -> 0.16129107 | AO33: ='Cash Flow'!E33/C33 -> 0.37118377 | AP33: =('Cash Flow'!E33+'Cash Flow'!F33)/Ratios!C33 -> 0.30801654 | AQ33: 10.9
A34: MSFT | B34: 41639 | C34: ='Income Statement'!C34 -> 77849 | D34: ='Income Statement'!E34 -> 57600 | E34: 30519 | F34: 26764 | G34: ='Income Statement'!P34 -> 27052 | H34: ='Income Statement'!R34 -> 21863 | I34: 77022 | J34: ='Balance Sheet'!I34 -> 101466 | K34: ='Balance Sheet'!R34 -> 142431 | L34: ='Balance Sheet'!X34 -> 37417 | M34: 78944 | N34: 429 | O34: 2462 | P34: 0 | Q34: 15665 | R34: =SUM(O34:Q34) -> 18127 | S34: 3755 | T34: =-'Cash Flow'!F34 -> 4257 | U34: =(C34-C35)/C35 -> 0.055966252 | V34: =D34/C34 -> 0.7398939 | W34: =E34/C34 -> 0.39202816 | X34: =F34/C34 -> 0.34379375 | Y34: =G34/C34 -> 0.34749322 | Z34: =(G34-H34)/G34 -> 0.19181576 | AA34: =H34/C34 -> 0.28083855 | AB34: =H34/M34 -> 0.27694315 | AC34: =(F34*(1-Z34))/(Q34-I34+M34) -> 1.2298995 | AD34: =H34/K34 -> 0.15349889 | AE34: =(I34+'Balance Sheet'!E34)/L34 -> 2.5258038 | AF34: =J34/L34 -> 2.711762 | AG34: =Q34-I34 -> -61357 | AH34: =Q34/M34 -> 0.1984318 | AI34: =Q34/SUM(Q34,M34) -> 0.16557621 | AJ34: =Q34/K34 -> 0.10998308 | AK34: =F34/N34 -> 62.386946 | AL34: =K34/M34 -> 1.804203 | AM34: =T34/C34 -> 0.054682783 | AN34: ='Balance Sheet'!J34/Ratios!K34 -> 0.15799931 | AO34: ='Cash Flow'!E34/C34 -> 0.37037085 | AP34: =('Cash Flow'!E34+'Cash Flow'!F34)/Ratios!C34 -> 0.31568806 | AQ34: 9.48
A35: MSFT | B35: 41274 | C35: ='Income Statement'!C35 -> 73723 | D35: ='Income Statement'!E35 -> 56193 | E35: 30714 | F35: ='Income Statement'!L35 -> 21763 | G35: ='Income Statement'!P35 -> 22267 | H35: ='Income Statement'!R35 -> 16978 | I35: ='Balance Sheet'!D35 -> 63040 | J35: ='Balance Sheet'!I35 -> 85084 | K35: ='Balance Sheet'!R35 -> 121271 | L35: ='Balance Sheet'!X35 -> 32688 | M35: ='Balance Sheet'!AL35 -> 66363 | N35: 380 | O35: 1977 | P35: 0 | Q35: 12000 | R35: =SUM(O35:Q35) -> 13977 | S35: 2967 | T35: =-'Cash Flow'!F35 -> 2305 | U35: =(C35-C36)/C36 -> 0.054044007 | V35: =D35/C35 -> 0.76221803 | W35: =E35/C35 -> 0.41661354 | X35: =F35/C35 -> 0.2951996 | Y35: =G35/C35 -> 0.302036 | Z35: =(G35-H35)/G35 -> 0.23752638 | AA35: =H35/C35 -> 0.23029448 | AB35: =H35/M35 -> 0.25583533 | AC35: =(F35*(1-Z35))/(Q35-I35+M35) -> 1.0829285 | AD35: =H35/K35 -> 0.14000049 | AE35: =(I35+'Balance Sheet'!E35)/L35 -> 2.4112824 | AF35: =J35/L35 -> 2.6029124 | AG35: =Q35-I35 -> -51040 | AH35: =Q35/M35 -> 0.18082365 | AI35: =Q35/SUM(Q35,M35) -> 0.15313349 | AJ35: =Q35/K35 -> 0.098951934 | AK35: =F35/N35 -> 57.271053 | AL35: =K35/M35 -> 1.8273888 | AM35: =T35/C35 -> 0.031265684 | AN35: ='Balance Sheet'!J35/Ratios!K35 -> 0.15857872 | AO35: ='Cash Flow'!E35/C35 -> 0.42898417 | AP35: =('Cash Flow'!E35+'Cash Flow'!F35)/Ratios!C35 -> 0.39771849 | AQ35: 7.92
A36: MSFT | B36: 40908 | C36: ='Income Statement'!C36 -> 69943 | D36: ='Income Statement'!E36 -> 54366 | E36: 29927 | F36: ='Income Statement'!L36 -> 27161 | G36: ='Income Statement'!P36 -> 28071 | H36: ='Income Statement'!R36 -> 23150 | I36: ='Balance Sheet'!D36 -> 52772 | J36: ='Balance Sheet'!I36 -> 74918 | K36: ='Balance Sheet'!R36 -> 108704 | L36: ='Balance Sheet'!X36 -> 28774 | M36: ='Balance Sheet'!AL36 -> 57083 | N36: 295 | O36: 1952 | P36: 0 | Q36: ='Balance Sheet'!V36+'Balance Sheet'!AA36 -> 11921 | R36: =SUM(O36:Q36) -> 13873 | S36: 2766 | T36: =-'Cash Flow'!F36 -> 2355 | U36: =(C36-C37)/C37 -> 0.11937456 | V36: =D36/C36 -> 0.77729008 | W36: =E36/C36 -> 0.42787699 | X36: =F36/C36 -> 0.3883305 | Y36: =G36/C36 -> 0.40134109 | Z36: =(G36-H36)/G36 -> 0.17530548 | AA36: =H36/C36 -> 0.3309838 | AB36: =H36/M36 -> 0.40554981 | AC36: =(F36*(1-Z36))/(Q36-I36+M36) -> 1.3799611 | AD36: =H36/K36 -> 0.21296364 | AE36: =(I36+'Balance Sheet'!E36)/L36 -> 2.354869 | AF36: =J36/L36 -> 2.60367 | AG36: =Q36-I36 -> -40851 | AH36: =Q36/M36 -> 0.20883626 | AI36: =Q36/SUM(Q36,M36) -> 0.1727581 | AJ36: =Q36/K36 -> 0.10966478 | AK36: =F36/N36 -> 92.071186 | AL36: =K36/M36 -> 1.9043148 | AM36: =T36/C36 -> 0.033670274 | AN36: ='Balance Sheet'!J36/Ratios!K36 -> 0.16550449 | AO36: ='Cash Flow'!E36/C36 -> 0.38594284 | AP36: =('Cash Flow'!E36+'Cash Flow'!F36)/Ratios!C36 -> 0.35227256 | AQ36: 6.82
A37: MSFT | B37: 40543 | C37: ='Income Statement'!C37 -> 62484 | D37: ='Income Statement'!E37 -> 50089 | E37: 26764 | F37: ='Income Statement'!L37 -> 24098 | G37: ='Income Statement'!P37 -> 25013 | H37: ='Income Statement'!R37 -> 18760 | I37: ='Balance Sheet'!D37 -> 36788 | J37: ='Balance Sheet'!I37 -> 55676 | K37: ='Balance Sheet'!R37 -> 86113 | L37: ='Balance Sheet'!X37 -> 26147 | M37: ='Balance Sheet'!AL37 -> 46175 | N37: 151 | O37: 1898 | P37: 0 | Q37: 4939 | R37: =SUM(O37:Q37) -> 6837 | S37: 2673 | T37: =-'Cash Flow'!F37 -> 1977 | U37: =(C37-C38)/C38 -> 0.069254068 | V37: =D37/C37 -> 0.80162922 | W37: =E37/C37 -> 0.42833365 | X37: =F37/C37 -> 0.38566673 | Y37: =G37/C37 -> 0.40031048 | Z37: =(G37-H37)/G37 -> 0.24999001 | AA37: =H37/C37 -> 0.30023686 | AB37: =H37/M37 -> 0.40628045 | AC37: =(F37*(1-Z37))/(Q37-I37+M37) -> 1.2616041 | AD37: =H37/K37 -> 0.21785329 | AE37: =(I37+'Balance Sheet'!E37)/L37 -> 1.9046927 | AF37: =J37/L37 -> 2.1293456 | AG37: =Q37-I37 -> -31849 | AH37: =Q37/M37 -> 0.10696264 | AI37: =Q37/SUM(Q37,M37) -> 0.096627147 | AJ37: =Q37/K37 -> 0.057354871 | AK37: =F37/N37 -> 159.5894 | AL37: =K37/M37 -> 1.8649269 | AM37: =T37/C37 -> 0.0316401 | AN37: ='Balance Sheet'!J37/Ratios!K37 -> 0.18881005 | AO37: ='Cash Flow'!E37/C37 -> 0.38526663 | AP37: =('Cash Flow'!E37+'Cash Flow'!F37)/Ratios!C37 -> 0.35362653 | AQ37: 5.33
A38: MSFT | B38: 40178 | C38: ='Income Statement'!C38 -> 58437 | D38: ='Income Statement'!E38 -> 46282 | E38: 22984 | F38: ='Income Statement'!L38 -> 21225 | G38: ='Income Statement'!P38 -> 19821 | H38: ='Income Statement'!R38 -> 14569 | I38: ='Balance Sheet'!D38 -> 31447 | J38: ='Balance Sheet'!I38 -> 49280 | K38: ='Balance Sheet'!R38 -> 77888 | L38: ='Balance Sheet'!X38 -> 27034 | M38: ='Balance Sheet'!AL38 -> 39558 | N38: 38 | O38: 2385 | P38: 0 | Q38: 3746 | R38: =SUM(O38:Q38) -> 6131 | S38: 2562 | T38: =-'Cash Flow'!F38 -> 3119 | U38: =(C38-C39)/C39 -> -0.032820258 | V38: =D38/C38 -> 0.79199822 | W38: =E38/C38 -> 0.39331246 | X38: =F38/C38 -> 0.36321166 | Y38: =G38/C38 -> 0.33918579 | Z38: =(G38-H38)/G38 -> 0.26497149 | AA38: =H38/C38 -> 0.24931122 | AB38: =H38/M38 -> 0.36829466 | AC38: =(F38*(1-Z38))/(Q38-I38+M38) -> 1.3157612 | AD38: =H38/K38 -> 0.18705064 | AE38: =(I38+'Balance Sheet'!E38)/L38 -> 1.5772361 | AF38: =J38/L38 -> 1.8228897 | AG38: =Q38-I38 -> -27701 | AH38: =Q38/M38 -> 0.094696395 | AI38: =Q38/SUM(Q38,M38) -> 0.086504711 | AJ38: =Q38/K38 -> 0.0480947 | AL38: =K38/M38 -> 1.968957 | AM38: =T38/C38 -> 0.053373719 | AN38: ='Balance Sheet'!J38/Ratios!K38 -> 0.19363702 | AO38: ='Cash Flow'!E38/C38 -> 0.32576963 | AP38: =('Cash Flow'!E38+'Cash Flow'!F38)/Ratios!C38 -> 0.27239591 | AQ38: 4.44
A39: MSFT | B39: 39813 | C39: ='Income Statement'!C39 -> 60420 | D39: ='Income Statement'!E39 -> 48822 | E39: 26164 | F39: ='Income Statement'!L39 -> 22492 | G39: ='Income Statement'!P39 -> 23814 | H39: ='Income Statement'!R39 -> 17681 | I39: ='Balance Sheet'!D39 -> 23662 | J39: ='Balance Sheet'!I39 -> 43242 | K39: ='Balance Sheet'!R39 -> 72793 | L39: ='Balance Sheet'!X39 -> 29886 | M39: ='Balance Sheet'!AL39 -> 36286 | N39: 0 | O39: 2208 | P39: 1 | Q39: 0 | R39: =SUM(O39:Q39) -> 2209 | S39: 2056 | T39: =-'Cash Flow'!F39 -> 3182 | U39: =(C39-C40)/C40 -> 0.18187864 | V39: =D39/C39 -> 0.80804369 | W39: =E39/C39 -> 0.43303542 | X39: =F39/C39 -> 0.37226084 | Y39: =G39/C39 -> 0.39414101 | Z39: =(G39-H39)/G39 -> 0.25753758 | AA39: =H39/C39 -> 0.29263489 | AB39: =H39/M39 -> 0.48726782 | AC39: =(F39*(1-Z39))/(Q39-I39+M39) -> 1.3228347 | AD39: =H39/K39 -> 0.24289423 | AE39: =(I39+'Balance Sheet'!E39)/L39 -> 1.2464365 | AF39: =J39/L39 -> 1.4468982 | AG39: =Q39-I39 -> -23662 | AH39: =Q39/M39 -> 0 | AI39: =Q39/SUM(Q39,M39) -> 0 | AJ39: =Q39/K39 -> 0 | AL39: =K39/M39 -> 2.0060905 | AM39: =T39/C39 -> 0.052664681 | AN39: ='Balance Sheet'!J39/Ratios!K39 -> 0.17232426 | AO39: ='Cash Flow'!E39/C39 -> 0.35769613 | AP39: =('Cash Flow'!E39+'Cash Flow'!F39)/Ratios!C39 -> 0.30503145 | AQ39: 3.97
A40: MSFT | B40: 39447 | C40: ='Income Statement'!C40 -> 51122 | D40: ='Income Statement'!E40 -> 40429 | E40: 20441 | F40: ='Income Statement'!L40 -> 18524 | G40: ='Income Statement'!P40 -> 20101 | H40: ='Income Statement'!R40 -> 14065 | I40: ='Balance Sheet'!D40 -> 23411 | J40: ='Balance Sheet'!I40 -> 40168 | K40: ='Balance Sheet'!R40 -> 63171 | L40: ='Balance Sheet'!X40 -> 23754 | M40: ='Balance Sheet'!AL40 -> 31097 | N40: 0 | O40: 1341 | P40: 0 | Q40: 0 | R40: =SUM(O40:Q40) -> 1341 | S40: 1440 | T40: =-'Cash Flow'!F40 -> 2264 | U40: =(C40-C41)/C41 -> 0.15446457 | V40: =D40/C40 -> 0.79083369 | W40: =E40/C40 -> 0.39984742 | X40: =F40/C40 -> 0.36234889 | Y40: =G40/C40 -> 0.39319667 | Z40: =(G40-H40)/G40 -> 0.30028357 | AA40: =H40/C40 -> 0.27512617 | AB40: =H40/M40 -> 0.45229443 | AC40: =(F40*(1-Z40))/(Q40-I40+M40) -> 1.686384 | AD40: =H40/K40 -> 0.22264963 | AE40: =(I40+'Balance Sheet'!E40)/L40 -> 1.4628694 | AF40: =J40/L40 -> 1.6909994 | AG40: =Q40-I40 -> -23411 | AH40: =Q40/M40 -> 0 | AI40: =Q40/SUM(Q40,M40) -> 0 | AJ40: =Q40/K40 -> 0 | AL40: =K40/M40 -> 2.0314178 | AM40: =T40/C40 -> 0.044286217 | AN40: ='Balance Sheet'!J40/Ratios!K40 -> 0.14826424 | AO40: ='Cash Flow'!E40/C40 -> 0.34810845 | AP40: =('Cash Flow'!E40+'Cash Flow'!F40)/Ratios!C40 -> 0.30382223 | AQ40: 3.32
A41: MSFT | B41: 39082 | C41: ='Income Statement'!C41 -> 44282 | D41: ='Income Statement'!E41 -> 36632 | E41: 18782 | F41: ='Income Statement'!L41 -> 16472 | G41: ='Income Statement'!P41 -> 18262 | H41: ='Income Statement'!R41 -> 12599 | I41: ='Balance Sheet'!D41 -> 34161 | J41: ='Balance Sheet'!I41 -> 49010 | K41: ='Balance Sheet'!R41 -> 69597 | L41: ='Balance Sheet'!X41 -> 22442 | M41: ='Balance Sheet'!AL41 -> 40104 | N41: 0 | O41: 885 | P41: 0 | Q41: 0 | R41: =SUM(O41:Q41) -> 885 | S41: 903 | T41: =-'Cash Flow'!F41 -> 1578 | V41: =D41/C41 -> 0.82724358 | W41: =E41/C41 -> 0.42414525 | X41: =F41/C41 -> 0.37197959 | Y41: =G41/C41 -> 0.41240233 | Z41: =(G41-H41)/G41 -> 0.31009747 | AA41: =H41/C41 -> 0.28451741 | AB41: =H41/M41 -> 0.31415819 | AC41: =(F41*(1-Z41))/(Q41-I41+M41) -> 1.9121781 | AD41: =H41/K41 -> 0.18102792 | AE41: =(I41+'Balance Sheet'!E41)/L41 -> 1.9373051 | AF41: =J41/L41 -> 2.1838517 | AG41: =Q41-I41 -> -34161 | AH41: =Q41/M41 -> 0 | AI41: =Q41/SUM(Q41,M41) -> 0 | AJ41: =Q41/K41 -> 0 | AL41: =K41/M41 -> 1.7354129 | AM41: =T41/C41 -> 0.035635247 | AN41: ='Balance Sheet'!J41/Ratios!K41 -> 0.10378321 | AO41: ='Cash Flow'!E41/C41 -> 0.32527889 | AP41: =('Cash Flow'!E41+'Cash Flow'!F41)/Ratios!C41 -> 0.28964365 | AQ41: 3.99
A42: GOOG | B42: 46022 | C42: ='Income Statement'!C42 -> 402836 | D42: ='Income Statement'!E42 -> 240301 | E42: 156375 | F42: ='Income Statement'!L42 -> 129039 | G42: ='Income Statement'!P42 -> 158826 | H42: ='Income Statement'!R42 -> 132170 | I42: ='Balance Sheet'!D42 -> 126843 | J42: ='Balance Sheet'!I42 -> 206038 | K42: ='Balance Sheet'!R42 -> 595281 | L42: ='Balance Sheet'!X42 -> 102745 | M42: ='Balance Sheet'!AL42 -> 415265 | N42: 736 | O42: 15954 | P42: 2500 | Q42: 48543 | R42: =SUM(O42:Q42) -> 66997 | S42: 21136 | T42: =-'Cash Flow'!F42 -> 91447 | U42: =(C42-C43)/C43 -> 0.15090081 | V42: =D42/C42 -> 0.59652315 | W42: =E42/C42 -> 0.38818527 | X42: =F42/C42 -> 0.32032639 | Y42: =G42/C42 -> 0.39426963 | Z42: =(G42-H42)/G42 -> 0.16783146 | AA42: =H42/C42 -> 0.32809878 | AB42: =H42/M42 -> 0.31827869 | AC42: =(F42*(1-Z42))/(Q42-I42+M42) -> 0.31867463 | AD42: =H42/K42 -> 0.2220296 | AE42: =(I42+'Balance Sheet'!E42)/L42 -> 1.8466008 | AF42: =J42/L42 -> 2.0053336 | AG42: =Q42-I42 -> -78300 | AH42: =Q42/M42 -> 0.11689644 | AI42: =Q42/SUM(Q42,M42) -> 0.10466184 | AJ42: =Q42/K42 -> 0.081546362 | AK42: =F42/N42 -> 175.32473 | AL42: =K42/M42 -> 1.4334967 | AM42: =T42/C42 -> 0.22700801 | AN42: ='Balance Sheet'!J42/Ratios!K42 -> 0.60526541 | AO42: ='Cash Flow'!E42/C42 -> 0.40888352 | AP42: =('Cash Flow'!E42+'Cash Flow'!F42)/Ratios!C42 -> 0.1818755 | AQ42: 34.35
A43: GOOG | B43: 45657 | C43: ='Income Statement'!C43 -> 350018 | D43: ='Income Statement'!E43 -> 203712 | E43: 129538 | F43: ='Income Statement'!L43 -> 112390 | G43: ='Income Statement'!P43 -> 119815 | H43: ='Income Statement'!R43 -> 100118 | I43: ='Balance Sheet'!D43 -> 95657 | J43: ='Balance Sheet'!I43 -> 163711 | K43: ='Balance Sheet'!R43 -> 450256 | L43: ='Balance Sheet'!X43 -> 89122 | M43: ='Balance Sheet'!AL43 -> 325084 | N43: 268 | O43: 14578 | P43: 1677 | Q43: 11882 | R43: =SUM(O43:Q43) -> 28137 | S43: 15311 | T43: =-'Cash Flow'!F43 -> 52535 | U43: =(C43-C44)/C44 -> 0.13866243 | V43: =D43/C43 -> 0.58200435 | W43: =E43/C43 -> 0.37008954 | X43: =F43/C43 -> 0.32109777 | Y43: =G43/C43 -> 0.34231097 | Z43: =(G43-H43)/G43 -> 0.16439511 | AA43: =H43/C43 -> 0.28603672 | AB43: =H43/M43 -> 0.30797578 | AC43: =(F43*(1-Z43))/(Q43-I43+M43) -> 0.38918413 | AD43: =H43/K43 -> 0.22235795 | AE43: =(I43+'Balance Sheet'!E43)/L43 -> 1.6606113 | AF43: =J43/L43 -> 1.8369314 | AG43: =Q43-I43 -> -83775 | AH43: =Q43/M43 -> 0.036550553 | AI43: =Q43/SUM(Q43,M43) -> 0.035261718 | AJ43: =Q43/K43 -> 0.026389432 | AK43: =F43/N43 -> 419.36567 | AL43: =K43/M43 -> 1.3850451 | AM43: =T43/C43 -> 0.15009228 | AN43: ='Balance Sheet'!J43/Ratios!K43 -> 0.5863642 | AO43: ='Cash Flow'!E43/C43 -> 0.35797873 | AP43: =('Cash Flow'!E43+'Cash Flow'!F43)/Ratios!C43 -> 0.20788645 | AQ43: 26.62
A44: GOOG | B44: 45291 | C44: ='Income Statement'!C44 -> 307394 | D44: ='Income Statement'!E44 -> 175022 | E44: 100172 | F44: ='Income Statement'!L44 -> 84293 | G44: ='Income Statement'!P44 -> 85717 | H44: ='Income Statement'!R44 -> 73795 | I44: ='Balance Sheet'!D44 -> 110916 | J44: ='Balance Sheet'!I44 -> 171530 | K44: ='Balance Sheet'!R44 -> 402392 | L44: ='Balance Sheet'!X44 -> 81814 | M44: ='Balance Sheet'!AL44 -> 283379 | N44: 308 | O44: 15251 | P44: 1666 | Q44: =13000-130 -> 12870 | R44: =SUM(O44:Q44) -> 29787 | S44: 11946 | T44: =-'Cash Flow'!F44 -> 32251 | U44: =(C44-C45)/C45 -> 0.086827702 | V44: =D44/C44 -> 0.56937351 | W44: =E44/C44 -> 0.32587494 | X44: =F44/C44 -> 0.2742181 | Y44: =G44/C44 -> 0.2788506 | Z44: =(G44-H44)/G44 -> 0.1390856 | AA44: =H44/C44 -> 0.24006649 | AB44: =H44/M44 -> 0.26041097 | AC44: =(F44*(1-Z44))/(Q44-I44+M44) -> 0.39156037 | AD44: =H44/K44 -> 0.18339082 | AE44: =(I44+'Balance Sheet'!E44)/L44 -> 1.9419659 | AF44: =J44/L44 -> 2.0965849 | AG44: =Q44-I44 -> -98046 | AH44: =Q44/M44 -> 0.045416209 | AI44: =Q44/SUM(Q44,M44) -> 0.043443185 | AJ44: =Q44/K44 -> 0.031983737 | AK44: =F44/N44 -> 273.67857 | AL44: =K44/M44 -> 1.4199782 | AM44: =T44/C44 -> 0.10491747 | AN44: ='Balance Sheet'!J44/Ratios!K44 -> 0.53652657 | AO44: ='Cash Flow'!E44/C44 -> 0.3309954 | AP44: =('Cash Flow'!E44+'Cash Flow'!F44)/Ratios!C44 -> 0.22607793 | AQ44: 22.74
A45: GOOG | B45: 44926 | C45: ='Income Statement'!C45 -> 282836 | D45: ='Income Statement'!E45 -> 156633 | E45: 90771 | F45: ='Income Statement'!L45 -> 74842 | G45: ='Income Statement'!P45 -> 71328 | H45: ='Income Statement'!R45 -> 59972 | I45: ='Balance Sheet'!D45 -> 113762 | J45: ='Balance Sheet'!I45 -> 164795 | K45: ='Balance Sheet'!R45 -> 365264 | L45: ='Balance Sheet'!X45 -> 69300 | M45: ='Balance Sheet'!AL45 -> 256144 | N45: 357 | O45: 14978 | P45: 2142 | Q45: 12857 | R45: =SUM(O45:Q45) -> 29977 | S45: 15287 | T45: =-'Cash Flow'!F45 -> 31485 | U45: =(C45-C46)/C46 -> 0.097808156 | V45: =D45/C45 -> 0.55379443 | W45: =E45/C45 -> 0.32093156 | X45: =F45/C45 -> 0.26461271 | Y45: =G45/C45 -> 0.25218855 | Z45: =(G45-H45)/G45 -> 0.15920817 | AA45: =H45/C45 -> 0.21203807 | AB45: =H45/M45 -> 0.23413392 | AC45: =(F45*(1-Z45))/(Q45-I45+M45) -> 0.40535267 | AD45: =H45/K45 -> 0.16418809 | AE45: =(I45+'Balance Sheet'!E45)/L45 -> 2.2225108 | AF45: =J45/L45 -> 2.3779942 | AG45: =Q45-I45 -> -100905 | AH45: =Q45/M45 -> 0.050194422 | AI45: =Q45/SUM(Q45,M45) -> 0.047795361 | AJ45: =Q45/K45 -> 0.035199198 | AK45: =F45/N45 -> 209.64146 | AL45: =K45/M45 -> 1.4260104 | AM45: =T45/C45 -> 0.11131893 | AN45: ='Balance Sheet'!J45/Ratios!K45 -> 0.50946986 | AO45: ='Cash Flow'!E45/C45 -> 0.32349135 | AP45: =('Cash Flow'!E45+'Cash Flow'!F45)/Ratios!C45 -> 0.21217243 | AQ45: 19.93
A46: GOOG | B46: 44561 | C46: ='Income Statement'!C46 -> 257637 | D46: ='Income Statement'!E46 -> 146698 | E46: 91144 | F46: ='Income Statement'!L46 -> 78714 | G46: ='Income Statement'!P46 -> 90734 | H46: ='Income Statement'!R46 -> 76033 | I46: ='Balance Sheet'!D46 -> 139649 | J46: ='Balance Sheet'!I46 -> 188143 | K46: ='Balance Sheet'!R46 -> 359268 | L46: ='Balance Sheet'!X46 -> 64254 | M46: ='Balance Sheet'!AL46 -> 251635 | N46: 346 | O46: 13578 | P46: 2086 | Q46: 12844 | R46: =SUM(O46:Q46) -> 28508 | S46: 11555 | T46: =-'Cash Flow'!F46 -> 24640 | U46: =(C46-C47)/C47 -> 0.41150076 | V46: =D46/C46 -> 0.56939803 | W46: =E46/C46 -> 0.35376906 | X46: =F46/C46 -> 0.30552289 | Y46: =G46/C46 -> 0.35217768 | Z46: =(G46-H46)/G46 -> 0.16202306 | AA46: =H46/C46 -> 0.29511677 | AB46: =H46/M46 -> 0.3021559 | AC46: =(F46*(1-Z46))/(Q46-I46+M46) -> 0.52840276 | AD46: =H46/K46 -> 0.2116331 | AE46: =(I46+'Balance Sheet'!E46)/L46 -> 2.8001214 | AF46: =J46/L46 -> 2.9281134 | AG46: =Q46-I46 -> -126805 | AH46: =Q46/M46 -> 0.051042184 | AI46: =Q46/SUM(Q46,M46) -> 0.048563402 | AJ46: =Q46/K46 -> 0.03575047 | AK46: =F46/N46 -> 227.49711 | AL46: =K46/M46 -> 1.4277346 | AM46: =T46/C46 -> 0.095638437 | AN46: ='Balance Sheet'!J46/Ratios!K46 -> 0.44526927 | AO46: ='Cash Flow'!E46/C46 -> 0.35574083 | AP46: =('Cash Flow'!E46+'Cash Flow'!F46)/Ratios!C46 -> 0.26010239 | AQ46: 19
A47: GOOG | B47: 44196 | C47: ='Income Statement'!C47 -> 182527 | D47: ='Income Statement'!E47 -> 97795 | E47: 54903 | F47: ='Income Statement'!L47 -> 41224 | G47: ='Income Statement'!P47 -> 48082 | H47: ='Income Statement'!R47 -> 40269 | I47: ='Balance Sheet'!D47 -> 136694 | J47: ='Balance Sheet'!I47 -> 174296 | K47: ='Balance Sheet'!R47 -> 319616 | L47: ='Balance Sheet'!X47 -> 56834 | M47: ='Balance Sheet'!AL47 -> 222544 | N47: 135 | O47: 12840 | P47: 1201 | Q47: 13831 | R47: =SUM(O47:Q47) -> 27872 | S47: 12905 | T47: =-'Cash Flow'!F47 -> 22281 | U47: =(C47-C48)/C48 -> 0.12770532 | V47: =D47/C47 -> 0.53578375 | W47: =E47/C47 -> 0.30079386 | X47: =F47/C47 -> 0.22585152 | Y47: =G47/C47 -> 0.26342404 | Z47: =(G47-H47)/G47 -> 0.16249324 | AA47: =H47/C47 -> 0.22061942 | AB47: =H47/M47 -> 0.18094849 | AC47: =(F47*(1-Z47))/(Q47-I47+M47) -> 0.34635867 | AD47: =H47/K47 -> 0.12599182 | AE47: =(I47+'Balance Sheet'!E47)/L47 -> 2.9573495 | AF47: =J47/L47 -> 3.0667558 | AG47: =Q47-I47 -> -122863 | AH47: =Q47/M47 -> 0.062149507 | AI47: =Q47/SUM(Q47,M47) -> 0.058512956 | AJ47: =Q47/K47 -> 0.043273804 | AK47: =F47/N47 -> 305.36296 | AL47: =K47/M47 -> 1.4361924 | AM47: =T47/C47 -> 0.12206961 | AN47: ='Balance Sheet'!J47/Ratios!K47 -> 0.43387377 | AO47: ='Cash Flow'!E47/C47 -> 0.35679105 | AP47: =('Cash Flow'!E47+'Cash Flow'!F47)/Ratios!C47 -> 0.23472144 | AQ47: 16.48
A48: GOOG | B48: 43830 | C48: ='Income Statement'!C48 -> 161857 | D48: ='Income Statement'!E48 -> 89961 | E48: 47579 | F48: ='Income Statement'!L48 -> 34231 | G48: ='Income Statement'!P48 -> 39625 | H48: ='Income Statement'!R48 -> 34343 | I48: ='Balance Sheet'!D48 -> 119675 | J48: ='Balance Sheet'!I48 -> 152578 | K48: ='Balance Sheet'!R48 -> 275909 | L48: ='Balance Sheet'!X48 -> 45221 | M48: ='Balance Sheet'!AL48 -> 201442 | N48: 100 | O48: 11413 | P48: 711 | Q48: 4000 | R48: =SUM(O48:Q48) -> 16124 | S48: 10856 | T48: =-'Cash Flow'!F48 -> 23548 | U48: =(C48-C49)/C49 -> 0.1830009 | V48: =D48/C48 -> 0.55580543 | W48: =E48/C48 -> 0.29395701 | X48: =F48/C48 -> 0.21148915 | Y48: =G48/C48 -> 0.24481487 | Z48: =(G48-H48)/G48 -> 0.13329968 | AA48: =H48/C48 -> 0.21218112 | AB48: =H48/M48 -> 0.1704858 | AC48: =(F48*(1-Z48))/(Q48-I48+M48) -> 0.34591415 | AD48: =H48/K48 -> 0.1244722 | AE48: =(I48+'Balance Sheet'!E48)/L48 -> 3.2543951 | AF48: =J48/L48 -> 3.3740519 | AG48: =Q48-I48 -> -115675 | AH48: =Q48/M48 -> 0.019856832 | AI48: =Q48/SUM(Q48,M48) -> 0.019470215 | AJ48: =Q48/K48 -> 0.014497534 | AK48: =F48/N48 -> 342.31 | AL48: =K48/M48 -> 1.3696697 | AM48: =T48/C48 -> 0.14548645 | AN48: ='Balance Sheet'!J48/Ratios!K48 -> 0.4173405 | AO48: ='Cash Flow'!E48/C48 -> 0.33684054 | AP48: =('Cash Flow'!E48+'Cash Flow'!F48)/Ratios!C48 -> 0.1913541 | AQ48: 14.63
A49: GOOG | B49: 43465 | C49: ='Income Statement'!C49 -> 136819 | D49: ='Income Statement'!E49 -> 77270 | E49: 40421 | F49: ='Income Statement'!L49 -> 26321 | G49: ='Income Statement'!P49 -> 34913 | H49: ='Income Statement'!R49 -> 30736 | I49: ='Balance Sheet'!D49 -> 109140 | J49: ='Balance Sheet'!I49 -> 135676 | K49: ='Balance Sheet'!R49 -> 232792 | L49: ='Balance Sheet'!X49 -> 34620 | M49: ='Balance Sheet'!AL49 -> 177628 | N49: 114 | O49: 10047 | P49: 62 | Q49: 3950 | R49: =SUM(O49:Q49) -> 14059 | S49: 8164 | T49: =-'Cash Flow'!F49 -> 25139 | U49: =(C49-C50)/C50 -> 0.23421587 | V49: =D49/C49 -> 0.56476074 | W49: =E49/C49 -> 0.29543411 | X49: =F49/C49 -> 0.19237825 | Y49: =G49/C49 -> 0.25517655 | Z49: =(G49-H49)/G49 -> 0.11964025 | AA49: =H49/C49 -> 0.22464716 | AB49: =H49/M49 -> 0.17303578 | AC49: =(F49*(1-Z49))/(Q49-I49+M49) -> 0.31988665 | AD49: =H49/K49 -> 0.13203203 | AE49: =(I49+'Balance Sheet'!E49)/L49 -> 3.7646736 | AF49: =J49/L49 -> 3.9190064 | AG49: =Q49-I49 -> -105190 | AH49: =Q49/M49 -> 0.022237485 | AI49: =Q49/SUM(Q49,M49) -> 0.021753737 | AJ49: =Q49/K49 -> 0.016967937 | AK49: =F49/N49 -> 230.88596 | AL49: =K49/M49 -> 1.3105591 | AM49: =T49/C49 -> 0.1837391 | AN49: ='Balance Sheet'!J49/Ratios!K49 -> 0.35442369 | AO49: ='Cash Flow'!E49/C49 -> 0.35061651 | AP49: =('Cash Flow'!E49+'Cash Flow'!F49)/Ratios!C49 -> 0.16687741 | AQ49: 12.77
A50: GOOG | B50: 43100 | C50: ='Income Statement'!C50 -> 110855 | D50: ='Income Statement'!E50 -> 65272 | E50: 35781 | F50: ='Income Statement'!L50 -> 26146 | G50: ='Income Statement'!P50 -> 27193 | H50: ='Income Statement'!R50 -> 12662 | I50: ='Balance Sheet'!D50 -> 101871 | J50: ='Balance Sheet'!I50 -> 124308 | K50: ='Balance Sheet'!R50 -> 197295 | L50: ='Balance Sheet'!X50 -> 24183 | M50: ='Balance Sheet'!AL50 -> 152502 | N50: 109 | O50: 8753 | P50: 26 | Q50: 3943 | R50: =SUM(O50:Q50) -> 12722 | S50: 6103 | T50: =-'Cash Flow'!F50 -> 13184 | U50: =(C50-C51)/C51 -> 0.2280109 | V50: =D50/C50 -> 0.5888052 | W50: =E50/C50 -> 0.32277299 | X50: =F50/C50 -> 0.23585765 | Y50: =G50/C50 -> 0.24530242 | Z50: =(G50-H50)/G50 -> 0.53436546 | AA50: =H50/C50 -> 0.11422128 | AB50: =H50/M50 -> 0.08302842 | AC50: =(F50*(1-Z50))/(Q50-I50+M50) -> 0.22308207 | AD50: =H50/K50 -> 0.064178008 | AE50: =(I50+'Balance Sheet'!E50)/L50 -> 4.9859819 | AF50: =J50/L50 -> 5.1403052 | AG50: =Q50-I50 -> -97928 | AH50: =Q50/M50 -> 0.025855399 | AI50: =Q50/SUM(Q50,M50) -> 0.025203746 | AJ50: =Q50/K50 -> 0.019985301 | AK50: =F50/N50 -> 239.87156 | AL50: =K50/M50 -> 1.2937207 | AM50: =T50/C50 -> 0.11893013 | AN50: ='Balance Sheet'!J50/Ratios!K50 -> 0.30232393 | AO50: ='Cash Flow'!E50/C50 -> 0.33459023 | AP50: =('Cash Flow'!E50+'Cash Flow'!F50)/Ratios!C50 -> 0.2156601 | AQ50: 10.97
A51: GOOG | B51: 42735 | C51: ='Income Statement'!C51 -> 90272 | D51: ='Income Statement'!E51 -> 55134 | E51: 29816 | F51: ='Income Statement'!L51 -> 23716 | G51: ='Income Statement'!P51 -> 24150 | H51: ='Income Statement'!R51 -> 19478 | I51: ='Balance Sheet'!D51 -> 86333 | J51: ='Balance Sheet'!I51 -> 105408 | K51: ='Balance Sheet'!R51 -> 167497 | L51: ='Balance Sheet'!X51 -> 16756 | M51: ='Balance Sheet'!AL51 -> 139036 | N51: 124 | O51: 7937 | P51: 0 | Q51: 3935 | R51: =SUM(O51:Q51) -> 11872 | S51: 5267 | T51: =-'Cash Flow'!F51 -> 10212 | U51: =(C51-C52)/C52 -> 0.20380322 | V51: =D51/C51 -> 0.61075417 | W51: =E51/C51 -> 0.33029068 | X51: =F51/C51 -> 0.26271712 | Y51: =G51/C51 -> 0.26752481 | Z51: =(G51-H51)/G51 -> 0.19345756 | AA51: =H51/C51 -> 0.21577012 | AB51: =H51/M51 -> 0.14009321 | AC51: =(F51*(1-Z51))/(Q51-I51+M51) -> 0.33772309 | AD51: =H51/K51 -> 0.11628865 | AE51: =(I51+'Balance Sheet'!E51)/L51 -> 6.0017307 | AF51: =J51/L51 -> 6.2907615 | AG51: =Q51-I51 -> -82398 | AH51: =Q51/M51 -> 0.028302022 | AI51: =Q51/SUM(Q51,M51) -> 0.027523064 | AJ51: =Q51/K51 -> 0.023492958 | AK51: =F51/N51 -> 191.25806 | AL51: =K51/M51 -> 1.2047024 | AM51: =T51/C51 -> 0.11312478 | AN51: ='Balance Sheet'!J51/Ratios!K51 -> 0.28374837 | AO51: ='Cash Flow'!E51/C51 -> 0.39919355 | AP51: =('Cash Flow'!E51+'Cash Flow'!F51)/Ratios!C51 -> 0.28606877 | AQ51: 10.06
A52: GOOG | B52: 42369 | C52: ='Income Statement'!C52 -> 74989 | D52: ='Income Statement'!E52 -> 46825 | E52: 24384 | F52: ='Income Statement'!L52 -> 19360 | G52: ='Income Statement'!P52 -> 19651 | H52: ='Income Statement'!R52 -> 16348 | I52: ='Balance Sheet'!D52 -> 73066 | J52: ='Balance Sheet'!I52 -> 90114 | K52: ='Balance Sheet'!R52 -> 147461 | L52: ='Balance Sheet'!X52 -> 19310 | M52: ='Balance Sheet'!AL52 -> 120331 | N52: 104 | O52: 7406 | P52: 225 | Q52: 2995 | R52: =SUM(O52:Q52) -> 10626 | S52: 4132 | T52: =-'Cash Flow'!F52 -> 9915 | U52: =(C52-C53)/C53 -> 0.13617975 | V52: =D52/C52 -> 0.62442492 | W52: =E52/C52 -> 0.32516769 | X52: =F52/C52 -> 0.2581712 | Y52: =G52/C52 -> 0.26205177 | Z52: =(G52-H52)/G52 -> 0.16808305 | AA52: =H52/C52 -> 0.21800531 | AB52: =H52/M52 -> 0.13585859 | AC52: =(F52*(1-Z52))/(Q52-I52+M52) -> 0.32045189 | AD52: =H52/K52 -> 0.11086321 | AE52: =(I52+'Balance Sheet'!E52)/L52 -> 4.5041429 | AF52: =J52/L52 -> 4.6667012 | AG52: =Q52-I52 -> -70071 | AH52: =Q52/M52 -> 0.024889679 | AI52: =Q52/SUM(Q52,M52) -> 0.024285228 | AJ52: =Q52/K52 -> 0.020310455 | AK52: =F52/N52 -> 186.15385 | AL52: =K52/M52 -> 1.2254614 | AM52: =T52/C52 -> 0.13221939 | AN52: ='Balance Sheet'!J52/Ratios!K52 -> 0.27224826 | AO52: ='Cash Flow'!E52/C52 -> 0.34703757 | AP52: =('Cash Flow'!E52+'Cash Flow'!F52)/Ratios!C52 -> 0.21481817 | AQ52: 8.75
A53: GOOG | B53: 42004 | C53: ='Income Statement'!C53 -> 66001 | D53: ='Income Statement'!E53 -> 40688 | E53: 21476 | F53: ='Income Statement'!L53 -> 16496 | G53: ='Income Statement'!P53 -> 17259 | H53: ='Income Statement'!R53 -> 14136 | I53: ='Balance Sheet'!D53 -> 64395 | J53: ='Balance Sheet'!I53 -> 78656 | K53: ='Balance Sheet'!R53 -> 129187 | L53: ='Balance Sheet'!X53 -> 16779 | M53: ='Balance Sheet'!AL53 -> 103860 | N53: 101 | O53: 6183 | P53: 246 | Q53: 2992 | R53: =SUM(O53:Q53) -> 9421 | S53: 3523 | T53: =-'Cash Flow'!F53 -> 10959 | U53: =(C53-C54)/C54 -> 0.10323443 | V53: =D53/C53 -> 0.61647551 | W53: =E53/C53 -> 0.32538901 | X53: =F53/C53 -> 0.24993561 | Y53: =G53/C53 -> 0.26149604 | Z53: =(G53-H53)/G53 -> 0.18094907 | AA53: =H53/C53 -> 0.21417857 | AB53: =H53/M53 -> 0.1361063 | AC53: =(F53*(1-Z53))/(Q53-I53+M53) -> 0.31822936 | AD53: =H53/K53 -> 0.10942277 | AE53: =(I53+'Balance Sheet'!E53)/L53 -> 4.484415 | AF53: =J53/L53 -> 4.6877645 | AG53: =Q53-I53 -> -61403 | AH53: =Q53/M53 -> 0.028808011 | AI53: =Q53/SUM(Q53,M53) -> 0.028001348 | AJ53: =Q53/K53 -> 0.023160225 | AK53: =F53/N53 -> 163.32673 | AL53: =K53/M53 -> 1.2438571 | AM53: =T53/C53 -> 0.16604294 | AN53: ='Balance Sheet'!J53/Ratios!K53 -> 0.25347752 | AO53: ='Cash Flow'!E53/C53 -> 0.33902517 | AP53: =('Cash Flow'!E53+'Cash Flow'!F53)/Ratios!C53 -> 0.17298223 | AQ53: 7.67
A54: GOOG | B54: 41639 | C54: 59825 | D54: =C54-21993-3865 -> 33967 | E54: 18028 | F54: 13966 | G54: 14496 | H54: 12920 | I54: ='Balance Sheet'!D54 -> 58717 | J54: ='Balance Sheet'!I54 -> 72886 | K54: ='Balance Sheet'!R54 -> 110920 | L54: ='Balance Sheet'!X54 -> 15908 | M54: ='Balance Sheet'!AL54 -> 87309 | N54: 83 | O54: 4038 | P54: 255 | Q54: 2990 | R54: =SUM(O54:Q54) -> 7283 | S54: 2781 | T54: =-'Cash Flow'!F54 -> 7358 | U54: =(C54-C55)/C55 -> 0.19232686 | V54: =D54/C54 -> 0.56777267 | W54: =E54/C54 -> 0.30134559 | X54: =F54/C54 -> 0.23344756 | Y54: =G54/C54 -> 0.24230673 | Z54: =(G54-H54)/G54 -> 0.10871965 | AA54: =H54/C54 -> 0.21596323 | AB54: =H54/M54 -> 0.14798016 | AC54: =(F54*(1-Z54))/(Q54-I54+M54) -> 0.39413658 | AD54: =H54/K54 -> 0.11648035 | AE54: =(I54+'Balance Sheet'!E54)/L54 -> 4.281305 | AF54: =J54/L54 -> 4.5817199 | AG54: =Q54-I54 -> -55727 | AH54: =Q54/M54 -> 0.034246183 | AI54: =Q54/SUM(Q54,M54) -> 0.033112216 | AJ54: =Q54/K54 -> 0.026956365 | AK54: =F54/N54 -> 168.26506 | AL54: =K54/M54 -> 1.2704303 | AM54: =T54/C54 -> 0.12299206 | AN54: ='Balance Sheet'!J54/Ratios!K54 -> 0.21490263 | AO54: ='Cash Flow'!E54/C54 -> 0.31189302 | AP54: =('Cash Flow'!E54+'Cash Flow'!F54)/Ratios!C54 -> 0.18890096 | AQ54: 6.51
A55: GOOG | B55: 41274 | C55: 50175 | D55: =C55-17176-3458 -> 29541 | E55: 16208 | F55: 12760 | G55: 13386 | H55: ='Income Statement'!R55 -> 10737 | I55: ='Balance Sheet'!D55 -> 48088 | J55: ='Balance Sheet'!I55 -> 60454 | K55: ='Balance Sheet'!R55 -> 93798 | L55: ='Balance Sheet'!X55 -> 14337 | M55: ='Balance Sheet'!AL55 -> 71715 | N55: 84 | O55: 3619 | P55: 0 | Q55: 2988 | R55: =SUM(O55:Q55) -> 6607 | S55: 1988 | T55: =-'Cash Flow'!F55 -> 3273 | U55: =(C55-C56)/C56 -> 0.323704 | V55: =D55/C55 -> 0.58875934 | W55: =E55/C55 -> 0.3230294 | X55: =F55/C55 -> 0.25430992 | Y55: =G55/C55 -> 0.26678625 | Z55: =(G55-H55)/G55 -> 0.19789332 | AA55: =H55/C55 -> 0.21399103 | AB55: =H55/M55 -> 0.14971763 | AC55: =(F55*(1-Z55))/(Q55-I55+M55) -> 0.38455312 | AD55: =H55/K55 -> 0.11446939 | AE55: =(I55+'Balance Sheet'!E55)/L55 -> 3.952919 | AF55: =J55/L55 -> 4.2166423 | AG55: =Q55-I55 -> -45100 | AH55: =Q55/M55 -> 0.041664924 | AI55: =Q55/SUM(Q55,M55) -> 0.039998394 | AJ55: =Q55/K55 -> 0.03185569 | AK55: =F55/N55 -> 151.90476 | AL55: =K55/M55 -> 1.3079272 | AM55: =T55/C55 -> 0.065231689 | AN55: ='Balance Sheet'!J55/Ratios!K55 -> 0.1886714 | AO55: ='Cash Flow'!E55/C55 -> 0.33122073 | AP55: =('Cash Flow'!E55+'Cash Flow'!F55)/Ratios!C55 -> 0.26598904 | AQ55: 5.43
A56: GOOG | B56: 40908 | C56: 37905 | D56: =C56-13188 -> 24717 | E56: 14079 | F56: 11742 | G56: ='Income Statement'!P56 -> 12326 | H56: ='Income Statement'!R56 -> 9737 | I56: ='Balance Sheet'!D56 -> 44626 | J56: ='Balance Sheet'!I56 -> 52758 | K56: ='Balance Sheet'!R56 -> 72574 | L56: ='Balance Sheet'!X56 -> 8913 | M56: ='Balance Sheet'!AL56 -> 58145 | N56: 58 | O56: 2879 | P56: 0 | Q56: 2986 | R56: =SUM(O56:Q56) -> 5865 | S56: 1396 | T56: =-'Cash Flow'!F56 -> 3438 | U56: =(C56-C57)/C57 -> 0.29275946 | V56: =D56/C56 -> 0.65207756 | W56: =E56/C56 -> 0.37142857 | X56: =F56/C56 -> 0.30977444 | Y56: =G56/C56 -> 0.32518137 | Z56: =(G56-H56)/G56 -> 0.21004381 | AA56: =H56/C56 -> 0.25687904 | AB56: =H56/M56 -> 0.16746066 | AC56: =(F56*(1-Z56))/(Q56-I56+M56) -> 0.56199125 | AD56: =H56/K56 -> 0.13416651 | AE56: =(I56+'Balance Sheet'!E56)/L56 -> 5.6993156 | AF56: =J56/L56 -> 5.9192191 | AG56: =Q56-I56 -> -41640 | AH56: =Q56/M56 -> 0.051354373 | AI56: =Q56/SUM(Q56,M56) -> 0.048845921 | AJ56: =Q56/K56 -> 0.041144211 | AK56: =F56/N56 -> 202.44828 | AL56: =K56/M56 -> 1.2481555 | AM56: =T56/C56 -> 0.090700435 | AN56: ='Balance Sheet'!J56/Ratios!K56 -> 0.19841817 | AO56: ='Cash Flow'!E56/C56 -> 0.3842501 | AP56: =('Cash Flow'!E56+'Cash Flow'!F56)/Ratios!C56 -> 0.29354966 | AQ56: 4.47
A57: GOOG | B57: 40543 | C57: ='Income Statement'!C57 -> 29321 | D57: ='Income Statement'!E57 -> 18904 | E57: 11762 | F57: ='Income Statement'!L57 -> 10381 | G57: ='Income Statement'!P57 -> 10796 | H57: ='Income Statement'!R57 -> 8505 | I57: ='Balance Sheet'!D57 -> 34975 | J57: ='Balance Sheet'!I57 -> 41562 | K57: ='Balance Sheet'!R57 -> 57851 | L57: ='Balance Sheet'!X57 -> 9996 | M57: ='Balance Sheet'!AL57 -> 46241 | N57: 0 | O57: 2305 | P57: 0 | Q57: 3465 | R57: =SUM(O57:Q57) -> 5770 | S57: 1067 | T57: =-'Cash Flow'!F57 -> 4018 | U57: =(C57-C58)/C58 -> 0.23975907 | V57: =D57/C57 -> 0.64472562 | W57: =E57/C57 -> 0.40114594 | X57: =F57/C57 -> 0.35404659 | Y57: =G57/C57 -> 0.36820027 | Z57: =(G57-H57)/G57 -> 0.21220823 | AA57: =H57/C57 -> 0.29006514 | AB57: =H57/M57 -> 0.18392768 | AC57: =(F57*(1-Z57))/(Q57-I57+M57) -> 0.5551603 | AD57: =H57/K57 -> 0.14701561 | AE57: =(I57+'Balance Sheet'!E57)/L57 -> 3.9992997 | AF57: =J57/L57 -> 4.1578631 | AG57: =Q57-I57 -> -31510 | AH57: =Q57/M57 -> 0.074933501 | AI57: =Q57/SUM(Q57,M57) -> 0.069709894 | AJ57: =Q57/K57 -> 0.059895248 | AL57: =K57/M57 -> 1.2510759 | AM57: =T57/C57 -> 0.13703489 | AN57: ='Balance Sheet'!J57/Ratios!K57 -> 0.20347099 | AO57: ='Cash Flow'!E57/C57 -> 0.37792026 | AP57: =('Cash Flow'!E57+'Cash Flow'!F57)/Ratios!C57 -> 0.24088537 | AQ57: 3.6
A58: GOOG | B58: 40178 | C58: ='Income Statement'!C58 -> 23650.563 | D58: ='Income Statement'!E58 -> 14806.448 | E58: 9818.2 | F58: ='Income Statement'!L58 -> 8312.186 | G58: ='Income Statement'!P58 -> 8381.189 | H58: ='Income Statement'!R58 -> 6520.448 | I58: ='Balance Sheet'!D58 -> 24484.775 | J58: ='Balance Sheet'!I58 -> 29166.958 | K58: ='Balance Sheet'!R58 -> 40496.778 | L58: ='Balance Sheet'!X58 -> 2747.467 | M58: ='Balance Sheet'!AL58 -> 36004.224 | N58: 0 | O58: 2461 | P58: 0 | Q58: 0 | R58: =SUM(O58:Q58) -> 2461 | S58: 1240 | T58: =-'Cash Flow'!F58 -> 809.888 | U58: =(C58-C59)/C59 -> 0.085109713 | V58: =D58/C58 -> 0.62605055 | W58: =E58/C58 -> 0.41513599 | X58: =F58/C58 -> 0.35145827 | Y58: =G58/C58 -> 0.35437588 | Z58: =(G58-H58)/G58 -> 0.22201396 | AA58: =H58/C58 -> 0.27569948 | AB58: =H58/M58 -> 0.18110231 | AC58: =(F58*(1-Z58))/(Q58-I58+M58) -> 0.56137795 | AD58: =H58/K58 -> 0.16101153 | AE58: =(I58+'Balance Sheet'!E58)/L58 -> 10.077096 | AF58: =J58/L58 -> 10.615945 | AG58: =Q58-I58 -> -24484.775 | AH58: =Q58/M58 -> 0 | AI58: =Q58/SUM(Q58,M58) -> 0 | AJ58: =Q58/K58 -> 0 | AL58: =K58/M58 -> 1.1247785 | AM58: =T58/C58 -> 0.034243921 | AN58: ='Balance Sheet'!J58/Ratios!K58 -> 0.20075918 | AO58: ='Cash Flow'!E58/C58 -> 0.3939102 | AP58: =('Cash Flow'!E58+'Cash Flow'!F58)/Ratios!C58 -> 0.35966628 | AQ58: 2.83
A59: GOOG | B59: 39813 | C59: ='Income Statement'!C59 -> 21795.55 | D59: ='Income Statement'!E59 -> 13174.044 | E59: 8123.9 | F59: ='Income Statement'!L59 -> 5537.212 | G59: ='Income Statement'!P59 -> 5853.596 | H59: ='Income Statement'!R59 -> 4226.858 | I59: ='Balance Sheet'!D59 -> 15845.771 | J59: ='Balance Sheet'!I59 -> 20178.182 | K59: ='Balance Sheet'!R59 -> 31767.575 | L59: ='Balance Sheet'!X59 -> 2302.09 | M59: ='Balance Sheet'!AL59 -> 28238.862 | N59: 0 | O59: 2857 | P59: 0 | Q59: 0 | R59: =SUM(O59:Q59) -> 2857 | S59: 1212 | T59: =-'Cash Flow'!F59 -> 2358.461 | U59: =(C59-C60)/C60 -> 0.31346079 | V59: =D59/C59 -> 0.60443733 | W59: =E59/C59 -> 0.37273205 | X59: =F59/C59 -> 0.25405241 | Y59: =G59/C59 -> 0.2685684 | Z59: =(G59-H59)/G59 -> 0.27790404 | AA59: =H59/C59 -> 0.19393216 | AB59: =H59/M59 -> 0.14968231 | AC59: =(F59*(1-Z59))/(Q59-I59+M59) -> 0.32263125 | AD59: =H59/K59 -> 0.13305573 | AE59: =(I59+'Balance Sheet'!E59)/L59 -> 8.0309471 | AF59: =J59/L59 -> 8.7651577 | AG59: =Q59-I59 -> -15845.771 | AH59: =Q59/M59 -> 0 | AI59: =Q59/SUM(Q59,M59) -> 0 | AJ59: =Q59/K59 -> 0 | AL59: =K59/M59 -> 1.1249595 | AM59: =T59/C59 -> 0.10820837 | AN59: ='Balance Sheet'!J59/Ratios!K59 -> 0.23849161 | AO59: ='Cash Flow'!E59/C59 -> 0.36029634 | AP59: =('Cash Flow'!E59+'Cash Flow'!F59)/Ratios!C59 -> 0.25208797 | AQ59: 2.24
A60: GOOG | B60: 39447 | C60: ='Income Statement'!C60 -> 16593.986 | D60: ='Income Statement'!E60 -> 9944.901 | E60: 6052.1 | F60: ='Income Statement'!L60 -> 5084.4 | G60: ='Income Statement'!P60 -> 5673.98 | H60: ='Income Statement'!R60 -> 4203.72 | I60: ='Balance Sheet'!D60 -> 14218.613 | J60: ='Balance Sheet'!I60 -> 17289.138 | K60: ='Balance Sheet'!R60 -> 25335.806 | L60: ='Balance Sheet'!X60 -> 2035.602 | M60: ='Balance Sheet'!AL60 -> 22689.679 | N60: 1203 | O60: 2203 | P60: 0 | Q60: 0 | R60: =SUM(O60:Q60) -> 2203 | S60: 808 | T60: =-'Cash Flow'!F60 -> 2402.84 | U60: =(C60-C61)/C61 -> 0.56474454 | V60: =D60/C60 -> 0.59930754 | W60: =E60/C60 -> 0.36471647 | X60: =F60/C60 -> 0.30640016 | Y60: =G60/C60 -> 0.3419299 | Z60: =(G60-H60)/G60 -> 0.25912323 | AA60: =H60/C60 -> 0.25332792 | AB60: =H60/M60 -> 0.18527014 | AC60: =(F60*(1-Z60))/(Q60-I60+M60) -> 0.44468003 | AD60: =H60/K60 -> 0.16592012 | AE60: =(I60+'Balance Sheet'!E60)/L60 -> 8.118673 | AF60: =J60/L60 -> 8.4933784 | AG60: =Q60-I60 -> -14218.613 | AH60: =Q60/M60 -> 0 | AI60: =Q60/SUM(Q60,M60) -> 0 | AJ60: =Q60/K60 -> 0 | AK60: =F60/N60 -> 4.2264339 | AL60: =K60/M60 -> 1.1166225 | AM60: =T60/C60 -> 0.14480186 | AN60: ='Balance Sheet'!J60/Ratios!K60 -> 0.21786952 | AO60: ='Cash Flow'!E60/C60 -> 0.34804236 | AP60: =('Cash Flow'!E60+'Cash Flow'!F60)/Ratios!C60 -> 0.2032405 | AQ60: 1.81
A61: GOOG | B61: 39082 | C61: ='Income Statement'!C61 -> 10604.917 | D61: ='Income Statement'!E61 -> 6379.89 | E61: 4121.9 | F61: ='Income Statement'!L61 -> 3549.996 | G61: ='Income Statement'!P61 -> 4011.04 | H61: ='Income Statement'!R61 -> 3077.446 | I61: ='Balance Sheet'!D61 -> 11243.914 | J61: ='Balance Sheet'!I61 -> 13039.847 | K61: ='Balance Sheet'!R61 -> 18473.351 | L61: ='Balance Sheet'!X61 -> 1304.587 | M61: ='Balance Sheet'!AL61 -> 17039.84 | N61: 257 | O61: 1168 | P61: 0 | Q61: 0 | R61: =SUM(O61:Q61) -> 1168 | S61: 494 | T61: =-'Cash Flow'!F61 -> 1902.798 | V61: =D61/C61 -> 0.60159735 | W61: =E61/C61 -> 0.3886782 | X61: =F61/C61 -> 0.33475 | Y61: =G61/C61 -> 0.37822455 | Z61: =(G61-H61)/G61 -> 0.23275609 | AA61: =H61/C61 -> 0.29019048 | AB61: =H61/M61 -> 0.18060299 | AC61: =(F61*(1-Z61))/(Q61-I61+M61) -> 0.46993574 | AD61: =H61/K61 -> 0.1665884 | AE61: =(I61+'Balance Sheet'!E61)/L61 -> 9.6323618 | AF61: =J61/L61 -> 9.9953832 | AG61: =Q61-I61 -> -11243.914 | AH61: =Q61/M61 -> 0 | AI61: =Q61/SUM(Q61,M61) -> 0 | AJ61: =Q61/K61 -> 0 | AK61: =F61/N61 -> 13.813214 | AL61: =K61/M61 -> 1.084127 | AM61: =T61/C61 -> 0.17942602 | AN61: ='Balance Sheet'!J61/Ratios!K61 -> 0.17807273 | AO61: ='Cash Flow'!E61/C61 -> 0.33762716 | AP61: =('Cash Flow'!E61+'Cash Flow'!F61)/Ratios!C61 -> 0.15820114 | AQ61: 1.38
A62: META | B62: 46022 | C62: ='Income Statement'!C62 -> 200966 | D62: ='Income Statement'!E62 -> 164791 | E62: 102129 | F62: ='Income Statement'!L62 -> 83276 | G62: ='Income Statement'!P62 -> 85932 | H62: ='Income Statement'!R62 -> 60458 | I62: ='Balance Sheet'!D62 -> 81592 | J62: ='Balance Sheet'!I62 -> 108722 | K62: ='Balance Sheet'!R62 -> 366021 | L62: ='Balance Sheet'!X62 -> 41836 | M62: ='Balance Sheet'!AL62 -> 217243 | N62: 1165 | O62: 25153 | P62: 1184 | Q62: 58744 | R62: =SUM(O62:Q62) -> 85081 | S62: 18616 | T62: =-'Cash Flow'!F62 -> 69691 | U62: =(C62-C63)/C63 -> 0.22167038 | V62: =D62/C62 -> 0.81999443 | W62: =E62/C62 -> 0.50819044 | X62: =F62/C62 -> 0.41437855 | Y62: =G62/C62 -> 0.42759472 | Z62: =(G62-H62)/G62 -> 0.2964437 | AA62: =H62/C62 -> 0.30083696 | AB62: =H62/M62 -> 0.27829665 | AC62: =(F62*(1-Z62))/(Q62-I62+M62) -> 0.30139332 | AD62: =H62/K62 -> 0.16517632 | AE62: =(I62+'Balance Sheet'!E62)/L62 -> 2.4228177 | AF62: =J62/L62 -> 2.5987666 | AG62: =Q62-I62 -> -22848 | AH62: =Q62/M62 -> 0.27040687 | AI62: =Q62/SUM(Q62,M62) -> 0.21285061 | AJ62: =Q62/K62 -> 0.16049352 | AK62: =F62/N62 -> 71.481545 | AL62: =K62/M62 -> 1.684846 | AM62: =T62/C62 -> 0.34678005 | AN62: ='Balance Sheet'!J62/Ratios!K62 -> 0.69430443 | AO62: ='Cash Flow'!E62/C62 -> 0.57621687 | AP62: =('Cash Flow'!E62+'Cash Flow'!F62)/Ratios!C62 -> 0.22943682 | AQ62: 85.87
A63: META | B63: 45657 | C63: ='Income Statement'!C63 -> 164501 | D63: ='Income Statement'!E63 -> 134371 | E63: 85270 | F63: ='Income Statement'!L63 -> 69380 | G63: ='Income Statement'!P63 -> 70663 | H63: ='Income Statement'!R63 -> 62360 | I63: ='Balance Sheet'!D63 -> 77815 | J63: ='Balance Sheet'!I63 -> 100045 | K63: ='Balance Sheet'!R63 -> 276054 | L63: ='Balance Sheet'!X63 -> 33596 | M63: ='Balance Sheet'!AL63 -> 182637 | N63: 715 | O63: 20234 | P63: 709 | Q63: 28826 | R63: =SUM(O63:Q63) -> 49769 | S63: 15498 | T63: =-'Cash Flow'!F63 -> 37256 | U63: =(C63-C64)/C64 -> 0.21941113 | V63: =D63/C63 -> 0.81684002 | W63: =E63/C63 -> 0.51835551 | X63: =F63/C63 -> 0.42176035 | Y63: =G63/C63 -> 0.4295597 | Z63: =(G63-H63)/G63 -> 0.11750138 | AA63: =H63/C63 -> 0.37908584 | AB63: =H63/M63 -> 0.34144231 | AC63: =(F63*(1-Z63))/(Q63-I63+M63) -> 0.45812698 | AD63: =H63/K63 -> 0.22589783 | AE63: =(I63+'Balance Sheet'!E63)/L63 -> 2.8220324 | AF63: =J63/L63 -> 2.9778843 | AG63: =Q63-I63 -> -48989 | AH63: =Q63/M63 -> 0.1578322 | AI63: =Q63/SUM(Q63,M63) -> 0.13631699 | AJ63: =Q63/K63 -> 0.1044216 | AK63: =F63/N63 -> 97.034965 | AL63: =K63/M63 -> 1.51149 | AM63: =T63/C63 -> 0.22647887 | AN63: ='Balance Sheet'!J63/Ratios!K63 -> 0.65054301 | AO63: ='Cash Flow'!E63/C63 -> 0.55518204 | AP63: =('Cash Flow'!E63+'Cash Flow'!F63)/Ratios!C63 -> 0.32870317 | AQ63: 72.07
A64: META | B64: 45291 | C64: ='Income Statement'!C64 -> 134902 | D64: ='Income Statement'!E64 -> 108896 | E64: 61384 | F64: ='Income Statement'!L64 -> 46751 | G64: ='Income Statement'!P64 -> 47428 | H64: ='Income Statement'!R64 -> 39098 | I64: ='Balance Sheet'!D64 -> 65403 | J64: ='Balance Sheet'!I64 -> 85365 | K64: ='Balance Sheet'!R64 -> 229623 | L64: ='Balance Sheet'!X64 -> 31960 | M64: ='Balance Sheet'!AL64 -> 153168 | N64: 446 | O64: 18849 | P64: 690 | Q64: 18385 | R64: =SUM(O64:Q64) -> 37924 | S64: 11178 | T64: =-'Cash Flow'!F64 -> 27266 | U64: =(C64-C65)/C65 -> 0.15687468 | V64: =D64/C64 -> 0.80722302 | W64: =E64/C64 -> 0.45502661 | X64: =F64/C64 -> 0.34655528 | Y64: =G64/C64 -> 0.35157374 | Z64: =(G64-H64)/G64 -> 0.17563465 | AA64: =H64/C64 -> 0.28982521 | AB64: =H64/M64 -> 0.2552622 | AC64: =(F64*(1-Z64))/(Q64-I64+M64) -> 0.36307023 | AD64: =H64/K64 -> 0.1702704 | AE64: =(I64+'Balance Sheet'!E64)/L64 -> 2.5523154 | AF64: =J64/L64 -> 2.670995 | AG64: =Q64-I64 -> -47018 | AH64: =Q64/M64 -> 0.1200316 | AI64: =Q64/SUM(Q64,M64) -> 0.10716805 | AJ64: =Q64/K64 -> 0.080066021 | AK64: =F64/N64 -> 104.82287 | AL64: =K64/M64 -> 1.4991578 | AM64: =T64/C64 -> 0.20211709 | AN64: ='Balance Sheet'!J64/Ratios!K64 -> 0.62282524 | AO64: ='Cash Flow'!E64/C64 -> 0.52714563 | AP64: =('Cash Flow'!E64+'Cash Flow'!F64)/Ratios!C64 -> 0.32502854 | AQ64: 59.81
A65: META | B65: 44926 | C65: ='Income Statement'!C65 -> 116609 | D65: =C65-25249 -> 91360 | E65: 42241 | F65: ='Income Statement'!L65 -> 28944 | G65: ='Income Statement'!P65 -> 28819 | H65: ='Income Statement'!R65 -> 23200 | I65: ='Balance Sheet'!D65 -> 40738 | J65: ='Balance Sheet'!I65 -> 59549 | K65: ='Balance Sheet'!R65 -> 185727 | L65: ='Balance Sheet'!X65 -> 27026 | M65: ='Balance Sheet'!AL65 -> 125713 | N65: 160 | O65: 16668 | P65: 687 | Q65: 9923 | R65: =SUM(O65:Q65) -> 27278 | S65: 8686 | T65: =-'Cash Flow'!F65 -> 31431 | U65: =(C65-C66)/C66 -> -0.011193176 | V65: =D65/C65 -> 0.78347297 | W65: =E65/C65 -> 0.36224477 | X65: =F65/C65 -> 0.24821412 | Y65: =G65/C65 -> 0.24714216 | Z65: =(G65-H65)/G65 -> 0.19497554 | AA65: =H65/C65 -> 0.19895548 | AB65: =H65/M65 -> 0.18454734 | AC65: =(F65*(1-Z65))/(Q65-I65+M65) -> 0.24553339 | AD65: =H65/K65 -> 0.12491453 | AE65: =(I65+'Balance Sheet'!E65)/L65 -> 2.0056242 | AF65: =J65/L65 -> 2.2033967 | AG65: =Q65-I65 -> -30815 | AH65: =Q65/M65 -> 0.078933762 | AI65: =Q65/SUM(Q65,M65) -> 0.073159043 | AJ65: =Q65/K65 -> 0.053427881 | AK65: =F65/N65 -> 180.9 | AL65: =K65/M65 -> 1.477389 | AM65: =T65/C65 -> 0.2695418 | AN65: ='Balance Sheet'!J65/Ratios!K65 -> 0.63085066 | AO65: ='Cash Flow'!E65/C65 -> 0.43285681 | AP65: =('Cash Flow'!E65+'Cash Flow'!F65)/Ratios!C65 -> 0.16331501 | AQ65: 48.09
A66: META | B66: 44561 | C66: ='Income Statement'!C66 -> 117929 | D66: =C66-22649 -> 95280 | E66: 54720 | F66: ='Income Statement'!L66 -> 46753 | G66: ='Income Statement'!P66 -> 47284 | H66: ='Income Statement'!R66 -> 39370 | I66: ='Balance Sheet'!D66 -> 47998 | J66: ='Balance Sheet'!I66 -> 66666 | K66: ='Balance Sheet'!R66 -> 165987 | L66: ='Balance Sheet'!X66 -> 21135 | M66: ='Balance Sheet'!AL66 -> 124879 | N66: 0 | O66: 13873 | P66: 581 | Q66: 0 | R66: =SUM(O66:Q66) -> 14454 | S66: 7967 | T66: =-'Cash Flow'!F66 -> 18567 | U66: =(C66-C67)/C67 -> 0.37182574 | V66: =D66/C66 -> 0.80794376 | W66: =E66/C66 -> 0.464008 | X66: =F66/C66 -> 0.39645041 | Y66: =G66/C66 -> 0.40095312 | Z66: =(G66-H66)/G66 -> 0.16737163 | AA66: =H66/C66 -> 0.33384494 | AB66: =H66/M66 -> 0.31526518 | AC66: =(F66*(1-Z66))/(Q66-I66+M66) -> 0.50633933 | AD66: =H66/K66 -> 0.23718725 | AE66: =(I66+'Balance Sheet'!E66)/L66 -> 2.9352732 | AF66: =J66/L66 -> 3.1542938 | AG66: =Q66-I66 -> -47998 | AH66: =Q66/M66 -> 0 | AI66: =Q66/SUM(Q66,M66) -> 0 | AJ66: =Q66/K66 -> 0 | AL66: =K66/M66 -> 1.3291826 | AM66: =T66/C66 -> 0.15744219 | AN66: ='Balance Sheet'!J66/Ratios!K66 -> 0.54247622 | AO66: ='Cash Flow'!E66/C66 -> 0.48913329 | AP66: =('Cash Flow'!E66+'Cash Flow'!F66)/Ratios!C66 -> 0.3316911 | AQ66: 45.56
A67: META | B67: 44196 | C67: ='Income Statement'!C67 -> 85965 | D67: =C67-16692 -> 69273 | E67: 39534 | F67: ='Income Statement'!L67 -> 32671 | G67: ='Income Statement'!P67 -> 33180 | H67: ='Income Statement'!R67 -> 29146 | I67: ='Balance Sheet'!D67 -> 61954 | J67: ='Balance Sheet'!I67 -> 75670 | K67: ='Balance Sheet'!R67 -> 159316 | L67: ='Balance Sheet'!X67 -> 14981 | M67: ='Balance Sheet'!AL67 -> 128290 | N67: 0 | O67: 10654 | P67: 523 | Q67: 0 | R67: =SUM(O67:Q67) -> 11177 | S67: 6862 | T67: =-'Cash Flow'!F67 -> 15115 | U67: =(C67-C68)/C68 -> 0.2159639 | V67: =D67/C67 -> 0.80582795 | W67: =E67/C67 -> 0.45988484 | X67: =F67/C67 -> 0.38005002 | Y67: =G67/C67 -> 0.38597103 | Z67: =(G67-H67)/G67 -> 0.12157926 | AA67: =H67/C67 -> 0.33904496 | AB67: =H67/M67 -> 0.2271884 | AC67: =(F67*(1-Z67))/(Q67-I67+M67) -> 0.4326291 | AD67: =H67/K67 -> 0.18294459 | AE67: =(I67+'Balance Sheet'!E67)/L67 -> 4.89213 | AF67: =J67/L67 -> 5.0510647 | AG67: =Q67-I67 -> -61954 | AH67: =Q67/M67 -> 0 | AI67: =Q67/SUM(Q67,M67) -> 0 | AJ67: =Q67/K67 -> 0 | AL67: =K67/M67 -> 1.2418427 | AM67: =T67/C67 -> 0.17582737 | AN67: ='Balance Sheet'!J67/Ratios!K67 -> 0.4418828 | AO67: ='Cash Flow'!E67/C67 -> 0.45072995 | AP67: =('Cash Flow'!E67+'Cash Flow'!F67)/Ratios!C67 -> 0.27490258 | AQ67: 45.03
A68: META | B68: 43830 | C68: ='Income Statement'!C68 -> 70697 | D68: ='Income Statement'!E68 -> 57927 | E68: 34728 | F68: ='Income Statement'!L68 -> 23986 | G68: ='Income Statement'!P68 -> 24812 | H68: ='Income Statement'!R68 -> 18485 | I68: ='Balance Sheet'!D68 -> 54855 | J68: ='Balance Sheet'!I68 -> 66225 | K68: ='Balance Sheet'!R68 -> 133376 | L68: ='Balance Sheet'!X68 -> 15053 | M68: ='Balance Sheet'!AL68 -> 101054 | N68: 20 | O68: 10324 | P68: 473 | Q68: 0 | R68: =SUM(O68:Q68) -> 10797 | S68: 5741 | T68: =-'Cash Flow'!F68 -> 15102 | U68: =(C68-C69)/C69 -> 0.2661091 | V68: =D68/C68 -> 0.81936999 | W68: =E68/C68 -> 0.49122311 | X68: =F68/C68 -> 0.33927889 | Y68: =G68/C68 -> 0.35096256 | Z68: =(G68-H68)/G68 -> 0.25499758 | AA68: =H68/C68 -> 0.26146795 | AB68: =H68/M68 -> 0.182922 | AC68: =(F68*(1-Z68))/(Q68-I68+M68) -> 0.38679686 | AD68: =H68/K68 -> 0.13859315 | AE68: =(I68+'Balance Sheet'!E68)/L68 -> 4.2764233 | AF68: =J68/L68 -> 4.3994553 | AG68: =Q68-I68 -> -54855 | AH68: =Q68/M68 -> 0 | AI68: =Q68/SUM(Q68,M68) -> 0 | AJ68: =Q68/K68 -> 0 | AL68: =K68/M68 -> 1.3198488 | AM68: =T68/C68 -> 0.21361585 | AN68: ='Balance Sheet'!J68/Ratios!K68 -> 0.41571197 | AO68: ='Cash Flow'!E68/C68 -> 0.51365687 | AP68: =('Cash Flow'!E68+'Cash Flow'!F68)/Ratios!C68 -> 0.30004102 | AQ68: 35.43
A69: META | B69: 43465 | C69: ='Income Statement'!C69 -> 55838 | D69: ='Income Statement'!E69 -> 46483 | E69: 29233 | F69: ='Income Statement'!L69 -> 24913 | G69: ='Income Statement'!P69 -> 25361 | H69: ='Income Statement'!R69 -> 22112 | I69: ='Balance Sheet'!D69 -> 41114 | J69: ='Balance Sheet'!I69 -> 50480 | K69: ='Balance Sheet'!R69 -> 97334 | L69: ='Balance Sheet'!X69 -> 7017 | M69: ='Balance Sheet'!AL69 -> 84127 | N69: 9 | O69: 14651 | P69: 0 | Q69: 0 | R69: =SUM(O69:Q69) -> 14651 | S69: 4315 | T69: =-'Cash Flow'!F69 -> 13915 | U69: =(C69-C70)/C70 -> 0.37352717 | V69: =D69/C69 -> 0.83246176 | W69: =E69/C69 -> 0.52353236 | X69: =F69/C69 -> 0.44616569 | Y69: =G69/C69 -> 0.4541889 | Z69: =(G69-H69)/G69 -> 0.12811009 | AA69: =H69/C69 -> 0.39600272 | AB69: =H69/M69 -> 0.26284071 | AC69: =(F69*(1-Z69))/(Q69-I69+M69) -> 0.50499601 | AD69: =H69/K69 -> 0.22717653 | AE69: =(I69+'Balance Sheet'!E69)/L69 -> 6.9404304 | AF69: =J69/L69 -> 7.1939575 | AG69: =Q69-I69 -> -41114 | AH69: =Q69/M69 -> 0 | AI69: =Q69/SUM(Q69,M69) -> 0 | AJ69: =Q69/K69 -> 0 | AL69: =K69/M69 -> 1.1569888 | AM69: =T69/C69 -> 0.24920305 | AN69: ='Balance Sheet'!J69/Ratios!K69 -> 0.32437792 | AO69: ='Cash Flow'!E69/C69 -> 0.52426663 | AP69: =('Cash Flow'!E69+'Cash Flow'!F69)/Ratios!C69 -> 0.27506358 | AQ69: 29.48
A70: META | B70: 43100 | C70: ='Income Statement'!C70 -> 40653 | D70: ='Income Statement'!E70 -> 35199 | E70: 23228 | F70: ='Income Statement'!L70 -> 20203 | G70: ='Income Statement'!P70 -> 20594 | H70: ='Income Statement'!R70 -> 15934 | I70: ='Balance Sheet'!D70 -> 41711 | J70: ='Balance Sheet'!I70 -> 48563 | K70: ='Balance Sheet'!R70 -> 84524 | L70: ='Balance Sheet'!X70 -> 3760 | M70: ='Balance Sheet'!AL70 -> 74347 | N70: 6 | O70: 4644 | P70: 195 | Q70: 0 | R70: =SUM(O70:Q70) -> 4839 | S70: 3025 | T70: =-'Cash Flow'!F70 -> 6733 | U70: =(C70-C71)/C71 -> 0.47090962 | V70: =D70/C70 -> 0.86584016 | W70: =E70/C70 -> 0.57137235 | X70: =F70/C70 -> 0.49696209 | Y70: =G70/C70 -> 0.50658008 | Z70: =(G70-H70)/G70 -> 0.2262795 | AA70: =H70/C70 -> 0.39195139 | AB70: =H70/M70 -> 0.21431934 | AC70: =(F70*(1-Z70))/(Q70-I70+M70) -> 0.47896419 | AD70: =H70/K70 -> 0.1885145 | AE70: =(I70+'Balance Sheet'!E70)/L70 -> 12.644415 | AF70: =J70/L70 -> 12.915691 | AG70: =Q70-I70 -> -41711 | AH70: =Q70/M70 -> 0 | AI70: =Q70/SUM(Q70,M70) -> 0 | AJ70: =Q70/K70 -> 0 | AL70: =K70/M70 -> 1.1368851 | AM70: =T70/C70 -> 0.16562123 | AN70: ='Balance Sheet'!J70/Ratios!K70 -> 0.2169443 | AO70: ='Cash Flow'!E70/C70 -> 0.5956756 | AP70: =('Cash Flow'!E70+'Cash Flow'!F70)/Ratios!C70 -> 0.43005436 | AQ70: 25.58
A71: META | B71: 42735 | C71: ='Income Statement'!C71 -> 27638 | D71: ='Income Statement'!E71 -> 23849 | E71: 14769 | F71: ='Income Statement'!L71 -> 12427 | G71: ='Income Statement'!P71 -> 12518 | H71: ='Income Statement'!R71 -> 10217 | I71: ='Balance Sheet'!D71 -> 29449 | J71: ='Balance Sheet'!I71 -> 34401 | K71: ='Balance Sheet'!R71 -> 64961 | L71: ='Balance Sheet'!X71 -> 2875 | M71: ='Balance Sheet'!AL71 -> 59194 | N71: 10 | O71: 1964 | P71: 0 | Q71: 0 | R71: =SUM(O71:Q71) -> 1964 | S71: 2342 | T71: =-'Cash Flow'!F71 -> 4491 | U71: =(C71-C72)/C72 -> 0.54161089 | V71: =D71/C71 -> 0.86290614 | W71: =E71/C71 -> 0.53437296 | X71: =F71/C71 -> 0.44963456 | Y71: =G71/C71 -> 0.45292713 | Z71: =(G71-H71)/G71 -> 0.18381531 | AA71: =H71/C71 -> 0.36967219 | AB71: =H71/M71 -> 0.17260195 | AC71: =(F71*(1-Z71))/(Q71-I71+M71) -> 0.34098932 | AD71: =H71/K71 -> 0.15727898 | AE71: =(I71+'Balance Sheet'!E71)/L71 -> 11.632 | AF71: =J71/L71 -> 11.965565 | AG71: =Q71-I71 -> -29449 | AH71: =Q71/M71 -> 0 | AI71: =Q71/SUM(Q71,M71) -> 0 | AJ71: =Q71/K71 -> 0 | AL71: =K71/M71 -> 1.0974254 | AM71: =T71/C71 -> 0.16249367 | AN71: ='Balance Sheet'!J71/Ratios!K71 -> 0.18169363 | AO71: ='Cash Flow'!E71/C71 -> 0.58282075 | AP71: =('Cash Flow'!E71+'Cash Flow'!F71)/Ratios!C71 -> 0.42032709 | AQ71: 20.47
A72: META | B72: 42369 | C72: ='Income Statement'!C72 -> 17928 | D72: ='Income Statement'!E72 -> 15061 | E72: 8175 | F72: ='Income Statement'!L72 -> 6225 | G72: ='Income Statement'!P72 -> 6194 | H72: ='Income Statement'!R72 -> 3688 | I72: ='Balance Sheet'!D72 -> 18434 | J72: ='Balance Sheet'!I72 -> 21652 | K72: ='Balance Sheet'!R72 -> 49407 | L72: ='Balance Sheet'!X72 -> 1925 | M72: ='Balance Sheet'!AL72 -> 44218 | N72: 23 | O72: 1452 | P72: 114 | Q72: 201 | R72: =SUM(O72:Q72) -> 1767 | S72: 1945 | T72: =-'Cash Flow'!F72 -> 2523 | U72: =(C72-C73)/C73 -> 0.43815177 | V72: =D72/C72 -> 0.84008255 | W72: =E72/C72 -> 0.45599063 | X72: =F72/C72 -> 0.34722222 | Y72: =G72/C72 -> 0.34549308 | Z72: =(G72-H72)/G72 -> 0.40458508 | AA72: =H72/C72 -> 0.20571174 | AB72: =H72/M72 -> 0.083404948 | AC72: =(F72*(1-Z72))/(Q72-I72+M72) -> 0.14263836 | AD72: =H72/K72 -> 0.074645293 | AE72: =(I72+'Balance Sheet'!E72)/L72 -> 10.905455 | AF72: =J72/L72 -> 11.247792 | AG72: =Q72-I72 -> -18233 | AH72: =Q72/M72 -> 0.0045456601 | AI72: =Q72/SUM(Q72,M72) -> 0.0045250906 | AJ72: =Q72/K72 -> 0.0040682494 | AK72: =F72/N72 -> 270.65217 | AL72: =K72/M72 -> 1.1173504 | AM72: =T72/C72 -> 0.14072959 | AN72: ='Balance Sheet'!J72/Ratios!K72 -> 0.15825693 | AO72: ='Cash Flow'!E72/C72 -> 0.47964079 | AP72: =('Cash Flow'!E72+'Cash Flow'!F72)/Ratios!C72 -> 0.3389112 | AQ72: 15.54
A73: META | B73: 42004 | C73: ='Income Statement'!C73 -> 12466 | D73: ='Income Statement'!E73 -> 10313 | E73: 6237 | F73: ='Income Statement'!L73 -> 4994 | G73: ='Income Statement'!P73 -> 4910 | H73: ='Income Statement'!R73 -> 2940 | I73: ='Balance Sheet'!D73 -> 11199 | J73: ='Balance Sheet'!I73 -> 13390 | K73: ='Balance Sheet'!R73 -> 39966 | L73: ='Balance Sheet'!X73 -> 1424 | M73: ='Balance Sheet'!AL73 -> 36096 | N73: 23 | O73: 1101 | P73: 233 | Q73: 0 | R73: =SUM(O73:Q73) -> 1334 | S73: 1243 | T73: =-'Cash Flow'!F73 -> 1831 | U73: =(C73-C74)/C74 -> 0.5835874 | V73: =D73/C73 -> 0.82729023 | W73: =E73/C73 -> 0.50032087 | X73: =F73/C73 -> 0.40060966 | Y73: =G73/C73 -> 0.39387133 | Z73: =(G73-H73)/G73 -> 0.401222 | AA73: =H73/C73 -> 0.23584149 | AB73: =H73/M73 -> 0.081449468 | AC73: =(F73*(1-Z73))/(Q73-I73+M73) -> 0.12010673 | AD73: =H73/K73 -> 0.073562528 | AE73: =(I73+'Balance Sheet'!E73)/L73 -> 9.0428371 | AF73: =J73/L73 -> 9.4030899 | AG73: =Q73-I73 -> -11199 | AH73: =Q73/M73 -> 0 | AI73: =Q73/SUM(Q73,M73) -> 0 | AJ73: =Q73/K73 -> 0 | AK73: =F73/N73 -> 217.13043 | AL73: =K73/M73 -> 1.1072141 | AM73: =T73/C73 -> 0.14687951 | AN73: ='Balance Sheet'!J73/Ratios!K73 -> 0.14472301 | AO73: ='Cash Flow'!E73/C73 -> 0.43775068 | AP73: =('Cash Flow'!E73+'Cash Flow'!F73)/Ratios!C73 -> 0.29087117 | AQ73: 12.91
A74: META | B74: 41639 | C74: ='Income Statement'!C74 -> 7872 | D74: ='Income Statement'!E74 -> 5997 | E74: 3815 | F74: ='Income Statement'!L74 -> 2804 | G74: ='Income Statement'!P74 -> 2754 | H74: ='Income Statement'!R74 -> 1500 | I74: ='Balance Sheet'!D74 -> 11449 | J74: ='Balance Sheet'!I74 -> 13070 | K74: ='Balance Sheet'!R74 -> 17895 | L74: ='Balance Sheet'!X74 -> 1100 | M74: ='Balance Sheet'!AL74 -> 15470 | N74: 56 | O74: 978 | P74: 476 | Q74: 0 | R74: =SUM(O74:Q74) -> 1454 | S74: 1011 | T74: =-'Cash Flow'!F74 -> 1362 | U74: =(C74-C75)/C75 -> 0.54686579 | V74: =D74/C74 -> 0.76181402 | W74: =E74/C74 -> 0.48462907 | X74: =F74/C74 -> 0.35619919 | Y74: =G74/C74 -> 0.34984756 | Z74: =(G74-H74)/G74 -> 0.45533769 | AA74: =H74/C74 -> 0.19054878 | AB74: =H74/M74 -> 0.096961862 | AC74: =(F74*(1-Z74))/(Q74-I74+M74) -> 0.37981425 | AD74: =H74/K74 -> 0.083822297 | AE74: =(I74+'Balance Sheet'!E74)/L74 -> 11.462727 | AF74: =J74/L74 -> 11.881818 | AG74: =Q74-I74 -> -11449 | AH74: =Q74/M74 -> 0 | AI74: =Q74/SUM(Q74,M74) -> 0 | AJ74: =Q74/K74 -> 0 | AK74: =F74/N74 -> 50.071429 | AL74: =K74/M74 -> 1.156755 | AM74: =T74/C74 -> 0.17301829 | AN74: ='Balance Sheet'!J74/Ratios!K74 -> 0.2314613 | AO74: ='Cash Flow'!E74/C74 -> 0.5363313 | AP74: =('Cash Flow'!E74+'Cash Flow'!F74)/Ratios!C74 -> 0.36331301 | AQ74: 6.07
A75: META | B75: 41274 | C75: ='Income Statement'!C75 -> 5089 | D75: ='Income Statement'!E75 -> 3725 | E75: 1187 | F75: ='Income Statement'!L75 -> 538 | G75: ='Income Statement'!P75 -> 494 | H75: ='Income Statement'!R75 -> 53 | I75: ='Balance Sheet'!D75 -> 9626 | J75: ='Balance Sheet'!I75 -> 11267 | K75: ='Balance Sheet'!R75 -> 15103 | L75: ='Balance Sheet'!X75 -> 1052 | M75: ='Balance Sheet'!AL75 -> 11755 | N75: 51 | O75: 851 | P75: 856 | Q75: 1500 | R75: =SUM(O75:Q75) -> 3207 | S75: 649 | T75: =-'Cash Flow'!F75 -> 1235 | U75: =(C75-C76)/C76 -> 0.37132848 | V75: =D75/C75 -> 0.73197092 | W75: =E75/C75 -> 0.23324818 | X75: =F75/C75 -> 0.10571822 | Y75: =G75/C75 -> 0.097072116 | Z75: =(G75-H75)/G75 -> 0.89271255 | AA75: =H75/C75 -> 0.01041462 | AB75: =H75/M75 -> 0.0045087197 | AC75: =(F75*(1-Z75))/(Q75-I75+M75) -> 0.015905387 | AD75: =H75/K75 -> 0.0035092366 | AE75: =(I75+'Balance Sheet'!E75)/L75 -> 10.262357 | AF75: =J75/L75 -> 10.710076 | AG75: =Q75-I75 -> -8126 | AH75: =Q75/M75 -> 0.12760527 | AI75: =Q75/SUM(Q75,M75) -> 0.11316484 | AJ75: =Q75/K75 -> 0.099318016 | AK75: =F75/N75 -> 10.54902 | AL75: =K75/M75 -> 1.284815 | AM75: =T75/C75 -> 0.24268029 | AN75: ='Balance Sheet'!J75/Ratios!K75 -> 0.21671191 | AO75: ='Cash Flow'!E75/C75 -> 0.31676164 | AP75: =('Cash Flow'!E75+'Cash Flow'!F75)/Ratios!C75 -> 0.074081352 | AQ75: 4.95
A76: META | B76: 40908 | C76: ='Income Statement'!C76 -> 3711 | D76: ='Income Statement'!E76 -> 2851 | E76: 2079 | F76: ='Income Statement'!L76 -> 1756 | G76: ='Income Statement'!P76 -> 1695 | H76: ='Income Statement'!R76 -> 1000 | I76: ='Balance Sheet'!D76 -> 3908 | J76: ='Balance Sheet'!I76 -> 4604 | K76: ='Balance Sheet'!R76 -> 6331 | L76: ='Balance Sheet'!X76 -> 899 | M76: ='Balance Sheet'!AL76 -> 4899 | N76: 42 | O76: 945 | P76: 677 | Q76: 0 | R76: =SUM(O76:Q76) -> 1622 | S76: 323 | T76: =-'Cash Flow'!F76 -> 606 | U76: =(C76-C77)/C77 -> 0.87993921 | V76: =D76/C76 -> 0.76825653 | W76: =E76/C76 -> 0.56022635 | X76: =F76/C76 -> 0.47318782 | Y76: =G76/C76 -> 0.4567502 | Z76: =(G76-H76)/G76 -> 0.4100295 | AA76: =H76/C76 -> 0.26946915 | AB76: =H76/M76 -> 0.20412329 | AC76: =(F76*(1-Z76))/(Q76-I76+M76) -> 1.0453968 | AD76: =H76/K76 -> 0.15795293 | AE76: =(I76+'Balance Sheet'!E76)/L76 -> 4.9555061 | AF76: =J76/L76 -> 5.1212458 | AG76: =Q76-I76 -> -3908 | AH76: =Q76/M76 -> 0 | AI76: =Q76/SUM(Q76,M76) -> 0 | AJ76: =Q76/K76 -> 0 | AK76: =F76/N76 -> 41.809524 | AL76: =K76/M76 -> 1.2923046 | AM76: =T76/C76 -> 0.1632983 | AN76: ='Balance Sheet'!J76/Ratios!K76 -> 0.30405939 | AO76: ='Cash Flow'!E76/C76 -> 0.41740771 | AP76: =('Cash Flow'!E76+'Cash Flow'!F76)/Ratios!C76 -> 0.2541094 | AQ76: 2.29
A77: META | B77: 40543 | C77: ='Income Statement'!C77 -> 1974 | D77: ='Income Statement'!E77 -> 1481 | E77: 1171 | F77: ='Income Statement'!L77 -> 1032 | G77: ='Income Statement'!P77 -> 1008 | H77: ='Income Statement'!R77 -> 606 | I77: ='Balance Sheet'!D77 -> 1785 | J77: ='Balance Sheet'!I77 -> 2246 | K77: ='Balance Sheet'!R77 -> 2990 | L77: ='Balance Sheet'!X77 -> 389 | M77: ='Balance Sheet'!AL77 -> 2162 | N77: 22 | O77: 0 | P77: 0 | Q77: 0 | R77: =SUM(O77:Q77) -> 0 | S77: 139 | T77: =-'Cash Flow'!F77 -> 293 | U77: =(C77-C78)/C78 -> 1.5405405 | V77: =D77/C77 -> 0.75025329 | W77: =E77/C77 -> 0.59321175 | X77: =F77/C77 -> 0.52279635 | Y77: =G77/C77 -> 0.5106383 | Z77: =(G77-H77)/G77 -> 0.39880952 | AA77: =H77/C77 -> 0.30699088 | AB77: =H77/M77 -> 0.28029602 | AC77: =(F77*(1-Z77))/(Q77-I77+M77) -> 1.6456991 | AD77: =H77/K77 -> 0.20267559 | AE77: =(I77+'Balance Sheet'!E77)/L77 -> 5.5475578 | AF77: =J77/L77 -> 5.7737789 | AG77: =Q77-I77 -> -1785 | AH77: =Q77/M77 -> 0 | AI77: =Q77/SUM(Q77,M77) -> 0 | AJ77: =Q77/K77 -> 0 | AK77: =F77/N77 -> 46.909091 | AL77: =K77/M77 -> 1.3829787 | AM77: =T77/C77 -> 0.14842958 | AN77: ='Balance Sheet'!J77/Ratios!K77 -> 0.27424749 | AO77: ='Cash Flow'!E77/C77 -> 0.35359676 | AP77: =('Cash Flow'!E77+'Cash Flow'!F77)/Ratios!C77 -> 0.20516717 | AQ77: 1.01
A78: META | B78: 40178 | C78: ='Income Statement'!C78 -> 777 | D78: ='Income Statement'!E78 -> 554 | E78: 340 | F78: ='Income Statement'!L78 -> 262 | G78: ='Income Statement'!P78 -> 254 | H78: 122 | I78: ='Balance Sheet'!D78 -> 633 | J78: 633 | K78: ='Balance Sheet'!R78 -> 1109 | L78: 0 | M78: ='Balance Sheet'!AL78 -> 868 | N78: 10 | O78: 0 | P78: 0 | Q78: 0 | R78: =SUM(O78:Q78) -> 0 | S78: 78 | T78: =-'Cash Flow'!F78 -> 33 | U78: =(C78-C79)/C79 -> 1.8566176 | V78: =D78/C78 -> 0.71299871 | W78: =E78/C78 -> 0.43758044 | X78: =F78/C78 -> 0.33719434 | Y78: =G78/C78 -> 0.32689833 | Z78: =(G78-H78)/G78 -> 0.51968504 | AA78: =H78/C78 -> 0.15701416 | AB78: =H78/M78 -> 0.140553 | AC78: =(F78*(1-Z78))/(Q78-I78+M78) -> 0.53550008 | AD78: =H78/K78 -> 0.11000902 | AG78: =Q78-I78 -> -633 | AH78: =Q78/M78 -> 0 | AI78: =Q78/SUM(Q78,M78) -> 0 | AJ78: =Q78/K78 -> 0 | AK78: =F78/N78 -> 26.2 | AL78: =K78/M78 -> 1.2776498 | AM78: =T78/C78 -> 0.042471042 | AN78: ='Balance Sheet'!J78/Ratios!K78 -> 0 | AO78: ='Cash Flow'!E78/C78 -> 0.1994852 | AP78: =('Cash Flow'!E78+'Cash Flow'!F78)/Ratios!C78 -> 0.15701416 | AQ78: 0.41
A79: META | B79: 39813 | C79: ='Income Statement'!C79 -> 272 | D79: ='Income Statement'!E79 -> 148 | F79: ='Income Statement'!L79 -> -55 | G79: ='Income Statement'!R79 -> -56 | H79: -56 | I79: 297 | J79: 297 | K79: 505 | L79: 0 | M79: 335 | N79: 1 | O79: 0 | P79: 0 | Q79: 0 | R79: =SUM(O79:Q79) -> 0 | S79: 0 | T79: 0 | U79: -0.202 | V79: =D79/C79 -> 0.54411765 | W79: =E79/C79 -> 0 | X79: =F79/C79 -> -0.20220588 | Y79: =G79/C79 -> -0.20588235 | Z79: =(G79-H79)/G79 -> 0 | AA79: =H79/C79 -> -0.20588235 | AB79: =H79/M79 -> -0.16716418 | AC79: =(F79*(1-Z79))/(Q79-I79+M79) -> -1.4473684 | AD79: =H79/K79 -> -0.11089109 | AG79: =Q79-I79 -> -297 | AH79: =Q79/M79 -> 0 | AI79: =Q79/SUM(Q79,M79) -> 0 | AJ79: =Q79/K79 -> 0 | AK79: =F79/N79 -> -55 | AL79: =K79/M79 -> 1.5074627 | AO79: =('Cash Flow'!E79+'Cash Flow'!F79)/Ratios!C79 -> -0.22794118
A80: META | B80: 39447 | C80: ='Income Statement'!C80 -> 153 | D80: ='Income Statement'!E80 -> 112 | F80: ='Income Statement'!L80 -> -124 | G80: -138 | H80: -138 | I80: 305 | J80: 305 | K80: 448 | L80: 0 | M80: 273 | N80: 11 | O80: 0 | P80: 0 | Q80: 0 | R80: =SUM(O80:Q80) -> 0 | S80: 0 | T80: 0 | U80: -0.811 | V80: =D80/C80 -> 0.73202614 | W80: =E80/C80 -> 0 | X80: =F80/C80 -> -0.81045752 | Y80: =G80/C80 -> -0.90196078 | Z80: =(G80-H80)/G80 -> 0 | AA80: =H80/C80 -> -0.90196078 | AB80: =H80/M80 -> -0.50549451 | AC80: =(F80*(1-Z80))/(Q80-I80+M80) -> 3.875 | AD80: =H80/K80 -> -0.30803571 | AG80: =Q80-I80 -> -305 | AH80: =Q80/M80 -> 0 | AI80: =Q80/SUM(Q80,M80) -> 0 | AJ80: =Q80/K80 -> 0 | AK80: =F80/N80 -> -11.272727 | AL80: =K80/M80 -> 1.6410256 | AO80: =('Cash Flow'!E80+'Cash Flow'!F80)/Ratios!C80 -> -0.2875817

Sheet Comps
A1: COMPS | B1: EV | C1: EV/EBITDA | D1: WACC
A2: AMZN | B2: =I21+Ratios!AG2 -> 2878822 | C2: =B2/Ratios!E2 -> 19.754356 | D2: 0.095015269
A3: MSFT | B3: =I22+Ratios!AG22 -> 3031586 | C3: =B3/Ratios!E22 -> 19.367691 | D3: 0.083939729
A4: GOOG | B4: =I23+Ratios!AG42 -> 4756700 | C4: =B4/Ratios!E42 -> 30.418545 | D4: 0.091120236
A5: META | B5: =I24+Ratios!AG62 -> 1524152 | C5: =B5/Ratios!E62 -> 14.923792 | D5: 0.092886238
B20: COMPS | C20: Cost of Debt | D20: Cost of Equity | E20: Tax Rate | F20: Beta | G20: Rf | H20: MRP | I20: Equity | J20: Debt | K20: Debt % | L20: Equity % | M20: WACC
B21: AMZN | C21: 0.044 | D21: =G21+F21*H21 -> 0.1005 | E21: =AVERAGE(Ratios!$Z2:$Z7) -> 0.21881783 | F21: 1.26 | G21: 0.0375 | H21: 0.05 | I21: 2933000 | J21: =Ratios!Q2*(0.041/C21) -> 64156.614 | K21: =J21/SUM(I21:J21) -> 0.021405826 | L21: =I21/SUM(I21:J21) -> 0.97859417 | M21: =((C21*1-E21)*K21)+(D21*L21) -> 0.094606594
B22: MSFT | C22: 0.0416 | D22: =G22+F22*H22 -> 0.0895 | E22: =AVERAGE(Ratios!$Z22:$Z27) -> 0.16381208 | F22: 1.04 | G22: 0.0375 | H22: 0.05 | I22: 3083000 | J22: =Ratios!Q22 -> 43151 | K22: =J22/SUM(I22:J22) -> 0.013803236 | L22: =I22/SUM(I22:J22) -> 0.98619676 | M22: =((C22*1-E22)*K22)+(D22*L22) -> 0.086577688
B23: GOOG | C23: 0.0425 | D23: =G23+F23*H23 -> 0.093 | E23: =AVERAGE(Ratios!$Z42:$Z47) -> 0.15917277 | F23: 1.11 | G23: 0.0375 | H23: 0.05 | I23: 4835000 | J23: =Ratios!Q42*(0.0405/C23) -> 46258.624 | K23: =J23/SUM(I23:J23) -> 0.0094767819 | L23: =I23/SUM(I23:J23) -> 0.99052322 | M23: =((C23*1-E23)*K23)+(D23*L23) -> 0.091012977
B24: META | C24: 0.0443 | D24: =G24+F24*H24 -> 0.1005 | E24: =AVERAGE(Ratios!$Z62:$Z67) -> 0.17891769 | F24: 1.26 | G24: 0.0375 | H24: 0.05 | I24: 1547000 | J24: =Ratios!Q62*((0.048+0.042)/2)/C24 -> 59672.235 | K24: =J24/SUM(I24:J24) -> 0.037140266 | L24: =I24/SUM(I24:J24) -> 0.96285973 | M24: =((C24*1-E24)*K24)+(D24*L24) -> 0.091767666

Sheet MSFT Valuation
B3: INCOME STATEMENTS % of Sales | N3: INCOME STATEMENTS
B4: shares in Millions, $ in Millions | I4: Jun. 30, 2023 | J4: Jun. 30, 2024 | K4: Jun. 30, 2025 | L4: 3 Year Avg | N4: shares in Millions, $ in Millions | T4: Jun. 30, 2023 | U4: Jun. 30, 2024 | V4: Jun. 30, 2025 | W4: Jun. 30, 2026 | X4: Jun. 30, 2027 | Y4: Jun. 30, 2028 | Z4: Jun. 30, 2029 | AA4: Jun. 30, 2030
B5: Revenue | I5: =T5/$T$5 -> 1 | J5: =U5/$U$5 -> 1 | K5: =V5/$V$5 -> 1 | L5: =(V5/T5)^(1/3)-1 -> 0.099564515 | N5: Revenue | T5: 211915 | U5: 245122 | V5: 281724 | W5: =V5*(1+($L$5)) -> 309773.71 | X5: =W5*(1+($L$5*(1-0.15745136)^1)) -> 335759.99 | Y5: =X5*(1+($L$5*(1-0.15745136)^2)) -> 359491.4 | Z5: =Y5*(1+($L$5*(1-0.15745136)^3)) -> 380899.5 | AA5: =Z5*(1+($L$5*(1-0.15745136)^4)) -> 400011
B6: Cost of revenue | I6: =T6/$T$5 -> 0.31079914 | J6: =U6/$U$5 -> 0.30235556 | K6: =V6/$V$5 -> 0.31176258 | L6: =AVERAGE(I6:K6) -> 0.30830576 | N6: Cost of revenue | T6: 65863 | U6: 74114 | V6: 87831 | W6: =W$5*$L6 -> 95505.02 | X6: =X$5*$L6 -> 103516.74 | Y6: =Y$5*$L6 -> 110833.27 | Z6: =Z$5*$L6 -> 117433.51 | AA6: =AA$5*$L6 -> 123325.7
B7: Gross margin | I7: =T7/$T$5 -> 0.68920086 | J7: =U7/$U$5 -> 0.69764444 | K7: =V7/$V$5 -> 0.68823742 | L7: =AVERAGE(I7:K7) -> 0.69169424 | N7: Gross margin | T7: =T5-T6 -> 146052 | U7: =U5-U6 -> 171008 | V7: =V5-V6 -> 193893 | W7: =W5-W6 -> 214268.69 | X7: =X5-X6 -> 232243.25 | Y7: =Y5-Y6 -> 248658.13 | Z7: =Z5-Z6 -> 263465.99 | AA7: =AA5-AA6 -> 276685.31
B8: Research and development | I8: =T8/$T$5 -> 0.12832975 | J8: =U8/$U$5 -> 0.12038903 | K8: =V8/$V$5 -> 0.11531854 | L8: =AVERAGE(I8:K8) -> 0.12134577 | N8: Research and development | T8: 27195 | U8: 29510 | V8: 32488 | W8: =W$5*$L8 -> 37589.731 | X8: =X$5*$L8 -> 40743.057 | Y8: =Y$5*$L8 -> 43622.763 | Z8: =Z$5*$L8 -> 46220.545 | AA8: =AA$5*$L8 -> 48539.645
B9: Sales and marketing | I9: =T9/$T$5 -> 0.10739683 | J9: =U9/$U$5 -> 0.099770726 | K9: =V9/$V$5 -> 0.091060754 | L9: =AVERAGE(I9:K9) -> 0.099409438 | N9: Sales and marketing | T9: 22759 | U9: 24456 | V9: 25654 | W9: =W$5*$L9 -> 30794.431 | X9: =X$5*$L9 -> 33377.712 | Y9: =Y$5*$L9 -> 35736.838 | Z9: =Z$5*$L9 -> 37865.005 | AA9: =AA$5*$L9 -> 39764.869
B10: General and administrative | I10: =T10/$T$5 -> 0.035745464 | J10: =U10/$U$5 -> 0.031041685 | K10: =V10/$V$5 -> 0.025638568 | L10: =AVERAGE(I10:K10) -> 0.030808573 | N10: General and administrative | T10: 7575 | U10: 7609 | V10: 7223 | W10: =W$5*$L10 -> 9543.6859 | X10: =X$5*$L10 -> 10344.286 | Y10: =Y$5*$L10 -> 11075.417 | Z10: =Z$5*$L10 -> 11734.97 | AA10: =AA$5*$L10 -> 12323.768
B11: Operating income | I11: =T11/$T$5 -> 0.41772881 | J11: =U11/$U$5 -> 0.446443 | K11: =V11/$V$5 -> 0.45621956 | L11: =AVERAGE(I11:K11) -> 0.44013045 | N11: Operating income | T11: =T7-SUM(T8:T10) -> 88523 | U11: =U7-SUM(U8:U10) -> 109433 | V11: =V7-SUM(V8:V10) -> 128528 | W11: =W7-SUM(W8:W10) -> 136340.85 | X11: =X7-SUM(X8:X10) -> 147778.2 | Y11: =Y7-SUM(Y8:Y10) -> 158223.11 | Z11: =Z7-SUM(Z8:Z10) -> 167645.47 | AA11: =AA7-SUM(AA8:AA10) -> 176057.02
B12: Other income (expense), net | I12: =T12/$T$5 -> 0.003718472 | J12: =U12/$U$5 -> -0.0067150235 | K12: =V12/$V$5 -> -0.017396459 | L12: =AVERAGE(I12:K12) -> -0.0067976702 | N12: Other income (expense), net | T12: 788 | U12: -1646 | V12: -4901 | W12: =W$5*$L12 -> -2105.7395 | X12: =X$5*$L12 -> -2282.3857 | Y12: =Y$5*$L12 -> -2443.704 | Z12: =Z$5*$L12 -> -2589.2291 | AA12: =AA$5*$L12 -> -2719.1429
B13: Income before income taxes | I13: =T13/$T$5 -> 0.42144728 | J13: =U13/$U$5 -> 0.43972797 | K13: =V13/$V$5 -> 0.4388231 | L13: =AVERAGE(I13:K13) -> 0.43333278 | N13: Income before income taxes | T13: =T11+T12 -> 89311 | U13: =U11+U12 -> 107787 | V13: =V11+V12 -> 123627 | W13: =W11+W12 -> 134235.11 | X13: =X11+X12 -> 145495.81 | Y13: =Y11+Y12 -> 155779.41 | Z13: =Z11+Z12 -> 165056.24 | AA13: =AA11+AA12 -> 173337.88
B14: Provision for income taxes | I14: =T14/$T$5 -> 0.0799849 | J14: =U14/$U$5 -> 0.080168243 | K14: =V14/$V$5 -> 0.077362951 | L14: =AVERAGE(I14:K14) -> 0.079172031 | N14: Provision for income taxes | T14: 16950 | U14: 19651 | V14: 21795 | W14: =W$5*$L14 -> 24525.414 | X14: =X$5*$L14 -> 26582.801 | Y14: =Y$5*$L14 -> 28461.664 | Z14: =Z$5*$L14 -> 30156.587 | AA14: =AA$5*$L14 -> 31669.684
B15: Net income | I15: =T15/$T$5 -> 0.34146238 | J15: =U15/$U$5 -> 0.35955973 | K15: =V15/$V$5 -> 0.36146015 | L15: =AVERAGE(I15:K15) -> 0.35416075 | N15: Net income | T15: =T13-T14 -> 72361 | U15: =U13-U14 -> 88136 | V15: =V13-V14 -> 101832 | W15: =W13-W14 -> 109709.69 | X15: =X13-X14 -> 118913.01 | Y15: =Y13-Y14 -> 127317.75 | Z15: =Z13-Z14 -> 134899.65 | AA15: =AA13-AA14 -> 141668.2
B20: BALANCE SHEETS % of Sales | J20: Jun. 30, 2024 | K20: Jun. 30, 2025 | N20: BALANCE SHEETS | T20: Jun. 30, 2023 | U20: Jun. 30, 2024 | V20: Jun. 30, 2025 | W20: Jun. 30, 2026 | X20: Jun. 30, 2027 | Y20: Jun. 30, 2028 | Z20: Jun. 30, 2029 | AA20: Jun. 30, 2030
B21: Current assets: | N21: Current assets:
B22: Cash and cash equivalents | I22: =T22/$U$5 -> 0.14157848 | J22: =U22/$U$5 -> 0.074717896 | K22: =V22/$V$5 -> 0.1073462 | L22: =AVERAGE(I22:K22) -> 0.10788086 | N22: Cash and cash equivalents | T22: 34704 | U22: 18315 | V22: 30242 | W22: =W$5*$L22 -> 33418.654 | X22: =X$5*$L22 -> 36222.076 | Y22: =Y$5*$L22 -> 38782.241 | Z22: =Z$5*$L22 -> 41091.764 | AA22: =AA$5*$L22 -> 43153.53
B23: Short-term investments | I23: =T23/$U$5 -> 0.31232611 | J23: =U23/$U$5 -> 0.23346742 | K23: =V23/$V$5 -> 0.22831921 | L23: =AVERAGE(I23:K23) -> 0.25803758 | N23: Short-term investments | T23: 76558 | U23: 57228 | V23: 64323 | W23: =W$5*$L23 -> 79933.258 | X23: =X$5*$L23 -> 86638.695 | Y23: =Y$5*$L23 -> 92762.29 | Z23: =Z$5*$L23 -> 98286.383 | AA23: =AA$5*$L23 -> 103217.87
B24: Total cash, cash equivalents, and short-term investments | I24: =T24/$U$5 -> 0.45390459 | J24: =U24/$U$5 -> 0.30818531 | K24: =V24/$V$5 -> 0.3356654 | L24: =AVERAGE(I24:K24) -> 0.36591843 | N24: Total cash, cash equivalents, and short-term investments | T24: =SUM(T22:T23) -> 111262 | U24: =SUM(U22:U23) -> 75543 | V24: =SUM(V22:V23) -> 94565 | W24: =SUM(W22:W23) -> 113351.91 | X24: =SUM(X22:X23) -> 122860.77 | Y24: =SUM(Y22:Y23) -> 131544.53 | Z24: =SUM(Z22:Z23) -> 139378.15 | AA24: =SUM(AA22:AA23) -> 146371.4
B25: Accounts receivable, net of allowance for doubtful accounts of $944 and $830 | I25: =T25/$U$5 -> 0.19862762 | J25: =U25/$U$5 -> 0.23222722 | K25: =V25/$V$5 -> 0.24813292 | L25: =AVERAGE(I25:K25) -> 0.22632925 | N25: Accounts receivable, net of allowance for doubtful accounts of $944 and $830 | T25: 48688 | U25: 56924 | V25: 69905 | W25: =W$5*$L25 -> 70110.854 | X25: =X$5*$L25 -> 75992.309 | Y25: =Y$5*$L25 -> 81363.421 | Z25: =Z$5*$L25 -> 86208.699 | AA25: =AA$5*$L25 -> 90534.192
B26: Inventories | I26: =T26/$U$5 -> 0.010199003 | J26: =U26/$U$5 -> 0.0050831831 | K26: =V26/$V$5 -> 0.0033294998 | L26: =AVERAGE(I26:K26) -> 0.0062038953 | N26: Inventories | T26: 2500 | U26: 1246 | V26: 938 | W26: =W$5*$L26 -> 1921.8037 | X26: =X$5*$L26 -> 2083.0198 | Y26: =Y$5*$L26 -> 2230.247 | Z26: =Z$5*$L26 -> 2363.0606 | AA26: =AA$5*$L26 -> 2481.6264
B27: Other current assets | I27: =T27/$U$5 -> 0.089004659 | J27: =U27/$U$5 -> 0.1061553 | K27: =V27/$V$5 -> 0.091305675 | L27: =AVERAGE(I27:K27) -> 0.095488545 | N27: Other current assets | T27: 21817 | U27: 26021 | V27: 25723 | W27: =W$5*$L27 -> 29579.841 | X27: =X$5*$L27 -> 32061.233 | Y27: =Y$5*$L27 -> 34327.311 | Z27: =Z$5*$L27 -> 36371.539 | AA27: =AA$5*$L27 -> 38196.469
B28: Total current assets | I28: =T28/$U$5 -> 0.75173587 | J28: =U28/$U$5 -> 0.65165101 | K28: =V28/$V$5 -> 0.6784335 | L28: =AVERAGE(I28:K28) -> 0.69394013 | N28: Total current assets | T28: =SUM(T24:T27) -> 184267 | U28: =SUM(U24:U27) -> 159734 | V28: =SUM(V24:V27) -> 191131 | W28: =SUM(W24:W27) -> 214964.41 | X28: =SUM(X24:X27) -> 232997.33 | Y28: =SUM(Y24:Y27) -> 249465.51 | Z28: =SUM(Z24:Z27) -> 264321.45 | AA28: =SUM(AA24:AA27) -> 277583.69
B29: Property and equipment, net of accumulated depreciation of $93,653 and $76,421 | I29: =T29/$U$5 -> 0.39017714 | J29: =U29/$U$5 -> 0.5531572 | K29: =V29/$V$5 -> 0.72754185 | L29: =AVERAGE(I29:K29) -> 0.55695873 | N29: Property and equipment, net of accumulated depreciation of $93,653 and $76,421 | T29: 95641 | U29: 135591 | V29: 204966 | W29: =W$5*$L29 -> 172531.17 | X29: =X$5*$L29 -> 187004.46 | Y29: =Y$5*$L29 -> 200221.87 | Z29: =Z$5*$L29 -> 212145.3 | AA29: =AA$5*$L29 -> 222789.62
B30: Depreciation | I30: =T30/$U$5 -> 0.044875613 | J30: =U30/$U$5 -> 0.062009938 | K30: =V30/$V$5 -> 0.078090614 | L30: =AVERAGE(I30:K30) -> 0.061658721 | N30: Depreciation | T30: 11000 | U30: 15200 | V30: 22000 | W30: =W$5*$L30 -> 19100.251 | X30: =X$5*$L30 -> 20702.532 | Y30: =Y$5*$L30 -> 22165.78 | Z30: =Z$5*$L30 -> 23485.776 | AA30: =AA$5*$L30 -> 24664.167
B31: Operating lease right-of-use assets | I31: =T31/$U$5 -> 0.058525959 | J31: =U31/$U$5 -> 0.077353318 | K31: =V31/$V$5 -> 0.088111059 | L31: =AVERAGE(I31:K31) -> 0.074663445 | N31: Operating lease right-of-use assets | T31: 14346 | U31: 18961 | V31: 24823 | W31: =W$5*$L31 -> 23128.773 | X31: =X$5*$L31 -> 25068.998 | Y31: =Y$5*$L31 -> 26840.867 | Z31: =Z$5*$L31 -> 28439.269 | AA31: =AA$5*$L31 -> 29866.2
B32: Equity and other investments | I32: =T32/$U$5 -> 0.04030238 | J32: =U32/$U$5 -> 0.059562177 | K32: =V32/$V$5 -> 0.054681177 | L32: =AVERAGE(I32:K32) -> 0.051515245 | N32: Equity and other investments | T32: 9879 | U32: 14600 | V32: 15405 | W32: =W$5*$L32 -> 15958.069 | X32: =X$5*$L32 -> 17296.758 | Y32: =Y$5*$L32 -> 18519.288 | Z32: =Z$5*$L32 -> 19622.131 | AA32: =AA$5*$L32 -> 20606.665
B33: Goodwill | I33: =T33/$U$5 -> 0.27694781 | J33: =U33/$U$5 -> 0.48637005 | K33: =V33/$V$5 -> 0.42420596 | L33: =AVERAGE(I33:K33) -> 0.39584127 | N33: Goodwill | T33: 67886 | U33: 119220 | V33: 119509 | W33: =W$5*$L33 -> 122621.22 | X33: =X$5*$L33 -> 132907.66 | Y33: =Y$5*$L33 -> 142301.53 | Z33: =Z$5*$L33 -> 150775.74 | AA33: =AA$5*$L33 -> 158340.86
B34: Intangible assets, net | I34: =T34/$U$5 -> 0.038209545 | J34: =U34/$U$5 -> 0.11258475 | K34: =V34/$V$5 -> 0.080234556 | L34: =AVERAGE(I34:K34) -> 0.077009618 | N34: Intangible assets, net | T34: 9366 | U34: 27597 | V34: 22604 | W34: =W$5*$L34 -> 23855.555 | X34: =X$5*$L34 -> 25856.749 | Y34: =Y$5*$L34 -> 27684.296 | Z34: =Z$5*$L34 -> 29332.925 | AA34: =AA$5*$L34 -> 30804.695
B35: Other long-term assets | I35: =T35/$U$5 -> 0.12483988 | J35: =U35/$U$5 -> 0.14874226 | K35: =V35/$V$5 -> 0.14398844 | L35: =AVERAGE(I35:K35) -> 0.13919019 | N35: Other long-term assets | T35: 30601 | U35: 36460 | V35: 40565 | W35: =W$5*$L35 -> 43117.463 | X35: =X$5*$L35 -> 46734.498 | Y35: =Y$5*$L35 -> 50037.677 | Z35: =Z$5*$L35 -> 53017.474 | AA35: =AA$5*$L35 -> 55677.608
B36: Total assets | I36: =T36/$U$5 -> 1.7256142 | J36: =U36/$U$5 -> 2.1514307 | K36: =V36/$V$5 -> 2.2752872 | L36: =AVERAGE(I36:K36) -> 2.0507774 | N36: Total assets | T36: =SUM(T28:T35) -> 422986 | U36: =SUM(U28:U35) -> 527363 | V36: =SUM(V28:V35) -> 641003 | W36: =SUM(W28:W35) -> 635276.92 | X36: =SUM(X28:X35) -> 688568.99 | Y36: =SUM(Y28:Y35) -> 737236.82 | Z36: =SUM(Z28:Z35) -> 781140.06 | AA36: =SUM(AA28:AA35) -> 820333.51
B37: Current liabilities: | N37: Current liabilities:
B38: Accounts payable | I38: =T38/$U$5 -> 0.073820383 | J38: =U38/$U$5 -> 0.089734908 | K38: =V38/$V$5 -> 0.098408371 | L38: =AVERAGE(I38:K38) -> 0.087321221 | N38: Accounts payable | T38: 18095 | U38: 21996 | V38: 27724 | W38: =W$5*$L38 -> 27049.819 | X38: =X$5*$L38 -> 29318.973 | Y38: =Y$5*$L38 -> 31391.228 | Z38: =Z$5*$L38 -> 33260.609 | AA38: =AA$5*$L38 -> 34929.449
B39: Short-term debt | I39: =T39/$U$5 -> 0 | J39: =U39/$U$5 -> 0.027304771 | K39: =V39/$V$5 -> 0 | L39: =AVERAGE(I39:K39) -> 0.0091015902 | N39: Short-term debt | T39: 0 | U39: 6693 | V39: 0 | W39: =W$5*$L39 -> 2819.4334 | X39: =X$5*$L39 -> 3055.9499 | Y39: =Y$5*$L39 -> 3271.9434 | Z39: =Z$5*$L39 -> 3466.7911 | AA39: =AA$5*$L39 -> 3640.7362
B40: Current portion of long-term debt | I40: =T40/$U$5 -> 0.021405667 | J40: =U40/$U$5 -> 0.009175023 | K40: =V40/$V$5 -> 0.01064517 | L40: =AVERAGE(I40:K40) -> 0.013741954 | N40: Current portion of long-term debt | T40: 5247 | U40: 2249 | V40: 2999 | W40: =W$5*$L40 -> 4256.896 | X40: =X$5*$L40 -> 4613.9983 | Y40: =Y$5*$L40 -> 4940.1142 | Z40: =Z$5*$L40 -> 5234.3032 | AA40: =AA$5*$L40 -> 5496.9327
B41: Accrued compensation | I41: =T41/$U$5 -> 0.044912329 | J41: =U41/$U$5 -> 0.051256109 | K41: =V41/$V$5 -> 0.048661101 | L41: =AVERAGE(I41:K41) -> 0.048276513 | N41: Accrued compensation | T41: 11009 | U41: 12564 | V41: 13709 | W41: =W$5*$L41 -> 14954.795 | X41: =X$5*$L41 -> 16209.322 | Y41: =Y$5*$L41 -> 17354.991 | Z41: =Z$5*$L41 -> 18388.5 | AA41: =AA$5*$L41 -> 19311.136
B42: Short-term income taxes | I42: =T42/$U$5 -> 0.016938504 | J42: =U42/$U$5 -> 0.020467359 | K42: =V42/$V$5 -> 0.025595973 | L42: =AVERAGE(I42:K42) -> 0.021000612 | N42: Short-term income taxes | T42: 4152 | U42: 5017 | V42: 7211 | W42: =W$5*$L42 -> 6505.4376 | X42: =X$5*$L42 -> 7051.1654 | Y42: =Y$5*$L42 -> 7549.5395 | Z42: =Z$5*$L42 -> 7999.1226 | AA42: =AA$5*$L42 -> 8400.4759
B43: Short-term unearned revenue | I43: =T43/$U$5 -> 0.20765578 | J43: =U43/$U$5 -> 0.2349116 | K43: =V43/$V$5 -> 0.22914271 | L43: =AVERAGE(I43:K43) -> 0.22390336 | N43: Short-term unearned revenue | T43: 50901 | U43: 57582 | V43: 64555 | W43: =W$5*$L43 -> 69359.375 | X43: =X$5*$L43 -> 75177.791 | Y43: =Y$5*$L43 -> 80491.333 | Z43: =Z$5*$L43 -> 85284.677 | AA43: =AA$5*$L43 -> 89563.808
B44: Other current liabilities | I44: =T44/$U$5 -> 0.060153719 | J44: =U44/$U$5 -> 0.078267149 | K44: =V44/$V$5 -> 0.088810325 | L44: =AVERAGE(I44:K44) -> 0.075743731 | N44: Other current liabilities | T44: 14745 | U44: 19185 | V44: 25020 | W44: =W$5*$L44 -> 23463.417 | X44: =X$5*$L44 -> 25431.715 | Y44: =Y$5*$L44 -> 27229.22 | Z44: =Z$5*$L44 -> 28850.749 | AA44: =AA$5*$L44 -> 30298.326
B45: Total current liabilities | I45: =T45/$U$5 -> 0.42488638 | J45: =U45/$U$5 -> 0.51111691 | K45: =V45/$V$5 -> 0.50126365 | L45: =AVERAGE(I45:K45) -> 0.47908898 | N45: Total current liabilities | T45: =SUM(T38:T44) -> 104149 | U45: =SUM(U38:U44) -> 125286 | V45: =SUM(V38:V44) -> 141218 | W45: =SUM(W38:W44) -> 148409.17 | X45: =SUM(X38:X44) -> 160858.91 | Y45: =SUM(Y38:Y44) -> 172228.37 | Z45: =SUM(Z38:Z44) -> 182484.75 | AA45: =SUM(AA38:AA44) -> 191640.86
B46: Long-term debt | I46: =T46/$U$5 -> 0.17130245 | J46: =U46/$U$5 -> 0.17415002 | K46: =V46/$V$5 -> 0.14252247 | L46: =AVERAGE(I46:K46) -> 0.16265831 | N46: Long-term debt | T46: 41990 | U46: 42688 | V46: 40152 | W46: =W$5*$L46 -> 50387.269 | X46: =X$5*$L46 -> 54614.154 | Y46: =Y$5*$L46 -> 58474.265 | Z46: =Z$5*$L46 -> 61956.469 | AA46: =AA$5*$L46 -> 65065.115
B47: Long-term income taxes | I47: =T47/$U$5 -> 0.10427461 | J47: =U47/$U$5 -> 0.11394734 | K47: =V47/$V$5 -> 0.092239213 | L47: =AVERAGE(I47:K47) -> 0.10348705 | N47: Long-term income taxes | T47: 25560 | U47: 27931 | V47: 25986 | W47: =W$5*$L47 -> 32057.569 | X47: =X$5*$L47 -> 34746.812 | Y47: =Y$5*$L47 -> 37202.706 | Z47: =Z$5*$L47 -> 39418.166 | AA47: =AA$5*$L47 -> 41395.96
B48: Long-term unearned revenue | I48: =T48/$U$5 -> 0.011879799 | J48: =U48/$U$5 -> 0.010615122 | K48: =V48/$V$5 -> 0.0096193438 | L48: =AVERAGE(I48:K48) -> 0.010704755 | N48: Long-term unearned revenue | T48: 2912 | U48: 2602 | V48: 2710 | W48: =W$5*$L48 -> 3316.0517 | X48: =X$5*$L48 -> 3594.2284 | Y48: =Y$5*$L48 -> 3848.2673 | Z48: =Z$5*$L48 -> 4077.4358 | AA48: =AA$5*$L48 -> 4282.0197
B49: Deferred income taxes | I49: =T49/$U$5 -> 0.0017664673 | J49: =U49/$U$5 -> 0.010680396 | K49: =V49/$V$5 -> 0.01006304 | L49: =AVERAGE(I49:K49) -> 0.0075033012 | N49: Deferred income taxes | T49: 433 | U49: 2618 | V49: 2835 | W49: =W$5*$L49 -> 2324.3255 | X49: =X$5*$L49 -> 2519.3084 | Y49: =Y$5*$L49 -> 2697.3723 | Z49: =Z$5*$L49 -> 2858.0037 | AA49: =AA$5*$L49 -> 3001.403
B50: Operating lease liabilities | I50: =T50/$U$5 -> 0.051925164 | J50: =U50/$U$5 -> 0.063221579 | K50: =V50/$V$5 -> 0.06189391 | L50: =AVERAGE(I50:K50) -> 0.059013551 | N50: Operating lease liabilities | T50: 12728 | U50: 15497 | V50: 17437 | W50: =W$5*$L50 -> 18280.847 | X50: =X$5*$L50 -> 19814.39 | Y50: =Y$5*$L50 -> 21214.864 | Z50: =Z$5*$L50 -> 22478.232 | AA50: =AA$5*$L50 -> 23606.07
